Workbook

Sheet Summary
B1: ORBITAL DATA COMPUTE — INTEGRATED MODEL
B2: Self-initiated work sample · J. Shapiro · inputs tagged [FACT]/[EST]/[REVEAL]/[TGT]/[SPX-IN] · shared inputs on the Global Assumptions tab
B4: ANALYSIS 1 — Orbital vs. Terrestrial unit economics (1 GW)
B5: Orbital build cost | C5: ='A1 Orbital'!C26 -> 81.39726
B6: Terrestrial build cost | C6: ='A1 Terrestrial'!C19 -> 38
B7: Orbital premium — per watt | C7: ='A1 Orbital'!C26/'A1 Terrestrial'!C19 -> 2.1420332
B8: Cost per effective PFLOP-hr — inference | C8: ='A1 EffCompute'!E15 -> 2.1623587
B9: Cost per effective PFLOP-hr — training | C9: ='A1 EffCompute'!D15 -> 4.8653071 | E9: networking tax
B11: ANALYSIS 2 — Bastrop insource vs. outsource
B12: Net NPV of insourcing (7 yr) | C12: ='A2 BuildVsBuy'!C22 -> 933946.48 | E12: illustrative inputs
B13: Mature in-house unit cost | C13: ='A2 BuildVsBuy'!C23 -> 1.9646292
B15: ANALYSIS 3 — AI-Sat production ramp
B16: Cumulative power to orbit (final yr) | C16: ='A3 Ramp'!C25 -> 1.158176
B17: Cumulative capex (final yr) | C17: ='A3 Ramp'!C26 -> 23538.203
B18: Cost per satellite (final yr) | C18: ='A3 Ramp'!C27 -> 0.59944211 | E18: 85% learning curve
B20: RADIATOR THERMAL TAX
B21: Implied radiator temperature | C21: ='RAD Model'!C14 -> 347.14975
B22: Margin to silicon throttle | C22: ='RAD Model'!C15 -> 10.850254 | E22: headroom
B23: Radiator mass (1 GW) | C23: ='A1 Orbital'!C13/1000 -> 5000
B25: HEADLINE: orbital AI compute is ~2x terrestrial for inference and ~5x for training — a launch-cost option and an inference play, not general compute. The split is set by interconnect bandwidth (1 Tbps laser vs ~1,040 Tbps NVLink), not dollars.

Sheet Global Assumptions
B1: GLOBAL ASSUMPTIONS — single source of truth
B2: Shared inputs live here only. Each analysis links to these cells (green font), so changing a value here updates every model — no drift.
B3: Parameter | C3: Value | D3: Unit | E3: Tag | F3: Used by
B5: FINANCIAL
B6: Discount rate (WACC) | C6: 0.12 | D6: %/yr | E6: [SPX-IN] | F6: A1, A2
B7: Launch cost to LEO | C7: 1000 | D7: $/kg | E7: [TGT] | F7: A1, A3, Radiator
B8: Target cluster power | C8: 1000 | D8: MW | E8: [EST] | F8: A1, Radiator
B10: AI1 REFERENCE SPECS (June 8 2026 reveal / S-1)
B11: Compute payload (avg) | C11: 120 | D11: kW/sat | E11: [REVEAL] | F11: A3
B12: Specific power | C12: 70 | D12: kW/ton | E12: [REVEAL] | F12: A3
B13: Radiator flux (double-sided) | C13: 1400 | D13: W/m2 | E13: [REVEAL] | F13: A1, Radiator
B15: NOTE: A1 cost model uses a CONSERVATIVE 36.5 W/kg specific-power base (not the AI1 70 kW/ton above) and stresses 70 as the bull case — deliberate; see A1 Inputs C12.

Sheet A1 Inputs
B2: INPUTS & ASSUMPTIONS
B3: Blue = input you can change · Yellow = most needs a real SpaceX number · tags: [FACT]/[EST]/[REVEAL]/[TGT]/[SPX-IN]
B4: SCOPE NOTE: both builds are ALL-IN (include power generation).
B5: TARGET SYSTEM
B6: Target cluster power (deployed compute) | C6: ='Global Assumptions'!$C$8 -> 1000 | D6: MW | E6: [EST] | F6: Sized to 1 GW to match published comparison models (McCalip, Epoch AI)
B7: Analysis period | C7: 10 | D7: years | E7: [EST] | F7: Standard infra horizon
B8: Discount rate (WACC) | C8: ='Global Assumptions'!$C$6 -> 0.12 | D8: %/yr | E8: [SPX-IN] | F8: Placeholder; use SpaceX cost of capital
B10: LAUNCH ECONOMICS (the master variable)
B11: Launch cost to LEO | C11: ='Global Assumptions'!$C$7 -> 1000 | D11: $/kg | E11: [TGT] | F11: Starship TARGET; not yet demonstrated. Falcon 9 rideshare = $7,000/kg (Feb 2026). McCalip baseline $1,000/kg.
B12: System specific power | C12: 36.5 | D12: W/kg | E12: [EST] | F12: BASE CASE conservative 36.5 W/kg = power+bus+structure EXCLUDING compute-rejection radiators (McCalip heritage basis). Radiators are added separately on tab 2 to CORRECT that omission — no overlap. AI1 reveal claims 70 kW/ton [REVEAL] = bull upside; stressed in tab 5.
B14: SPACE HARDWARE & POWER
B15: Compute accelerator cost | C15: =25*1.4 -> 35 | D15: $/W | E15: [EST] | F15: GB300-class ~$25/W on a hardware-COST basis (not Nvidia retail ~$54/W, which embeds vendor margin SpaceX insources around) x 1.4 space-grade premium.
B16: Power system (solar+PMAD) | C16: 8 | D16: $/W | E16: [EST] | F16: Space solar array + power mgmt/distribution per watt; order-of-magnitude
B17: Bus, structure, integration | C17: 6 | D17: $/W | E17: [EST] | F17: Satellite bus, structure, harness, assembly/test per watt
B19: Compute + bus hardware cost (built up) | C19: =SUM(C15:C17) -> 49 | D19: $/W | E19: [EST] | F19: Independent build-up (compute + power + bus). Ratio to terrestrial falls out; NOT calibrated to a target.
B20: Solar cell degradation | C20: 0.025
B21: GPU annual failure rate | C21: 0.09 | D21: %/yr | E21: [EST] | F21: Meta Llama-3 fleet figure (9%/yr) [EST]; no on-orbit repair. Space radiation may push this higher — which only strengthens the case (more re-launch).
B22: Orbital ops & ground network | C22: 0.01 | D22: %capex/yr | E22: [SPX-IN] | F22: Illustrative annual O&M as % of hardware capex
B24: THERMAL (radiative cooling only — vacuum)
B25: Radiator heat rejection | C25: ='Global Assumptions'!$C$13 -> 1400 | D25: W/m2 | E25: [REVEAL] | F25: AI1 reveal: double-sided radiators 1,400 W/m2
B26: Radiator areal mass | C26: 7 | D26: kg/m2 | E26: [EST] | F26: ISS ~2.7 kg/m2; modern deployable 5-10 kg/m2; midpoint 7
B28: TERRESTRIAL BENCHMARK
B29: All-in build capex | C29: 38000 | D29: $/kW | E29: [EST] | F29: Epoch AI 1 GW ALL-IN incl on-site power generation = $38/W. (McCalip infra-only = ~$15/W; we use all-in to match orbital scope, which includes its own solar power.)
B30: IT (GPU) refresh life | C30: 5 | D30: years | E30: [EST] | F30: Epoch AI base case
B31: Facility / shell life | C31: 14 | D31: years | E31: [EST] | F31: Epoch AI base case
B32: IT share of capex | C32: 0.6 | D32: % | E32: [EST] | F32: Epoch AI: servers ~60% of cost
B33: Electricity price | C33: 0.0834
B34: PUE (power usage effectiveness) | C34: 1.15 | D34: x | E34: [EST] | F34: Modern AI DC ~1.1-1.2
B35: Non-power opex | C35: 0.02 | D35: %capex/yr | E35: [EST] | F35: Maintenance/staff/network
B37: EFFECTIVE COMPUTE (utilization)
B38: Accelerator compute density | C38: 1.45 | D38: PFLOP/kW | E38: [FACT] | F38: ~H100 FP16-dense reference (989 TFLOP / 700W ~ 1.4 PFLOP/kW). FP8 dense is ~1,979 TFLOP; figure cancels in the orbital/terrestrial ratio, used only for the effective-PFLOP denominator.
B39: MFU — terrestrial training | C39: 0.45 | D39: % | E39: [FACT] | F39: PaLM 46%, Llama-3 38-43%, MegaScale 55%
B40: MFU — orbital training | C40: 0.2 | D40: % | E40: [SPX-IN] | F40: Lower: ISL bandwidth ~1 Tbps vs ~1,040 Tbps intra-rack NVLink
B41: MFU — orbital inference | C41: 0.45 | D41: % | E41: [SPX-IN] | F41: Comparable to terrestrial for batch inference w/ preloaded weights
B44: J. Shapiro · Prepared as an independent work sample · all figures public-sourced or labeled illustrative

Sheet A1 Orbital
B2: ORBITAL CLUSTER — BOTTOMS-UP $/W
B4: Target power | C4: ='A1 Inputs'!$C$6*1000 -> 1000000 | D4: kW | F4: MW -> kW
B5: System mass to orbit | C5: =C4*1000/'A1 Inputs'!$C$12 -> 27397260 | D5: kg | F5: power / specific power
B6: Mass to orbit, incl. radiator (t) | C6: =(C5+C13)/1000 -> 32397.26 | D6: t
B7: Starship launches @150t (incl. radiator) | C7: =(C5+C13)/1000/150 -> 215.98174 | D7: launches
B9: Launch cost | C9: =C5*'A1 Inputs'!$C$11 -> 2.739726e+10 | D9: $ | F9: mass x $/kg
B10: Compute + bus hardware | C10: =C4*1000*'A1 Inputs'!$C$19 -> 49000000000 | D10: $ | F10: W x $/W
B11: Heat to reject (~= compute power) | C11: =C4 -> 1000000 | D11: kW | F11: assume ~100% of electrical power -> heat
B12: Radiator area | C12: =C11*1000/'A1 Inputs'!$C$25 -> 714285.71 | D12: m2 | F12: heat W / (W/m2)
B13: Radiator mass | C13: =C12*'A1 Inputs'!$C$26 -> 5000000 | D13: kg
B14: Radiator launch cost (incremental) | C14: =C13*'A1 Inputs'!$C$11 -> 5000000000 | D14: $ | F14: thermal mass tax McCalip omits
B16: Total upfront capex | C16: =C9+C10+C14 -> 8.139726e+10 | D16: $
B18: Capital recovery factor | C18: ='A1 Inputs'!$C$8*(1+'A1 Inputs'!$C$8)^'A1 Inputs'!$C$7/((1+'A1 Inputs'!$C$8)^'A1 Inputs'!$C$7-1) -> 0.17698416 | D18: x | F18: CRF over analysis period
B19: Annualized capex | C19: =C16*C18 -> 1.4406026e+10 | D19: $/yr
B20: GPU failure replacement | C20: =C10*'A1 Inputs'!$C$21 -> 4410000000 | D20: $/yr | F20: no repair; amortized replacement
B21: GPU replacement launch cost | C21: =C5*'A1 Inputs'!$C$21*'A1 Inputs'!$C$11 -> 2.4657534e+09 | D21: $/yr | F21: No on-orbit repair: replacement GPUs must be re-launched. Mass x failure rate x launch $/kg. Worsens orbital case (correct direction).
B22: Ops & ground network | C22: =C16*'A1 Inputs'!$C$22 -> 8.139726e+08 | D22: $/yr
B24: Total annual cost | C24: =C19+C20+C21+C22 -> 2.2095752e+10 | D24: $/yr
B26: Cost per watt (upfront capex) | C26: =C16/(C4*1000) -> 81.39726 | D26: $/W
B27: Solar availability derate (avg over life) | C27: =(1+(1-'A1 Inputs'!$C$20)^'A1 Inputs'!$C$7)/2 -> 0.88816481 | D27: x | F27: Average solar power availability over life given degradation; derates delivered MW.
B28: Cost per MW-year (annualized) | C28: =C24/('A1 Inputs'!$C$6*C27) -> 24877986 | D28: $/MW-yr
B31: J. Shapiro · Prepared as an independent work sample · all figures public-sourced or labeled illustrative

Sheet A1 Terrestrial
B2: TERRESTRIAL AI DATA CENTER — BOTTOMS-UP $/W
B4: Target power | C4: ='A1 Inputs'!$C$6*1000 -> 1000000 | D4: kW
B5: Total build capex | C5: =C4*'A1 Inputs'!$C$29 -> 38000000000 | D5: $ | F5: kW x $/kW
B6: of which IT (GPU) capex | C6: =C5*'A1 Inputs'!$C$32 -> 22800000000 | D6: $
B7: of which facility capex | C7: =C5-C6 -> 15200000000 | D7: $
B9: CRF — IT (refresh life) | C9: ='A1 Inputs'!$C$8*(1+'A1 Inputs'!$C$8)^'A1 Inputs'!$C$30/((1+'A1 Inputs'!$C$8)^'A1 Inputs'!$C$30-1) -> 0.27740973 | D9: x
B10: CRF — facility life | C10: ='A1 Inputs'!$C$8*(1+'A1 Inputs'!$C$8)^'A1 Inputs'!$C$31/((1+'A1 Inputs'!$C$8)^'A1 Inputs'!$C$31-1) -> 0.15087125 | D10: x
B11: Annualized IT capex | C11: =C6*C9 -> 6.3249419e+09 | D11: $/yr
B12: Annualized facility capex | C12: =C7*C10 -> 2.2932429e+09 | D12: $/yr
B14: Annual electricity (incl PUE) | C14: =C4*'A1 Inputs'!$C$34*8760*'A1 Inputs'!$C$33 -> 840171600 | D14: $/yr | F14: kW x PUE x hrs x $/kWh
B15: Non-power opex | C15: =C5*'A1 Inputs'!$C$35 -> 760000000 | D15: $/yr
B17: Total annual cost | C17: =C11+C12+C14+C15 -> 1.0218356e+10 | D17: $/yr
B19: Cost per watt (upfront capex) | C19: =C5/(C4*1000) -> 38 | D19: $/W
B20: Cost per MW-year (annualized) | C20: =C17/'A1 Inputs'!$C$6 -> 10218356 | D20: $/MW-yr
B23: J. Shapiro · Prepared as an independent work sample · all figures public-sourced or labeled illustrative

Sheet A1 EffCompute
B2: COST PER EFFECTIVE PFLOP-HOUR (apples-to-apples)
B3: Peak FLOPS is misleading; only the MODEL FLOPS UTILIZATION fraction is usable. Networking sets the ceiling.
C5: Terrestrial | D5: Orbital (train) | E5: Orbital (infer)
B6: Annual system cost ($/yr) | C6: ='A1 Terrestrial'!C17 -> 1.0218356e+10 | D6: ='A1 Orbital'!C24 -> 2.2095752e+10 | E6: ='A1 Orbital'!C24 -> 2.2095752e+10 | G6: from build tabs
B7: Deployed power (MW) | C7: ='A1 Inputs'!$C$6 -> 1000 | D7: ='A1 Inputs'!$C$6 -> 1000 | E7: ='A1 Inputs'!$C$6 -> 1000 | G7: nameplate
B8: Peak compute (PFLOP) | C8: =C7*1000*'A1 Inputs'!$C$38 -> 1450000 | D8: =D7*1000*'A1 Inputs'!$C$38 -> 1450000 | E8: =E7*1000*'A1 Inputs'!$C$38 -> 1450000 | G8: MW x 1000 x PFLOP/kW
B9: MFU (usable fraction) | C9: ='A1 Inputs'!$C$39 -> 0.45 | D9: ='A1 Inputs'!$C$40 -> 0.2 | E9: ='A1 Inputs'!$C$41 -> 0.45 | G9: utilization haircut
B10: Effective compute (PFLOP) | C10: =C8*C9 -> 652500 | D10: =D8*D9 -> 290000 | E10: =E8*E9 -> 652500
B11: Effective PFLOP-hours / yr | C11: =C10*8760 -> 5715900000 | D11: =D10*8760 -> 2540400000 | E11: =E10*8760 -> 5715900000
B13: COST PER EFFECTIVE PFLOP-HOUR | C13: =C6/C11 -> 1.7877073 | D13: =D6/D11 -> 8.6977453 | E13: =E6/E11 -> 3.8656646
B15: Orbital premium vs terrestrial | C15: ="--" -> -- | D15: =D13/C13 -> 4.8653071 | E15: =E13/C13 -> 2.1623587
B18: THE NETWORKING TAX (why inference, not training)
B19: Intra-rack NVLink-5 fabric (GB300 NVL72): ~130 TB/s aggregate = ~1,040 Tbps [FACT, NVIDIA]
B20: AI1 inter-satellite laser link: ~1 Tbps [REVEAL, Jun 8 2026] -> ~1,000x below intra-rack bandwidth
B21: Even Google Suncatcher's 10 Tbps DWDM target ~ a single GPU's NVLink budget (14.4 Tbps).
B22: Consequence: tensor-parallel TRAINING needs NVLink-class bandwidth orbit cannot supply -> low orbital-train MFU.
B23: Batch INFERENCE with preloaded weights is embarrassingly parallel -> orbital MFU ~ terrestrial. This is the
B24: workload SpaceX's S-1 names ('energy-intensive AI workloads, such as inference demand').
B27: J. Shapiro · Prepared as an independent work sample · all figures public-sourced or labeled illustrative

Sheet A1 Sensitivity
B2: CROSSOVER ANALYSIS — Orbital $/W ÷ Terrestrial $/W
B3: Values < 1.0x (green) = orbital cheaper. The model recomputes orbital $/W for each launch-cost / specific-power pair.
B5: Terrestrial $/W (constant): | D5: ='A1 Terrestrial'!C19 -> 38
B7: Launch $/kg \ Specific power (W/kg) -> | C7: 50 | D7: 70 | E7: 100 | F7: 150 | G7: 250 | H7: 400 | I7: 700
B8: 100 | C8: =(100/50 + 'A1 Inputs'!$C$19 + ('A1 Inputs'!$C$26/'A1 Inputs'!$C$25)*100) / $D$5 -> 1.3552632 | D8: =(100/70 + 'A1 Inputs'!$C$19 + ('A1 Inputs'!$C$26/'A1 Inputs'!$C$25)*100) / $D$5 -> 1.3402256 | E8: =(100/100 + 'A1 Inputs'!$C$19 + ('A1 Inputs'!$C$26/'A1 Inputs'!$C$25)*100) / $D$5 -> 1.3289474 | F8: =(100/150 + 'A1 Inputs'!$C$19 + ('A1 Inputs'!$C$26/'A1 Inputs'!$C$25)*100) / $D$5 -> 1.3201754 | G8: =(100/250 + 'A1 Inputs'!$C$19 + ('A1 Inputs'!$C$26/'A1 Inputs'!$C$25)*100) / $D$5 -> 1.3131579 | H8: =(100/400 + 'A1 Inputs'!$C$19 + ('A1 Inputs'!$C$26/'A1 Inputs'!$C$25)*100) / $D$5 -> 1.3092105 | I8: =(100/700 + 'A1 Inputs'!$C$19 + ('A1 Inputs'!$C$26/'A1 Inputs'!$C$25)*100) / $D$5 -> 1.306391
B9: 200 | C9: =(200/50 + 'A1 Inputs'!$C$19 + ('A1 Inputs'!$C$26/'A1 Inputs'!$C$25)*200) / $D$5 -> 1.4210526 | D9: =(200/70 + 'A1 Inputs'!$C$19 + ('A1 Inputs'!$C$26/'A1 Inputs'!$C$25)*200) / $D$5 -> 1.3909774 | E9: =(200/100 + 'A1 Inputs'!$C$19 + ('A1 Inputs'!$C$26/'A1 Inputs'!$C$25)*200) / $D$5 -> 1.3684211 | F9: =(200/150 + 'A1 Inputs'!$C$19 + ('A1 Inputs'!$C$26/'A1 Inputs'!$C$25)*200) / $D$5 -> 1.3508772 | G9: =(200/250 + 'A1 Inputs'!$C$19 + ('A1 Inputs'!$C$26/'A1 Inputs'!$C$25)*200) / $D$5 -> 1.3368421 | H9: =(200/400 + 'A1 Inputs'!$C$19 + ('A1 Inputs'!$C$26/'A1 Inputs'!$C$25)*200) / $D$5 -> 1.3289474 | I9: =(200/700 + 'A1 Inputs'!$C$19 + ('A1 Inputs'!$C$26/'A1 Inputs'!$C$25)*200) / $D$5 -> 1.3233083
B10: 300 | C10: =(300/50 + 'A1 Inputs'!$C$19 + ('A1 Inputs'!$C$26/'A1 Inputs'!$C$25)*300) / $D$5 -> 1.4868421 | D10: =(300/70 + 'A1 Inputs'!$C$19 + ('A1 Inputs'!$C$26/'A1 Inputs'!$C$25)*300) / $D$5 -> 1.4417293 | E10: =(300/100 + 'A1 Inputs'!$C$19 + ('A1 Inputs'!$C$26/'A1 Inputs'!$C$25)*300) / $D$5 -> 1.4078947 | F10: =(300/150 + 'A1 Inputs'!$C$19 + ('A1 Inputs'!$C$26/'A1 Inputs'!$C$25)*300) / $D$5 -> 1.3815789 | G10: =(300/250 + 'A1 Inputs'!$C$19 + ('A1 Inputs'!$C$26/'A1 Inputs'!$C$25)*300) / $D$5 -> 1.3605263 | H10: =(300/400 + 'A1 Inputs'!$C$19 + ('A1 Inputs'!$C$26/'A1 Inputs'!$C$25)*300) / $D$5 -> 1.3486842 | I10: =(300/700 + 'A1 Inputs'!$C$19 + ('A1 Inputs'!$C$26/'A1 Inputs'!$C$25)*300) / $D$5 -> 1.3402256
B11: 500 | C11: =(500/50 + 'A1 Inputs'!$C$19 + ('A1 Inputs'!$C$26/'A1 Inputs'!$C$25)*500) / $D$5 -> 1.6184211 | D11: =(500/70 + 'A1 Inputs'!$C$19 + ('A1 Inputs'!$C$26/'A1 Inputs'!$C$25)*500) / $D$5 -> 1.5432331 | E11: =(500/100 + 'A1 Inputs'!$C$19 + ('A1 Inputs'!$C$26/'A1 Inputs'!$C$25)*500) / $D$5 -> 1.4868421 | F11: =(500/150 + 'A1 Inputs'!$C$19 + ('A1 Inputs'!$C$26/'A1 Inputs'!$C$25)*500) / $D$5 -> 1.4429825 | G11: =(500/250 + 'A1 Inputs'!$C$19 + ('A1 Inputs'!$C$26/'A1 Inputs'!$C$25)*500) / $D$5 -> 1.4078947 | H11: =(500/400 + 'A1 Inputs'!$C$19 + ('A1 Inputs'!$C$26/'A1 Inputs'!$C$25)*500) / $D$5 -> 1.3881579 | I11: =(500/700 + 'A1 Inputs'!$C$19 + ('A1 Inputs'!$C$26/'A1 Inputs'!$C$25)*500) / $D$5 -> 1.3740602
B12: 1000 | C12: =(1000/50 + 'A1 Inputs'!$C$19 + ('A1 Inputs'!$C$26/'A1 Inputs'!$C$25)*1000) / $D$5 -> 1.9473684 | D12: =(1000/70 + 'A1 Inputs'!$C$19 + ('A1 Inputs'!$C$26/'A1 Inputs'!$C$25)*1000) / $D$5 -> 1.7969925 | E12: =(1000/100 + 'A1 Inputs'!$C$19 + ('A1 Inputs'!$C$26/'A1 Inputs'!$C$25)*1000) / $D$5 -> 1.6842105 | F12: =(1000/150 + 'A1 Inputs'!$C$19 + ('A1 Inputs'!$C$26/'A1 Inputs'!$C$25)*1000) / $D$5 -> 1.5964912 | G12: =(1000/250 + 'A1 Inputs'!$C$19 + ('A1 Inputs'!$C$26/'A1 Inputs'!$C$25)*1000) / $D$5 -> 1.5263158 | H12: =(1000/400 + 'A1 Inputs'!$C$19 + ('A1 Inputs'!$C$26/'A1 Inputs'!$C$25)*1000) / $D$5 -> 1.4868421 | I12: =(1000/700 + 'A1 Inputs'!$C$19 + ('A1 Inputs'!$C$26/'A1 Inputs'!$C$25)*1000) / $D$5 -> 1.4586466
B13: 2000 | C13: =(2000/50 + 'A1 Inputs'!$C$19 + ('A1 Inputs'!$C$26/'A1 Inputs'!$C$25)*2000) / $D$5 -> 2.6052632 | D13: =(2000/70 + 'A1 Inputs'!$C$19 + ('A1 Inputs'!$C$26/'A1 Inputs'!$C$25)*2000) / $D$5 -> 2.3045113 | E13: =(2000/100 + 'A1 Inputs'!$C$19 + ('A1 Inputs'!$C$26/'A1 Inputs'!$C$25)*2000) / $D$5 -> 2.0789474 | F13: =(2000/150 + 'A1 Inputs'!$C$19 + ('A1 Inputs'!$C$26/'A1 Inputs'!$C$25)*2000) / $D$5 -> 1.9035088 | G13: =(2000/250 + 'A1 Inputs'!$C$19 + ('A1 Inputs'!$C$26/'A1 Inputs'!$C$25)*2000) / $D$5 -> 1.7631579 | H13: =(2000/400 + 'A1 Inputs'!$C$19 + ('A1 Inputs'!$C$26/'A1 Inputs'!$C$25)*2000) / $D$5 -> 1.6842105 | I13: =(2000/700 + 'A1 Inputs'!$C$19 + ('A1 Inputs'!$C$26/'A1 Inputs'!$C$25)*2000) / $D$5 -> 1.6278195
B14: 5000 | C14: =(5000/50 + 'A1 Inputs'!$C$19 + ('A1 Inputs'!$C$26/'A1 Inputs'!$C$25)*5000) / $D$5 -> 4.5789474 | D14: =(5000/70 + 'A1 Inputs'!$C$19 + ('A1 Inputs'!$C$26/'A1 Inputs'!$C$25)*5000) / $D$5 -> 3.8270677 | E14: =(5000/100 + 'A1 Inputs'!$C$19 + ('A1 Inputs'!$C$26/'A1 Inputs'!$C$25)*5000) / $D$5 -> 3.2631579 | F14: =(5000/150 + 'A1 Inputs'!$C$19 + ('A1 Inputs'!$C$26/'A1 Inputs'!$C$25)*5000) / $D$5 -> 2.8245614 | G14: =(5000/250 + 'A1 Inputs'!$C$19 + ('A1 Inputs'!$C$26/'A1 Inputs'!$C$25)*5000) / $D$5 -> 2.4736842 | H14: =(5000/400 + 'A1 Inputs'!$C$19 + ('A1 Inputs'!$C$26/'A1 Inputs'!$C$25)*5000) / $D$5 -> 2.2763158 | I14: =(5000/700 + 'A1 Inputs'!$C$19 + ('A1 Inputs'!$C$26/'A1 Inputs'!$C$25)*5000) / $D$5 -> 2.1353383
B15: 7000 | C15: =(7000/50 + 'A1 Inputs'!$C$19 + ('A1 Inputs'!$C$26/'A1 Inputs'!$C$25)*7000) / $D$5 -> 5.8947368 | D15: =(7000/70 + 'A1 Inputs'!$C$19 + ('A1 Inputs'!$C$26/'A1 Inputs'!$C$25)*7000) / $D$5 -> 4.8421053 | E15: =(7000/100 + 'A1 Inputs'!$C$19 + ('A1 Inputs'!$C$26/'A1 Inputs'!$C$25)*7000) / $D$5 -> 4.0526316 | F15: =(7000/150 + 'A1 Inputs'!$C$19 + ('A1 Inputs'!$C$26/'A1 Inputs'!$C$25)*7000) / $D$5 -> 3.4385965 | G15: =(7000/250 + 'A1 Inputs'!$C$19 + ('A1 Inputs'!$C$26/'A1 Inputs'!$C$25)*7000) / $D$5 -> 2.9473684 | H15: =(7000/400 + 'A1 Inputs'!$C$19 + ('A1 Inputs'!$C$26/'A1 Inputs'!$C$25)*7000) / $D$5 -> 2.6710526 | I15: =(7000/700 + 'A1 Inputs'!$C$19 + ('A1 Inputs'!$C$26/'A1 Inputs'!$C$25)*7000) / $D$5 -> 2.4736842
B17: READING THIS TABLE:
B18: Each cell = orbital cost per watt / terrestrial cost per watt, recomputed at that launch cost (row) and specific power (col).
B19: Holds hardware $/W, radiator mass, and radiator W/m2 at their Inputs-tab values; change those to re-stress.
B20: GREEN (<1.0x) = orbital cheaper per watt. YELLOW (1-2x) = contested. RED (>2x) = terrestrial wins clearly.
B22: TAKEAWAY: orbital reaches parity per-watt only in the bottom-left corner — LOW launch cost AND HIGH specific power
B23: together. At the demonstrated Falcon-9 rate ($7,000/kg) nothing is close. This is a launch-cost option, not a today trade.
B24: Note: this is capex-per-watt; the asset-life and MFU levers (tabs 2-4) further favor terrestrial for training workloads.
B25: NOTE (specific power >= 70 W/kg): AI1s 70 kW/ton is likely an ALL-IN figure already including radiators, so the radiator term added here may double-count in those columns — read them as a CONSERVATIVE upper bound.
B26: NOTE (base case): the 36.5 W/kg base sits just left of the 50 W/kg column (~1.95-2.0x here). This grid is the simplified capex-per-watt ratio; the headline 2.14x is the full TCO / effective-PFLOP figure on tabs 2-4.
B30: CROSSOVER #2 — Orbital ÷ Terrestrial cost per MW-YEAR (annualized), by launch $/kg × asset life
B31: Asset life drives the capital-recovery factor AND the solar-degradation derate; this isolates that lever on a full annualized basis (incl. compute, radiator, GPU re-launch). Terrestrial denominator uses its own 5/14-yr lives.
B32: Terrestrial $/MW-yr (constant): | C32: ='A1 Terrestrial'!C20 -> 10218356
B33: Launch $/kg \ Asset life (yrs) -> | C33: 3 | D33: 5 | E33: 7 | F33: 10 | G33: 14 | H33: 20
B34: 100 | C34: =((('A1 Orbital'!$C$5*$B34+'A1 Orbital'!$C$10+'A1 Orbital'!$C$13*$B34)*('A1 Inputs'!$C$8*(1+'A1 Inputs'!$C$8)^C$33/((1+'A1 Inputs'!$C$8)^C$33-1))+'A1 Orbital'!$C$20+'A1 Orbital'!$C$5*'A1 Inputs'!$C$21*$B34+('A1 Orbital'!$C$5*$B34+'A1 Orbital'!$C$10+'A1 Orbital'!$C$13*$B34)*'A1 Inputs'!$C$22)/('A1 Inputs'!$C$6*((1+(1-'A1 Inputs'!$C$20)^C$33)/2)))/'A1 Terrestrial'!$C$20 -> 2.7353822 | D34: =((('A1 Orbital'!$C$5*$B34+'A1 Orbital'!$C$10+'A1 Orbital'!$C$13*$B34)*('A1 Inputs'!$C$8*(1+'A1 Inputs'!$C$8)^D$33/((1+'A1 Inputs'!$C$8)^D$33-1))+'A1 Orbital'!$C$20+'A1 Orbital'!$C$5*'A1 Inputs'!$C$21*$B34+('A1 Orbital'!$C$5*$B34+'A1 Orbital'!$C$10+'A1 Orbital'!$C$13*$B34)*'A1 Inputs'!$C$22)/('A1 Inputs'!$C$6*((1+(1-'A1 Inputs'!$C$20)^D$33)/2)))/'A1 Terrestrial'!$C$20 -> 2.0467258 | E34: =((('A1 Orbital'!$C$5*$B34+'A1 Orbital'!$C$10+'A1 Orbital'!$C$13*$B34)*('A1 Inputs'!$C$8*(1+'A1 Inputs'!$C$8)^E$33/((1+'A1 Inputs'!$C$8)^E$33-1))+'A1 Orbital'!$C$20+'A1 Orbital'!$C$5*'A1 Inputs'!$C$21*$B34+('A1 Orbital'!$C$5*$B34+'A1 Orbital'!$C$10+'A1 Orbital'!$C$13*$B34)*'A1 Inputs'!$C$22)/('A1 Inputs'!$C$6*((1+(1-'A1 Inputs'!$C$20)^E$33)/2)))/'A1 Terrestrial'!$C$20 -> 1.7708341 | F34: =((('A1 Orbital'!$C$5*$B34+'A1 Orbital'!$C$10+'A1 Orbital'!$C$13*$B34)*('A1 Inputs'!$C$8*(1+'A1 Inputs'!$C$8)^F$33/((1+'A1 Inputs'!$C$8)^F$33-1))+'A1 Orbital'!$C$20+'A1 Orbital'!$C$5*'A1 Inputs'!$C$21*$B34+('A1 Orbital'!$C$5*$B34+'A1 Orbital'!$C$10+'A1 Orbital'!$C$13*$B34)*'A1 Inputs'!$C$22)/('A1 Inputs'!$C$6*((1+(1-'A1 Inputs'!$C$20)^F$33)/2)))/'A1 Terrestrial'!$C$20 -> 1.5893827 | G34: =((('A1 Orbital'!$C$5*$B34+'A1 Orbital'!$C$10+'A1 Orbital'!$C$13*$B34)*('A1 Inputs'!$C$8*(1+'A1 Inputs'!$C$8)^G$33/((1+'A1 Inputs'!$C$8)^G$33-1))+'A1 Orbital'!$C$20+'A1 Orbital'!$C$5*'A1 Inputs'!$C$21*$B34+('A1 Orbital'!$C$5*$B34+'A1 Orbital'!$C$10+'A1 Orbital'!$C$13*$B34)*'A1 Inputs'!$C$22)/('A1 Inputs'!$C$6*((1+(1-'A1 Inputs'!$C$20)^G$33)/2)))/'A1 Terrestrial'!$C$20 -> 1.5023106 | H34: =((('A1 Orbital'!$C$5*$B34+'A1 Orbital'!$C$10+'A1 Orbital'!$C$13*$B34)*('A1 Inputs'!$C$8*(1+'A1 Inputs'!$C$8)^H$33/((1+'A1 Inputs'!$C$8)^H$33-1))+'A1 Orbital'!$C$20+'A1 Orbital'!$C$5*'A1 Inputs'!$C$21*$B34+('A1 Orbital'!$C$5*$B34+'A1 Orbital'!$C$10+'A1 Orbital'!$C$13*$B34)*'A1 Inputs'!$C$22)/('A1 Inputs'!$C$6*((1+(1-'A1 Inputs'!$C$20)^H$33)/2)))/'A1 Terrestrial'!$C$20 -> 1.4865832
B35: 200 | C35: =((('A1 Orbital'!$C$5*$B35+'A1 Orbital'!$C$10+'A1 Orbital'!$C$13*$B35)*('A1 Inputs'!$C$8*(1+'A1 Inputs'!$C$8)^C$33/((1+'A1 Inputs'!$C$8)^C$33-1))+'A1 Orbital'!$C$20+'A1 Orbital'!$C$5*'A1 Inputs'!$C$21*$B35+('A1 Orbital'!$C$5*$B35+'A1 Orbital'!$C$10+'A1 Orbital'!$C$13*$B35)*'A1 Inputs'!$C$22)/('A1 Inputs'!$C$6*((1+(1-'A1 Inputs'!$C$20)^C$33)/2)))/'A1 Terrestrial'!$C$20 -> 2.9007335 | D35: =((('A1 Orbital'!$C$5*$B35+'A1 Orbital'!$C$10+'A1 Orbital'!$C$13*$B35)*('A1 Inputs'!$C$8*(1+'A1 Inputs'!$C$8)^D$33/((1+'A1 Inputs'!$C$8)^D$33-1))+'A1 Orbital'!$C$20+'A1 Orbital'!$C$5*'A1 Inputs'!$C$21*$B35+('A1 Orbital'!$C$5*$B35+'A1 Orbital'!$C$10+'A1 Orbital'!$C$13*$B35)*'A1 Inputs'!$C$22)/('A1 Inputs'!$C$6*((1+(1-'A1 Inputs'!$C$20)^D$33)/2)))/'A1 Terrestrial'!$C$20 -> 2.1692648 | E35: =((('A1 Orbital'!$C$5*$B35+'A1 Orbital'!$C$10+'A1 Orbital'!$C$13*$B35)*('A1 Inputs'!$C$8*(1+'A1 Inputs'!$C$8)^E$33/((1+'A1 Inputs'!$C$8)^E$33-1))+'A1 Orbital'!$C$20+'A1 Orbital'!$C$5*'A1 Inputs'!$C$21*$B35+('A1 Orbital'!$C$5*$B35+'A1 Orbital'!$C$10+'A1 Orbital'!$C$13*$B35)*'A1 Inputs'!$C$22)/('A1 Inputs'!$C$6*((1+(1-'A1 Inputs'!$C$20)^E$33)/2)))/'A1 Terrestrial'!$C$20 -> 1.8761593 | F35: =((('A1 Orbital'!$C$5*$B35+'A1 Orbital'!$C$10+'A1 Orbital'!$C$13*$B35)*('A1 Inputs'!$C$8*(1+'A1 Inputs'!$C$8)^F$33/((1+'A1 Inputs'!$C$8)^F$33-1))+'A1 Orbital'!$C$20+'A1 Orbital'!$C$5*'A1 Inputs'!$C$21*$B35+('A1 Orbital'!$C$5*$B35+'A1 Orbital'!$C$10+'A1 Orbital'!$C$13*$B35)*'A1 Inputs'!$C$22)/('A1 Inputs'!$C$6*((1+(1-'A1 Inputs'!$C$20)^F$33)/2)))/'A1 Terrestrial'!$C$20 -> 1.6832998 | G35: =((('A1 Orbital'!$C$5*$B35+'A1 Orbital'!$C$10+'A1 Orbital'!$C$13*$B35)*('A1 Inputs'!$C$8*(1+'A1 Inputs'!$C$8)^G$33/((1+'A1 Inputs'!$C$8)^G$33-1))+'A1 Orbital'!$C$20+'A1 Orbital'!$C$5*'A1 Inputs'!$C$21*$B35+('A1 Orbital'!$C$5*$B35+'A1 Orbital'!$C$10+'A1 Orbital'!$C$13*$B35)*'A1 Inputs'!$C$22)/('A1 Inputs'!$C$6*((1+(1-'A1 Inputs'!$C$20)^G$33)/2)))/'A1 Terrestrial'!$C$20 -> 1.5906235 | H35: =((('A1 Orbital'!$C$5*$B35+'A1 Orbital'!$C$10+'A1 Orbital'!$C$13*$B35)*('A1 Inputs'!$C$8*(1+'A1 Inputs'!$C$8)^H$33/((1+'A1 Inputs'!$C$8)^H$33-1))+'A1 Orbital'!$C$20+'A1 Orbital'!$C$5*'A1 Inputs'!$C$21*$B35+('A1 Orbital'!$C$5*$B35+'A1 Orbital'!$C$10+'A1 Orbital'!$C$13*$B35)*'A1 Inputs'!$C$22)/('A1 Inputs'!$C$6*((1+(1-'A1 Inputs'!$C$20)^H$33)/2)))/'A1 Terrestrial'!$C$20 -> 1.5736212
B36: 300 | C36: =((('A1 Orbital'!$C$5*$B36+'A1 Orbital'!$C$10+'A1 Orbital'!$C$13*$B36)*('A1 Inputs'!$C$8*(1+'A1 Inputs'!$C$8)^C$33/((1+'A1 Inputs'!$C$8)^C$33-1))+'A1 Orbital'!$C$20+'A1 Orbital'!$C$5*'A1 Inputs'!$C$21*$B36+('A1 Orbital'!$C$5*$B36+'A1 Orbital'!$C$10+'A1 Orbital'!$C$13*$B36)*'A1 Inputs'!$C$22)/('A1 Inputs'!$C$6*((1+(1-'A1 Inputs'!$C$20)^C$33)/2)))/'A1 Terrestrial'!$C$20 -> 3.0660849 | D36: =((('A1 Orbital'!$C$5*$B36+'A1 Orbital'!$C$10+'A1 Orbital'!$C$13*$B36)*('A1 Inputs'!$C$8*(1+'A1 Inputs'!$C$8)^D$33/((1+'A1 Inputs'!$C$8)^D$33-1))+'A1 Orbital'!$C$20+'A1 Orbital'!$C$5*'A1 Inputs'!$C$21*$B36+('A1 Orbital'!$C$5*$B36+'A1 Orbital'!$C$10+'A1 Orbital'!$C$13*$B36)*'A1 Inputs'!$C$22)/('A1 Inputs'!$C$6*((1+(1-'A1 Inputs'!$C$20)^D$33)/2)))/'A1 Terrestrial'!$C$20 -> 2.2918038 | E36: =((('A1 Orbital'!$C$5*$B36+'A1 Orbital'!$C$10+'A1 Orbital'!$C$13*$B36)*('A1 Inputs'!$C$8*(1+'A1 Inputs'!$C$8)^E$33/((1+'A1 Inputs'!$C$8)^E$33-1))+'A1 Orbital'!$C$20+'A1 Orbital'!$C$5*'A1 Inputs'!$C$21*$B36+('A1 Orbital'!$C$5*$B36+'A1 Orbital'!$C$10+'A1 Orbital'!$C$13*$B36)*'A1 Inputs'!$C$22)/('A1 Inputs'!$C$6*((1+(1-'A1 Inputs'!$C$20)^E$33)/2)))/'A1 Terrestrial'!$C$20 -> 1.9814845 | F36: =((('A1 Orbital'!$C$5*$B36+'A1 Orbital'!$C$10+'A1 Orbital'!$C$13*$B36)*('A1 Inputs'!$C$8*(1+'A1 Inputs'!$C$8)^F$33/((1+'A1 Inputs'!$C$8)^F$33-1))+'A1 Orbital'!$C$20+'A1 Orbital'!$C$5*'A1 Inputs'!$C$21*$B36+('A1 Orbital'!$C$5*$B36+'A1 Orbital'!$C$10+'A1 Orbital'!$C$13*$B36)*'A1 Inputs'!$C$22)/('A1 Inputs'!$C$6*((1+(1-'A1 Inputs'!$C$20)^F$33)/2)))/'A1 Terrestrial'!$C$20 -> 1.7772169 | G36: =((('A1 Orbital'!$C$5*$B36+'A1 Orbital'!$C$10+'A1 Orbital'!$C$13*$B36)*('A1 Inputs'!$C$8*(1+'A1 Inputs'!$C$8)^G$33/((1+'A1 Inputs'!$C$8)^G$33-1))+'A1 Orbital'!$C$20+'A1 Orbital'!$C$5*'A1 Inputs'!$C$21*$B36+('A1 Orbital'!$C$5*$B36+'A1 Orbital'!$C$10+'A1 Orbital'!$C$13*$B36)*'A1 Inputs'!$C$22)/('A1 Inputs'!$C$6*((1+(1-'A1 Inputs'!$C$20)^G$33)/2)))/'A1 Terrestrial'!$C$20 -> 1.6789363 | H36: =((('A1 Orbital'!$C$5*$B36+'A1 Orbital'!$C$10+'A1 Orbital'!$C$13*$B36)*('A1 Inputs'!$C$8*(1+'A1 Inputs'!$C$8)^H$33/((1+'A1 Inputs'!$C$8)^H$33-1))+'A1 Orbital'!$C$20+'A1 Orbital'!$C$5*'A1 Inputs'!$C$21*$B36+('A1 Orbital'!$C$5*$B36+'A1 Orbital'!$C$10+'A1 Orbital'!$C$13*$B36)*'A1 Inputs'!$C$22)/('A1 Inputs'!$C$6*((1+(1-'A1 Inputs'!$C$20)^H$33)/2)))/'A1 Terrestrial'!$C$20 -> 1.6606592
B37: 500 | C37: =((('A1 Orbital'!$C$5*$B37+'A1 Orbital'!$C$10+'A1 Orbital'!$C$13*$B37)*('A1 Inputs'!$C$8*(1+'A1 Inputs'!$C$8)^C$33/((1+'A1 Inputs'!$C$8)^C$33-1))+'A1 Orbital'!$C$20+'A1 Orbital'!$C$5*'A1 Inputs'!$C$21*$B37+('A1 Orbital'!$C$5*$B37+'A1 Orbital'!$C$10+'A1 Orbital'!$C$13*$B37)*'A1 Inputs'!$C$22)/('A1 Inputs'!$C$6*((1+(1-'A1 Inputs'!$C$20)^C$33)/2)))/'A1 Terrestrial'!$C$20 -> 3.3967876 | D37: =((('A1 Orbital'!$C$5*$B37+'A1 Orbital'!$C$10+'A1 Orbital'!$C$13*$B37)*('A1 Inputs'!$C$8*(1+'A1 Inputs'!$C$8)^D$33/((1+'A1 Inputs'!$C$8)^D$33-1))+'A1 Orbital'!$C$20+'A1 Orbital'!$C$5*'A1 Inputs'!$C$21*$B37+('A1 Orbital'!$C$5*$B37+'A1 Orbital'!$C$10+'A1 Orbital'!$C$13*$B37)*'A1 Inputs'!$C$22)/('A1 Inputs'!$C$6*((1+(1-'A1 Inputs'!$C$20)^D$33)/2)))/'A1 Terrestrial'!$C$20 -> 2.5368817 | E37: =((('A1 Orbital'!$C$5*$B37+'A1 Orbital'!$C$10+'A1 Orbital'!$C$13*$B37)*('A1 Inputs'!$C$8*(1+'A1 Inputs'!$C$8)^E$33/((1+'A1 Inputs'!$C$8)^E$33-1))+'A1 Orbital'!$C$20+'A1 Orbital'!$C$5*'A1 Inputs'!$C$21*$B37+('A1 Orbital'!$C$5*$B37+'A1 Orbital'!$C$10+'A1 Orbital'!$C$13*$B37)*'A1 Inputs'!$C$22)/('A1 Inputs'!$C$6*((1+(1-'A1 Inputs'!$C$20)^E$33)/2)))/'A1 Terrestrial'!$C$20 -> 2.1921348 | F37: =((('A1 Orbital'!$C$5*$B37+'A1 Orbital'!$C$10+'A1 Orbital'!$C$13*$B37)*('A1 Inputs'!$C$8*(1+'A1 Inputs'!$C$8)^F$33/((1+'A1 Inputs'!$C$8)^F$33-1))+'A1 Orbital'!$C$20+'A1 Orbital'!$C$5*'A1 Inputs'!$C$21*$B37+('A1 Orbital'!$C$5*$B37+'A1 Orbital'!$C$10+'A1 Orbital'!$C$13*$B37)*'A1 Inputs'!$C$22)/('A1 Inputs'!$C$6*((1+(1-'A1 Inputs'!$C$20)^F$33)/2)))/'A1 Terrestrial'!$C$20 -> 1.9650512 | G37: =((('A1 Orbital'!$C$5*$B37+'A1 Orbital'!$C$10+'A1 Orbital'!$C$13*$B37)*('A1 Inputs'!$C$8*(1+'A1 Inputs'!$C$8)^G$33/((1+'A1 Inputs'!$C$8)^G$33-1))+'A1 Orbital'!$C$20+'A1 Orbital'!$C$5*'A1 Inputs'!$C$21*$B37+('A1 Orbital'!$C$5*$B37+'A1 Orbital'!$C$10+'A1 Orbital'!$C$13*$B37)*'A1 Inputs'!$C$22)/('A1 Inputs'!$C$6*((1+(1-'A1 Inputs'!$C$20)^G$33)/2)))/'A1 Terrestrial'!$C$20 -> 1.855562 | H37: =((('A1 Orbital'!$C$5*$B37+'A1 Orbital'!$C$10+'A1 Orbital'!$C$13*$B37)*('A1 Inputs'!$C$8*(1+'A1 Inputs'!$C$8)^H$33/((1+'A1 Inputs'!$C$8)^H$33-1))+'A1 Orbital'!$C$20+'A1 Orbital'!$C$5*'A1 Inputs'!$C$21*$B37+('A1 Orbital'!$C$5*$B37+'A1 Orbital'!$C$10+'A1 Orbital'!$C$13*$B37)*'A1 Inputs'!$C$22)/('A1 Inputs'!$C$6*((1+(1-'A1 Inputs'!$C$20)^H$33)/2)))/'A1 Terrestrial'!$C$20 -> 1.8347351
B38: 1000 | C38: =((('A1 Orbital'!$C$5*$B38+'A1 Orbital'!$C$10+'A1 Orbital'!$C$13*$B38)*('A1 Inputs'!$C$8*(1+'A1 Inputs'!$C$8)^C$33/((1+'A1 Inputs'!$C$8)^C$33-1))+'A1 Orbital'!$C$20+'A1 Orbital'!$C$5*'A1 Inputs'!$C$21*$B38+('A1 Orbital'!$C$5*$B38+'A1 Orbital'!$C$10+'A1 Orbital'!$C$13*$B38)*'A1 Inputs'!$C$22)/('A1 Inputs'!$C$6*((1+(1-'A1 Inputs'!$C$20)^C$33)/2)))/'A1 Terrestrial'!$C$20 -> 4.2235444 | D38: =((('A1 Orbital'!$C$5*$B38+'A1 Orbital'!$C$10+'A1 Orbital'!$C$13*$B38)*('A1 Inputs'!$C$8*(1+'A1 Inputs'!$C$8)^D$33/((1+'A1 Inputs'!$C$8)^D$33-1))+'A1 Orbital'!$C$20+'A1 Orbital'!$C$5*'A1 Inputs'!$C$21*$B38+('A1 Orbital'!$C$5*$B38+'A1 Orbital'!$C$10+'A1 Orbital'!$C$13*$B38)*'A1 Inputs'!$C$22)/('A1 Inputs'!$C$6*((1+(1-'A1 Inputs'!$C$20)^D$33)/2)))/'A1 Terrestrial'!$C$20 -> 3.1495766 | E38: =((('A1 Orbital'!$C$5*$B38+'A1 Orbital'!$C$10+'A1 Orbital'!$C$13*$B38)*('A1 Inputs'!$C$8*(1+'A1 Inputs'!$C$8)^E$33/((1+'A1 Inputs'!$C$8)^E$33-1))+'A1 Orbital'!$C$20+'A1 Orbital'!$C$5*'A1 Inputs'!$C$21*$B38+('A1 Orbital'!$C$5*$B38+'A1 Orbital'!$C$10+'A1 Orbital'!$C$13*$B38)*'A1 Inputs'!$C$22)/('A1 Inputs'!$C$6*((1+(1-'A1 Inputs'!$C$20)^E$33)/2)))/'A1 Terrestrial'!$C$20 -> 2.7187606 | F38: =((('A1 Orbital'!$C$5*$B38+'A1 Orbital'!$C$10+'A1 Orbital'!$C$13*$B38)*('A1 Inputs'!$C$8*(1+'A1 Inputs'!$C$8)^F$33/((1+'A1 Inputs'!$C$8)^F$33-1))+'A1 Orbital'!$C$20+'A1 Orbital'!$C$5*'A1 Inputs'!$C$21*$B38+('A1 Orbital'!$C$5*$B38+'A1 Orbital'!$C$10+'A1 Orbital'!$C$13*$B38)*'A1 Inputs'!$C$22)/('A1 Inputs'!$C$6*((1+(1-'A1 Inputs'!$C$20)^F$33)/2)))/'A1 Terrestrial'!$C$20 -> 2.4346368 | G38: =((('A1 Orbital'!$C$5*$B38+'A1 Orbital'!$C$10+'A1 Orbital'!$C$13*$B38)*('A1 Inputs'!$C$8*(1+'A1 Inputs'!$C$8)^G$33/((1+'A1 Inputs'!$C$8)^G$33-1))+'A1 Orbital'!$C$20+'A1 Orbital'!$C$5*'A1 Inputs'!$C$21*$B38+('A1 Orbital'!$C$5*$B38+'A1 Orbital'!$C$10+'A1 Orbital'!$C$13*$B38)*'A1 Inputs'!$C$22)/('A1 Inputs'!$C$6*((1+(1-'A1 Inputs'!$C$20)^G$33)/2)))/'A1 Terrestrial'!$C$20 -> 2.2971263 | H38: =((('A1 Orbital'!$C$5*$B38+'A1 Orbital'!$C$10+'A1 Orbital'!$C$13*$B38)*('A1 Inputs'!$C$8*(1+'A1 Inputs'!$C$8)^H$33/((1+'A1 Inputs'!$C$8)^H$33-1))+'A1 Orbital'!$C$20+'A1 Orbital'!$C$5*'A1 Inputs'!$C$21*$B38+('A1 Orbital'!$C$5*$B38+'A1 Orbital'!$C$10+'A1 Orbital'!$C$13*$B38)*'A1 Inputs'!$C$22)/('A1 Inputs'!$C$6*((1+(1-'A1 Inputs'!$C$20)^H$33)/2)))/'A1 Terrestrial'!$C$20 -> 2.2699249
B39: 2000 | C39: =((('A1 Orbital'!$C$5*$B39+'A1 Orbital'!$C$10+'A1 Orbital'!$C$13*$B39)*('A1 Inputs'!$C$8*(1+'A1 Inputs'!$C$8)^C$33/((1+'A1 Inputs'!$C$8)^C$33-1))+'A1 Orbital'!$C$20+'A1 Orbital'!$C$5*'A1 Inputs'!$C$21*$B39+('A1 Orbital'!$C$5*$B39+'A1 Orbital'!$C$10+'A1 Orbital'!$C$13*$B39)*'A1 Inputs'!$C$22)/('A1 Inputs'!$C$6*((1+(1-'A1 Inputs'!$C$20)^C$33)/2)))/'A1 Terrestrial'!$C$20 -> 5.877058 | D39: =((('A1 Orbital'!$C$5*$B39+'A1 Orbital'!$C$10+'A1 Orbital'!$C$13*$B39)*('A1 Inputs'!$C$8*(1+'A1 Inputs'!$C$8)^D$33/((1+'A1 Inputs'!$C$8)^D$33-1))+'A1 Orbital'!$C$20+'A1 Orbital'!$C$5*'A1 Inputs'!$C$21*$B39+('A1 Orbital'!$C$5*$B39+'A1 Orbital'!$C$10+'A1 Orbital'!$C$13*$B39)*'A1 Inputs'!$C$22)/('A1 Inputs'!$C$6*((1+(1-'A1 Inputs'!$C$20)^D$33)/2)))/'A1 Terrestrial'!$C$20 -> 4.3749664 | E39: =((('A1 Orbital'!$C$5*$B39+'A1 Orbital'!$C$10+'A1 Orbital'!$C$13*$B39)*('A1 Inputs'!$C$8*(1+'A1 Inputs'!$C$8)^E$33/((1+'A1 Inputs'!$C$8)^E$33-1))+'A1 Orbital'!$C$20+'A1 Orbital'!$C$5*'A1 Inputs'!$C$21*$B39+('A1 Orbital'!$C$5*$B39+'A1 Orbital'!$C$10+'A1 Orbital'!$C$13*$B39)*'A1 Inputs'!$C$22)/('A1 Inputs'!$C$6*((1+(1-'A1 Inputs'!$C$20)^E$33)/2)))/'A1 Terrestrial'!$C$20 -> 3.7720122 | F39: =((('A1 Orbital'!$C$5*$B39+'A1 Orbital'!$C$10+'A1 Orbital'!$C$13*$B39)*('A1 Inputs'!$C$8*(1+'A1 Inputs'!$C$8)^F$33/((1+'A1 Inputs'!$C$8)^F$33-1))+'A1 Orbital'!$C$20+'A1 Orbital'!$C$5*'A1 Inputs'!$C$21*$B39+('A1 Orbital'!$C$5*$B39+'A1 Orbital'!$C$10+'A1 Orbital'!$C$13*$B39)*'A1 Inputs'!$C$22)/('A1 Inputs'!$C$6*((1+(1-'A1 Inputs'!$C$20)^F$33)/2)))/'A1 Terrestrial'!$C$20 -> 3.373808 | G39: =((('A1 Orbital'!$C$5*$B39+'A1 Orbital'!$C$10+'A1 Orbital'!$C$13*$B39)*('A1 Inputs'!$C$8*(1+'A1 Inputs'!$C$8)^G$33/((1+'A1 Inputs'!$C$8)^G$33-1))+'A1 Orbital'!$C$20+'A1 Orbital'!$C$5*'A1 Inputs'!$C$21*$B39+('A1 Orbital'!$C$5*$B39+'A1 Orbital'!$C$10+'A1 Orbital'!$C$13*$B39)*'A1 Inputs'!$C$22)/('A1 Inputs'!$C$6*((1+(1-'A1 Inputs'!$C$20)^G$33)/2)))/'A1 Terrestrial'!$C$20 -> 3.1802548 | H39: =((('A1 Orbital'!$C$5*$B39+'A1 Orbital'!$C$10+'A1 Orbital'!$C$13*$B39)*('A1 Inputs'!$C$8*(1+'A1 Inputs'!$C$8)^H$33/((1+'A1 Inputs'!$C$8)^H$33-1))+'A1 Orbital'!$C$20+'A1 Orbital'!$C$5*'A1 Inputs'!$C$21*$B39+('A1 Orbital'!$C$5*$B39+'A1 Orbital'!$C$10+'A1 Orbital'!$C$13*$B39)*'A1 Inputs'!$C$22)/('A1 Inputs'!$C$6*((1+(1-'A1 Inputs'!$C$20)^H$33)/2)))/'A1 Terrestrial'!$C$20 -> 3.1403046
B40: 5000 | C40: =((('A1 Orbital'!$C$5*$B40+'A1 Orbital'!$C$10+'A1 Orbital'!$C$13*$B40)*('A1 Inputs'!$C$8*(1+'A1 Inputs'!$C$8)^C$33/((1+'A1 Inputs'!$C$8)^C$33-1))+'A1 Orbital'!$C$20+'A1 Orbital'!$C$5*'A1 Inputs'!$C$21*$B40+('A1 Orbital'!$C$5*$B40+'A1 Orbital'!$C$10+'A1 Orbital'!$C$13*$B40)*'A1 Inputs'!$C$22)/('A1 Inputs'!$C$6*((1+(1-'A1 Inputs'!$C$20)^C$33)/2)))/'A1 Terrestrial'!$C$20 -> 10.837599 | D40: =((('A1 Orbital'!$C$5*$B40+'A1 Orbital'!$C$10+'A1 Orbital'!$C$13*$B40)*('A1 Inputs'!$C$8*(1+'A1 Inputs'!$C$8)^D$33/((1+'A1 Inputs'!$C$8)^D$33-1))+'A1 Orbital'!$C$20+'A1 Orbital'!$C$5*'A1 Inputs'!$C$21*$B40+('A1 Orbital'!$C$5*$B40+'A1 Orbital'!$C$10+'A1 Orbital'!$C$13*$B40)*'A1 Inputs'!$C$22)/('A1 Inputs'!$C$6*((1+(1-'A1 Inputs'!$C$20)^D$33)/2)))/'A1 Terrestrial'!$C$20 -> 8.0511358 | E40: =((('A1 Orbital'!$C$5*$B40+'A1 Orbital'!$C$10+'A1 Orbital'!$C$13*$B40)*('A1 Inputs'!$C$8*(1+'A1 Inputs'!$C$8)^E$33/((1+'A1 Inputs'!$C$8)^E$33-1))+'A1 Orbital'!$C$20+'A1 Orbital'!$C$5*'A1 Inputs'!$C$21*$B40+('A1 Orbital'!$C$5*$B40+'A1 Orbital'!$C$10+'A1 Orbital'!$C$13*$B40)*'A1 Inputs'!$C$22)/('A1 Inputs'!$C$6*((1+(1-'A1 Inputs'!$C$20)^E$33)/2)))/'A1 Terrestrial'!$C$20 -> 6.9317672 | F40: =((('A1 Orbital'!$C$5*$B40+'A1 Orbital'!$C$10+'A1 Orbital'!$C$13*$B40)*('A1 Inputs'!$C$8*(1+'A1 Inputs'!$C$8)^F$33/((1+'A1 Inputs'!$C$8)^F$33-1))+'A1 Orbital'!$C$20+'A1 Orbital'!$C$5*'A1 Inputs'!$C$21*$B40+('A1 Orbital'!$C$5*$B40+'A1 Orbital'!$C$10+'A1 Orbital'!$C$13*$B40)*'A1 Inputs'!$C$22)/('A1 Inputs'!$C$6*((1+(1-'A1 Inputs'!$C$20)^F$33)/2)))/'A1 Terrestrial'!$C$20 -> 6.1913218 | G40: =((('A1 Orbital'!$C$5*$B40+'A1 Orbital'!$C$10+'A1 Orbital'!$C$13*$B40)*('A1 Inputs'!$C$8*(1+'A1 Inputs'!$C$8)^G$33/((1+'A1 Inputs'!$C$8)^G$33-1))+'A1 Orbital'!$C$20+'A1 Orbital'!$C$5*'A1 Inputs'!$C$21*$B40+('A1 Orbital'!$C$5*$B40+'A1 Orbital'!$C$10+'A1 Orbital'!$C$13*$B40)*'A1 Inputs'!$C$22)/('A1 Inputs'!$C$6*((1+(1-'A1 Inputs'!$C$20)^G$33)/2)))/'A1 Terrestrial'!$C$20 -> 5.8296404 | H40: =((('A1 Orbital'!$C$5*$B40+'A1 Orbital'!$C$10+'A1 Orbital'!$C$13*$B40)*('A1 Inputs'!$C$8*(1+'A1 Inputs'!$C$8)^H$33/((1+'A1 Inputs'!$C$8)^H$33-1))+'A1 Orbital'!$C$20+'A1 Orbital'!$C$5*'A1 Inputs'!$C$21*$B40+('A1 Orbital'!$C$5*$B40+'A1 Orbital'!$C$10+'A1 Orbital'!$C$13*$B40)*'A1 Inputs'!$C$22)/('A1 Inputs'!$C$6*((1+(1-'A1 Inputs'!$C$20)^H$33)/2)))/'A1 Terrestrial'!$C$20 -> 5.7514436
B41: 7000 | C41: =((('A1 Orbital'!$C$5*$B41+'A1 Orbital'!$C$10+'A1 Orbital'!$C$13*$B41)*('A1 Inputs'!$C$8*(1+'A1 Inputs'!$C$8)^C$33/((1+'A1 Inputs'!$C$8)^C$33-1))+'A1 Orbital'!$C$20+'A1 Orbital'!$C$5*'A1 Inputs'!$C$21*$B41+('A1 Orbital'!$C$5*$B41+'A1 Orbital'!$C$10+'A1 Orbital'!$C$13*$B41)*'A1 Inputs'!$C$22)/('A1 Inputs'!$C$6*((1+(1-'A1 Inputs'!$C$20)^C$33)/2)))/'A1 Terrestrial'!$C$20 -> 14.144626 | D41: =((('A1 Orbital'!$C$5*$B41+'A1 Orbital'!$C$10+'A1 Orbital'!$C$13*$B41)*('A1 Inputs'!$C$8*(1+'A1 Inputs'!$C$8)^D$33/((1+'A1 Inputs'!$C$8)^D$33-1))+'A1 Orbital'!$C$20+'A1 Orbital'!$C$5*'A1 Inputs'!$C$21*$B41+('A1 Orbital'!$C$5*$B41+'A1 Orbital'!$C$10+'A1 Orbital'!$C$13*$B41)*'A1 Inputs'!$C$22)/('A1 Inputs'!$C$6*((1+(1-'A1 Inputs'!$C$20)^D$33)/2)))/'A1 Terrestrial'!$C$20 -> 10.501915 | E41: =((('A1 Orbital'!$C$5*$B41+'A1 Orbital'!$C$10+'A1 Orbital'!$C$13*$B41)*('A1 Inputs'!$C$8*(1+'A1 Inputs'!$C$8)^E$33/((1+'A1 Inputs'!$C$8)^E$33-1))+'A1 Orbital'!$C$20+'A1 Orbital'!$C$5*'A1 Inputs'!$C$21*$B41+('A1 Orbital'!$C$5*$B41+'A1 Orbital'!$C$10+'A1 Orbital'!$C$13*$B41)*'A1 Inputs'!$C$22)/('A1 Inputs'!$C$6*((1+(1-'A1 Inputs'!$C$20)^E$33)/2)))/'A1 Terrestrial'!$C$20 -> 9.0382704 | F41: =((('A1 Orbital'!$C$5*$B41+'A1 Orbital'!$C$10+'A1 Orbital'!$C$13*$B41)*('A1 Inputs'!$C$8*(1+'A1 Inputs'!$C$8)^F$33/((1+'A1 Inputs'!$C$8)^F$33-1))+'A1 Orbital'!$C$20+'A1 Orbital'!$C$5*'A1 Inputs'!$C$21*$B41+('A1 Orbital'!$C$5*$B41+'A1 Orbital'!$C$10+'A1 Orbital'!$C$13*$B41)*'A1 Inputs'!$C$22)/('A1 Inputs'!$C$6*((1+(1-'A1 Inputs'!$C$20)^F$33)/2)))/'A1 Terrestrial'!$C$20 -> 8.0696642 | G41: =((('A1 Orbital'!$C$5*$B41+'A1 Orbital'!$C$10+'A1 Orbital'!$C$13*$B41)*('A1 Inputs'!$C$8*(1+'A1 Inputs'!$C$8)^G$33/((1+'A1 Inputs'!$C$8)^G$33-1))+'A1 Orbital'!$C$20+'A1 Orbital'!$C$5*'A1 Inputs'!$C$21*$B41+('A1 Orbital'!$C$5*$B41+'A1 Orbital'!$C$10+'A1 Orbital'!$C$13*$B41)*'A1 Inputs'!$C$22)/('A1 Inputs'!$C$6*((1+(1-'A1 Inputs'!$C$20)^G$33)/2)))/'A1 Terrestrial'!$C$20 -> 7.5958974 | H41: =((('A1 Orbital'!$C$5*$B41+'A1 Orbital'!$C$10+'A1 Orbital'!$C$13*$B41)*('A1 Inputs'!$C$8*(1+'A1 Inputs'!$C$8)^H$33/((1+'A1 Inputs'!$C$8)^H$33-1))+'A1 Orbital'!$C$20+'A1 Orbital'!$C$5*'A1 Inputs'!$C$21*$B41+('A1 Orbital'!$C$5*$B41+'A1 Orbital'!$C$10+'A1 Orbital'!$C$13*$B41)*'A1 Inputs'!$C$22)/('A1 Inputs'!$C$6*((1+(1-'A1 Inputs'!$C$20)^H$33)/2)))/'A1 Terrestrial'!$C$20 -> 7.492203
B43: TIE-OUT: base cell (1,000 $/kg, 10-yr life) = Orbital Build!C28 ÷ Terrestrial Build!C20 = the headline ~2.4x per MW-year.
B44: READING: longer life lowers the annualized burden, but orbital stays >1x even at 20-yr life + low launch — asset life alone cannot offset the compute+radiator+re-launch stack. Parity needs launch, specific power, AND life together (see crossover #1 above).
B48: Scenario launch cost ($/kg): | C48: 300 | D48: [TGT] forward Starship target
B49: LONG-RUN SCENARIO (INFERENCE) — Orbital ÷ Terrestrial annual cost, as the bet's two levers move
B50: Forward inputs: orbital hardware $/W falls (vertical integration, terafab, scale) and terrestrial $/W rises (grid scarcity, transformers, permitting); launch held at the scenario cell above. Green <1.0x = orbit cheaper. INFERENCE ONLY — frontier training stays on Earth (bandwidth-bound, see Effective Compute).
B51: Orbital HW $/W \ Terrestrial $/W -> | C51: 38 | D51: 50 | E51: 70 | F51: 100 | G51: 150
B52: 49 | C52: =(('A1 Orbital'!$C$5*$C$48+(('A1 Inputs'!$C$6*1000000)*$B52)+'A1 Orbital'!$C$13*$C$48)*'A1 Orbital'!$C$18+(('A1 Inputs'!$C$6*1000000)*$B52)*'A1 Inputs'!$C$21+'A1 Orbital'!$C$5*'A1 Inputs'!$C$21*$C$48+('A1 Orbital'!$C$5*$C$48+(('A1 Inputs'!$C$6*1000000)*$B52)+'A1 Orbital'!$C$13*$C$48)*'A1 Inputs'!$C$22)/((('A1 Inputs'!$C$6*1000000)*C$51)*'A1 Inputs'!$C$32*'A1 Terrestrial'!$C$9+(('A1 Inputs'!$C$6*1000000)*C$51)*(1-'A1 Inputs'!$C$32)*'A1 Terrestrial'!$C$10+'A1 Terrestrial'!$C$14+(('A1 Inputs'!$C$6*1000000)*C$51)*'A1 Inputs'!$C$35) -> 1.5784615 | D52: =(('A1 Orbital'!$C$5*$C$48+(('A1 Inputs'!$C$6*1000000)*$B52)+'A1 Orbital'!$C$13*$C$48)*'A1 Orbital'!$C$18+(('A1 Inputs'!$C$6*1000000)*$B52)*'A1 Inputs'!$C$21+'A1 Orbital'!$C$5*'A1 Inputs'!$C$21*$C$48+('A1 Orbital'!$C$5*$C$48+(('A1 Inputs'!$C$6*1000000)*$B52)+'A1 Orbital'!$C$13*$C$48)*'A1 Inputs'!$C$22)/((('A1 Inputs'!$C$6*1000000)*D$51)*'A1 Inputs'!$C$32*'A1 Terrestrial'!$C$9+(('A1 Inputs'!$C$6*1000000)*D$51)*(1-'A1 Inputs'!$C$32)*'A1 Terrestrial'!$C$10+'A1 Terrestrial'!$C$14+(('A1 Inputs'!$C$6*1000000)*D$51)*'A1 Inputs'!$C$35) -> 1.2237799 | E52: =(('A1 Orbital'!$C$5*$C$48+(('A1 Inputs'!$C$6*1000000)*$B52)+'A1 Orbital'!$C$13*$C$48)*'A1 Orbital'!$C$18+(('A1 Inputs'!$C$6*1000000)*$B52)*'A1 Inputs'!$C$21+'A1 Orbital'!$C$5*'A1 Inputs'!$C$21*$C$48+('A1 Orbital'!$C$5*$C$48+(('A1 Inputs'!$C$6*1000000)*$B52)+'A1 Orbital'!$C$13*$C$48)*'A1 Inputs'!$C$22)/((('A1 Inputs'!$C$6*1000000)*E$51)*'A1 Inputs'!$C$32*'A1 Terrestrial'!$C$9+(('A1 Inputs'!$C$6*1000000)*E$51)*(1-'A1 Inputs'!$C$32)*'A1 Terrestrial'!$C$10+'A1 Terrestrial'!$C$14+(('A1 Inputs'!$C$6*1000000)*E$51)*'A1 Inputs'!$C$35) -> 0.89034459 | F52: =(('A1 Orbital'!$C$5*$C$48+(('A1 Inputs'!$C$6*1000000)*$B52)+'A1 Orbital'!$C$13*$C$48)*'A1 Orbital'!$C$18+(('A1 Inputs'!$C$6*1000000)*$B52)*'A1 Inputs'!$C$21+'A1 Orbital'!$C$5*'A1 Inputs'!$C$21*$C$48+('A1 Orbital'!$C$5*$C$48+(('A1 Inputs'!$C$6*1000000)*$B52)+'A1 Orbital'!$C$13*$C$48)*'A1 Inputs'!$C$22)/((('A1 Inputs'!$C$6*1000000)*F$51)*'A1 Inputs'!$C$32*'A1 Terrestrial'!$C$9+(('A1 Inputs'!$C$6*1000000)*F$51)*(1-'A1 Inputs'!$C$32)*'A1 Terrestrial'!$C$10+'A1 Terrestrial'!$C$14+(('A1 Inputs'!$C$6*1000000)*F$51)*'A1 Inputs'!$C$35) -> 0.63203495 | G52: =(('A1 Orbital'!$C$5*$C$48+(('A1 Inputs'!$C$6*1000000)*$B52)+'A1 Orbital'!$C$13*$C$48)*'A1 Orbital'!$C$18+(('A1 Inputs'!$C$6*1000000)*$B52)*'A1 Inputs'!$C$21+'A1 Orbital'!$C$5*'A1 Inputs'!$C$21*$C$48+('A1 Orbital'!$C$5*$C$48+(('A1 Inputs'!$C$6*1000000)*$B52)+'A1 Orbital'!$C$13*$C$48)*'A1 Inputs'!$C$22)/((('A1 Inputs'!$C$6*1000000)*G$51)*'A1 Inputs'!$C$32*'A1 Terrestrial'!$C$9+(('A1 Inputs'!$C$6*1000000)*G$51)*(1-'A1 Inputs'!$C$32)*'A1 Terrestrial'!$C$10+'A1 Terrestrial'!$C$14+(('A1 Inputs'!$C$6*1000000)*G$51)*'A1 Inputs'!$C$35) -> 0.42603199
B53: 40 | C53: =(('A1 Orbital'!$C$5*$C$48+(('A1 Inputs'!$C$6*1000000)*$B53)+'A1 Orbital'!$C$13*$C$48)*'A1 Orbital'!$C$18+(('A1 Inputs'!$C$6*1000000)*$B53)*'A1 Inputs'!$C$21+'A1 Orbital'!$C$5*'A1 Inputs'!$C$21*$C$48+('A1 Orbital'!$C$5*$C$48+(('A1 Inputs'!$C$6*1000000)*$B53)+'A1 Orbital'!$C$13*$C$48)*'A1 Inputs'!$C$22)/((('A1 Inputs'!$C$6*1000000)*C$51)*'A1 Inputs'!$C$32*'A1 Terrestrial'!$C$9+(('A1 Inputs'!$C$6*1000000)*C$51)*(1-'A1 Inputs'!$C$32)*'A1 Terrestrial'!$C$10+'A1 Terrestrial'!$C$14+(('A1 Inputs'!$C$6*1000000)*C$51)*'A1 Inputs'!$C$35) -> 1.3345028 | D53: =(('A1 Orbital'!$C$5*$C$48+(('A1 Inputs'!$C$6*1000000)*$B53)+'A1 Orbital'!$C$13*$C$48)*'A1 Orbital'!$C$18+(('A1 Inputs'!$C$6*1000000)*$B53)*'A1 Inputs'!$C$21+'A1 Orbital'!$C$5*'A1 Inputs'!$C$21*$C$48+('A1 Orbital'!$C$5*$C$48+(('A1 Inputs'!$C$6*1000000)*$B53)+'A1 Orbital'!$C$13*$C$48)*'A1 Inputs'!$C$22)/((('A1 Inputs'!$C$6*1000000)*D$51)*'A1 Inputs'!$C$32*'A1 Terrestrial'!$C$9+(('A1 Inputs'!$C$6*1000000)*D$51)*(1-'A1 Inputs'!$C$32)*'A1 Terrestrial'!$C$10+'A1 Terrestrial'!$C$14+(('A1 Inputs'!$C$6*1000000)*D$51)*'A1 Inputs'!$C$35) -> 1.0346389 | E53: =(('A1 Orbital'!$C$5*$C$48+(('A1 Inputs'!$C$6*1000000)*$B53)+'A1 Orbital'!$C$13*$C$48)*'A1 Orbital'!$C$18+(('A1 Inputs'!$C$6*1000000)*$B53)*'A1 Inputs'!$C$21+'A1 Orbital'!$C$5*'A1 Inputs'!$C$21*$C$48+('A1 Orbital'!$C$5*$C$48+(('A1 Inputs'!$C$6*1000000)*$B53)+'A1 Orbital'!$C$13*$C$48)*'A1 Inputs'!$C$22)/((('A1 Inputs'!$C$6*1000000)*E$51)*'A1 Inputs'!$C$32*'A1 Terrestrial'!$C$9+(('A1 Inputs'!$C$6*1000000)*E$51)*(1-'A1 Inputs'!$C$32)*'A1 Terrestrial'!$C$10+'A1 Terrestrial'!$C$14+(('A1 Inputs'!$C$6*1000000)*E$51)*'A1 Inputs'!$C$35) -> 0.75273759 | F53: =(('A1 Orbital'!$C$5*$C$48+(('A1 Inputs'!$C$6*1000000)*$B53)+'A1 Orbital'!$C$13*$C$48)*'A1 Orbital'!$C$18+(('A1 Inputs'!$C$6*1000000)*$B53)*'A1 Inputs'!$C$21+'A1 Orbital'!$C$5*'A1 Inputs'!$C$21*$C$48+('A1 Orbital'!$C$5*$C$48+(('A1 Inputs'!$C$6*1000000)*$B53)+'A1 Orbital'!$C$13*$C$48)*'A1 Inputs'!$C$22)/((('A1 Inputs'!$C$6*1000000)*F$51)*'A1 Inputs'!$C$32*'A1 Terrestrial'!$C$9+(('A1 Inputs'!$C$6*1000000)*F$51)*(1-'A1 Inputs'!$C$32)*'A1 Terrestrial'!$C$10+'A1 Terrestrial'!$C$14+(('A1 Inputs'!$C$6*1000000)*F$51)*'A1 Inputs'!$C$35) -> 0.53435093 | G53: =(('A1 Orbital'!$C$5*$C$48+(('A1 Inputs'!$C$6*1000000)*$B53)+'A1 Orbital'!$C$13*$C$48)*'A1 Orbital'!$C$18+(('A1 Inputs'!$C$6*1000000)*$B53)*'A1 Inputs'!$C$21+'A1 Orbital'!$C$5*'A1 Inputs'!$C$21*$C$48+('A1 Orbital'!$C$5*$C$48+(('A1 Inputs'!$C$6*1000000)*$B53)+'A1 Orbital'!$C$13*$C$48)*'A1 Inputs'!$C$22)/((('A1 Inputs'!$C$6*1000000)*G$51)*'A1 Inputs'!$C$32*'A1 Terrestrial'!$C$9+(('A1 Inputs'!$C$6*1000000)*G$51)*(1-'A1 Inputs'!$C$32)*'A1 Terrestrial'!$C$10+'A1 Terrestrial'!$C$14+(('A1 Inputs'!$C$6*1000000)*G$51)*'A1 Inputs'!$C$35) -> 0.36018672
B54: 30 | C54: =(('A1 Orbital'!$C$5*$C$48+(('A1 Inputs'!$C$6*1000000)*$B54)+'A1 Orbital'!$C$13*$C$48)*'A1 Orbital'!$C$18+(('A1 Inputs'!$C$6*1000000)*$B54)*'A1 Inputs'!$C$21+'A1 Orbital'!$C$5*'A1 Inputs'!$C$21*$C$48+('A1 Orbital'!$C$5*$C$48+(('A1 Inputs'!$C$6*1000000)*$B54)+'A1 Orbital'!$C$13*$C$48)*'A1 Inputs'!$C$22)/((('A1 Inputs'!$C$6*1000000)*C$51)*'A1 Inputs'!$C$32*'A1 Terrestrial'!$C$9+(('A1 Inputs'!$C$6*1000000)*C$51)*(1-'A1 Inputs'!$C$32)*'A1 Terrestrial'!$C$10+'A1 Terrestrial'!$C$14+(('A1 Inputs'!$C$6*1000000)*C$51)*'A1 Inputs'!$C$35) -> 1.0634375 | D54: =(('A1 Orbital'!$C$5*$C$48+(('A1 Inputs'!$C$6*1000000)*$B54)+'A1 Orbital'!$C$13*$C$48)*'A1 Orbital'!$C$18+(('A1 Inputs'!$C$6*1000000)*$B54)*'A1 Inputs'!$C$21+'A1 Orbital'!$C$5*'A1 Inputs'!$C$21*$C$48+('A1 Orbital'!$C$5*$C$48+(('A1 Inputs'!$C$6*1000000)*$B54)+'A1 Orbital'!$C$13*$C$48)*'A1 Inputs'!$C$22)/((('A1 Inputs'!$C$6*1000000)*D$51)*'A1 Inputs'!$C$32*'A1 Terrestrial'!$C$9+(('A1 Inputs'!$C$6*1000000)*D$51)*(1-'A1 Inputs'!$C$32)*'A1 Terrestrial'!$C$10+'A1 Terrestrial'!$C$14+(('A1 Inputs'!$C$6*1000000)*D$51)*'A1 Inputs'!$C$35) -> 0.82448219 | E54: =(('A1 Orbital'!$C$5*$C$48+(('A1 Inputs'!$C$6*1000000)*$B54)+'A1 Orbital'!$C$13*$C$48)*'A1 Orbital'!$C$18+(('A1 Inputs'!$C$6*1000000)*$B54)*'A1 Inputs'!$C$21+'A1 Orbital'!$C$5*'A1 Inputs'!$C$21*$C$48+('A1 Orbital'!$C$5*$C$48+(('A1 Inputs'!$C$6*1000000)*$B54)+'A1 Orbital'!$C$13*$C$48)*'A1 Inputs'!$C$22)/((('A1 Inputs'!$C$6*1000000)*E$51)*'A1 Inputs'!$C$32*'A1 Terrestrial'!$C$9+(('A1 Inputs'!$C$6*1000000)*E$51)*(1-'A1 Inputs'!$C$32)*'A1 Terrestrial'!$C$10+'A1 Terrestrial'!$C$14+(('A1 Inputs'!$C$6*1000000)*E$51)*'A1 Inputs'!$C$35) -> 0.59984092 | F54: =(('A1 Orbital'!$C$5*$C$48+(('A1 Inputs'!$C$6*1000000)*$B54)+'A1 Orbital'!$C$13*$C$48)*'A1 Orbital'!$C$18+(('A1 Inputs'!$C$6*1000000)*$B54)*'A1 Inputs'!$C$21+'A1 Orbital'!$C$5*'A1 Inputs'!$C$21*$C$48+('A1 Orbital'!$C$5*$C$48+(('A1 Inputs'!$C$6*1000000)*$B54)+'A1 Orbital'!$C$13*$C$48)*'A1 Inputs'!$C$22)/((('A1 Inputs'!$C$6*1000000)*F$51)*'A1 Inputs'!$C$32*'A1 Terrestrial'!$C$9+(('A1 Inputs'!$C$6*1000000)*F$51)*(1-'A1 Inputs'!$C$32)*'A1 Terrestrial'!$C$10+'A1 Terrestrial'!$C$14+(('A1 Inputs'!$C$6*1000000)*F$51)*'A1 Inputs'!$C$35) -> 0.42581314 | G54: =(('A1 Orbital'!$C$5*$C$48+(('A1 Inputs'!$C$6*1000000)*$B54)+'A1 Orbital'!$C$13*$C$48)*'A1 Orbital'!$C$18+(('A1 Inputs'!$C$6*1000000)*$B54)*'A1 Inputs'!$C$21+'A1 Orbital'!$C$5*'A1 Inputs'!$C$21*$C$48+('A1 Orbital'!$C$5*$C$48+(('A1 Inputs'!$C$6*1000000)*$B54)+'A1 Orbital'!$C$13*$C$48)*'A1 Inputs'!$C$22)/((('A1 Inputs'!$C$6*1000000)*G$51)*'A1 Inputs'!$C$32*'A1 Terrestrial'!$C$9+(('A1 Inputs'!$C$6*1000000)*G$51)*(1-'A1 Inputs'!$C$32)*'A1 Terrestrial'!$C$10+'A1 Terrestrial'!$C$14+(('A1 Inputs'!$C$6*1000000)*G$51)*'A1 Inputs'!$C$35) -> 0.2870253
B55: 25 | C55: =(('A1 Orbital'!$C$5*$C$48+(('A1 Inputs'!$C$6*1000000)*$B55)+'A1 Orbital'!$C$13*$C$48)*'A1 Orbital'!$C$18+(('A1 Inputs'!$C$6*1000000)*$B55)*'A1 Inputs'!$C$21+'A1 Orbital'!$C$5*'A1 Inputs'!$C$21*$C$48+('A1 Orbital'!$C$5*$C$48+(('A1 Inputs'!$C$6*1000000)*$B55)+'A1 Orbital'!$C$13*$C$48)*'A1 Inputs'!$C$22)/((('A1 Inputs'!$C$6*1000000)*C$51)*'A1 Inputs'!$C$32*'A1 Terrestrial'!$C$9+(('A1 Inputs'!$C$6*1000000)*C$51)*(1-'A1 Inputs'!$C$32)*'A1 Terrestrial'!$C$10+'A1 Terrestrial'!$C$14+(('A1 Inputs'!$C$6*1000000)*C$51)*'A1 Inputs'!$C$35) -> 0.92790485 | D55: =(('A1 Orbital'!$C$5*$C$48+(('A1 Inputs'!$C$6*1000000)*$B55)+'A1 Orbital'!$C$13*$C$48)*'A1 Orbital'!$C$18+(('A1 Inputs'!$C$6*1000000)*$B55)*'A1 Inputs'!$C$21+'A1 Orbital'!$C$5*'A1 Inputs'!$C$21*$C$48+('A1 Orbital'!$C$5*$C$48+(('A1 Inputs'!$C$6*1000000)*$B55)+'A1 Orbital'!$C$13*$C$48)*'A1 Inputs'!$C$22)/((('A1 Inputs'!$C$6*1000000)*D$51)*'A1 Inputs'!$C$32*'A1 Terrestrial'!$C$9+(('A1 Inputs'!$C$6*1000000)*D$51)*(1-'A1 Inputs'!$C$32)*'A1 Terrestrial'!$C$10+'A1 Terrestrial'!$C$14+(('A1 Inputs'!$C$6*1000000)*D$51)*'A1 Inputs'!$C$35) -> 0.71940385 | E55: =(('A1 Orbital'!$C$5*$C$48+(('A1 Inputs'!$C$6*1000000)*$B55)+'A1 Orbital'!$C$13*$C$48)*'A1 Orbital'!$C$18+(('A1 Inputs'!$C$6*1000000)*$B55)*'A1 Inputs'!$C$21+'A1 Orbital'!$C$5*'A1 Inputs'!$C$21*$C$48+('A1 Orbital'!$C$5*$C$48+(('A1 Inputs'!$C$6*1000000)*$B55)+'A1 Orbital'!$C$13*$C$48)*'A1 Inputs'!$C$22)/((('A1 Inputs'!$C$6*1000000)*E$51)*'A1 Inputs'!$C$32*'A1 Terrestrial'!$C$9+(('A1 Inputs'!$C$6*1000000)*E$51)*(1-'A1 Inputs'!$C$32)*'A1 Terrestrial'!$C$10+'A1 Terrestrial'!$C$14+(('A1 Inputs'!$C$6*1000000)*E$51)*'A1 Inputs'!$C$35) -> 0.52339259 | F55: =(('A1 Orbital'!$C$5*$C$48+(('A1 Inputs'!$C$6*1000000)*$B55)+'A1 Orbital'!$C$13*$C$48)*'A1 Orbital'!$C$18+(('A1 Inputs'!$C$6*1000000)*$B55)*'A1 Inputs'!$C$21+'A1 Orbital'!$C$5*'A1 Inputs'!$C$21*$C$48+('A1 Orbital'!$C$5*$C$48+(('A1 Inputs'!$C$6*1000000)*$B55)+'A1 Orbital'!$C$13*$C$48)*'A1 Inputs'!$C$22)/((('A1 Inputs'!$C$6*1000000)*F$51)*'A1 Inputs'!$C$32*'A1 Terrestrial'!$C$9+(('A1 Inputs'!$C$6*1000000)*F$51)*(1-'A1 Inputs'!$C$32)*'A1 Terrestrial'!$C$10+'A1 Terrestrial'!$C$14+(('A1 Inputs'!$C$6*1000000)*F$51)*'A1 Inputs'!$C$35) -> 0.37154425 | G55: =(('A1 Orbital'!$C$5*$C$48+(('A1 Inputs'!$C$6*1000000)*$B55)+'A1 Orbital'!$C$13*$C$48)*'A1 Orbital'!$C$18+(('A1 Inputs'!$C$6*1000000)*$B55)*'A1 Inputs'!$C$21+'A1 Orbital'!$C$5*'A1 Inputs'!$C$21*$C$48+('A1 Orbital'!$C$5*$C$48+(('A1 Inputs'!$C$6*1000000)*$B55)+'A1 Orbital'!$C$13*$C$48)*'A1 Inputs'!$C$22)/((('A1 Inputs'!$C$6*1000000)*G$51)*'A1 Inputs'!$C$32*'A1 Terrestrial'!$C$9+(('A1 Inputs'!$C$6*1000000)*G$51)*(1-'A1 Inputs'!$C$32)*'A1 Terrestrial'!$C$10+'A1 Terrestrial'!$C$14+(('A1 Inputs'!$C$6*1000000)*G$51)*'A1 Inputs'!$C$35) -> 0.25044459
B56: 20 | C56: =(('A1 Orbital'!$C$5*$C$48+(('A1 Inputs'!$C$6*1000000)*$B56)+'A1 Orbital'!$C$13*$C$48)*'A1 Orbital'!$C$18+(('A1 Inputs'!$C$6*1000000)*$B56)*'A1 Inputs'!$C$21+'A1 Orbital'!$C$5*'A1 Inputs'!$C$21*$C$48+('A1 Orbital'!$C$5*$C$48+(('A1 Inputs'!$C$6*1000000)*$B56)+'A1 Orbital'!$C$13*$C$48)*'A1 Inputs'!$C$22)/((('A1 Inputs'!$C$6*1000000)*C$51)*'A1 Inputs'!$C$32*'A1 Terrestrial'!$C$9+(('A1 Inputs'!$C$6*1000000)*C$51)*(1-'A1 Inputs'!$C$32)*'A1 Terrestrial'!$C$10+'A1 Terrestrial'!$C$14+(('A1 Inputs'!$C$6*1000000)*C$51)*'A1 Inputs'!$C$35) -> 0.79237221 | D56: =(('A1 Orbital'!$C$5*$C$48+(('A1 Inputs'!$C$6*1000000)*$B56)+'A1 Orbital'!$C$13*$C$48)*'A1 Orbital'!$C$18+(('A1 Inputs'!$C$6*1000000)*$B56)*'A1 Inputs'!$C$21+'A1 Orbital'!$C$5*'A1 Inputs'!$C$21*$C$48+('A1 Orbital'!$C$5*$C$48+(('A1 Inputs'!$C$6*1000000)*$B56)+'A1 Orbital'!$C$13*$C$48)*'A1 Inputs'!$C$22)/((('A1 Inputs'!$C$6*1000000)*D$51)*'A1 Inputs'!$C$32*'A1 Terrestrial'!$C$9+(('A1 Inputs'!$C$6*1000000)*D$51)*(1-'A1 Inputs'!$C$32)*'A1 Terrestrial'!$C$10+'A1 Terrestrial'!$C$14+(('A1 Inputs'!$C$6*1000000)*D$51)*'A1 Inputs'!$C$35) -> 0.61432551 | E56: =(('A1 Orbital'!$C$5*$C$48+(('A1 Inputs'!$C$6*1000000)*$B56)+'A1 Orbital'!$C$13*$C$48)*'A1 Orbital'!$C$18+(('A1 Inputs'!$C$6*1000000)*$B56)*'A1 Inputs'!$C$21+'A1 Orbital'!$C$5*'A1 Inputs'!$C$21*$C$48+('A1 Orbital'!$C$5*$C$48+(('A1 Inputs'!$C$6*1000000)*$B56)+'A1 Orbital'!$C$13*$C$48)*'A1 Inputs'!$C$22)/((('A1 Inputs'!$C$6*1000000)*E$51)*'A1 Inputs'!$C$32*'A1 Terrestrial'!$C$9+(('A1 Inputs'!$C$6*1000000)*E$51)*(1-'A1 Inputs'!$C$32)*'A1 Terrestrial'!$C$10+'A1 Terrestrial'!$C$14+(('A1 Inputs'!$C$6*1000000)*E$51)*'A1 Inputs'!$C$35) -> 0.44694426 | F56: =(('A1 Orbital'!$C$5*$C$48+(('A1 Inputs'!$C$6*1000000)*$B56)+'A1 Orbital'!$C$13*$C$48)*'A1 Orbital'!$C$18+(('A1 Inputs'!$C$6*1000000)*$B56)*'A1 Inputs'!$C$21+'A1 Orbital'!$C$5*'A1 Inputs'!$C$21*$C$48+('A1 Orbital'!$C$5*$C$48+(('A1 Inputs'!$C$6*1000000)*$B56)+'A1 Orbital'!$C$13*$C$48)*'A1 Inputs'!$C$22)/((('A1 Inputs'!$C$6*1000000)*F$51)*'A1 Inputs'!$C$32*'A1 Terrestrial'!$C$9+(('A1 Inputs'!$C$6*1000000)*F$51)*(1-'A1 Inputs'!$C$32)*'A1 Terrestrial'!$C$10+'A1 Terrestrial'!$C$14+(('A1 Inputs'!$C$6*1000000)*F$51)*'A1 Inputs'!$C$35) -> 0.31727535 | G56: =(('A1 Orbital'!$C$5*$C$48+(('A1 Inputs'!$C$6*1000000)*$B56)+'A1 Orbital'!$C$13*$C$48)*'A1 Orbital'!$C$18+(('A1 Inputs'!$C$6*1000000)*$B56)*'A1 Inputs'!$C$21+'A1 Orbital'!$C$5*'A1 Inputs'!$C$21*$C$48+('A1 Orbital'!$C$5*$C$48+(('A1 Inputs'!$C$6*1000000)*$B56)+'A1 Orbital'!$C$13*$C$48)*'A1 Inputs'!$C$22)/((('A1 Inputs'!$C$6*1000000)*G$51)*'A1 Inputs'!$C$32*'A1 Terrestrial'!$C$9+(('A1 Inputs'!$C$6*1000000)*G$51)*(1-'A1 Inputs'!$C$32)*'A1 Terrestrial'!$C$10+'A1 Terrestrial'!$C$14+(('A1 Inputs'!$C$6*1000000)*G$51)*'A1 Inputs'!$C$35) -> 0.21386388
B57: 15 | C57: =(('A1 Orbital'!$C$5*$C$48+(('A1 Inputs'!$C$6*1000000)*$B57)+'A1 Orbital'!$C$13*$C$48)*'A1 Orbital'!$C$18+(('A1 Inputs'!$C$6*1000000)*$B57)*'A1 Inputs'!$C$21+'A1 Orbital'!$C$5*'A1 Inputs'!$C$21*$C$48+('A1 Orbital'!$C$5*$C$48+(('A1 Inputs'!$C$6*1000000)*$B57)+'A1 Orbital'!$C$13*$C$48)*'A1 Inputs'!$C$22)/((('A1 Inputs'!$C$6*1000000)*C$51)*'A1 Inputs'!$C$32*'A1 Terrestrial'!$C$9+(('A1 Inputs'!$C$6*1000000)*C$51)*(1-'A1 Inputs'!$C$32)*'A1 Terrestrial'!$C$10+'A1 Terrestrial'!$C$14+(('A1 Inputs'!$C$6*1000000)*C$51)*'A1 Inputs'!$C$35) -> 0.65683957 | D57: =(('A1 Orbital'!$C$5*$C$48+(('A1 Inputs'!$C$6*1000000)*$B57)+'A1 Orbital'!$C$13*$C$48)*'A1 Orbital'!$C$18+(('A1 Inputs'!$C$6*1000000)*$B57)*'A1 Inputs'!$C$21+'A1 Orbital'!$C$5*'A1 Inputs'!$C$21*$C$48+('A1 Orbital'!$C$5*$C$48+(('A1 Inputs'!$C$6*1000000)*$B57)+'A1 Orbital'!$C$13*$C$48)*'A1 Inputs'!$C$22)/((('A1 Inputs'!$C$6*1000000)*D$51)*'A1 Inputs'!$C$32*'A1 Terrestrial'!$C$9+(('A1 Inputs'!$C$6*1000000)*D$51)*(1-'A1 Inputs'!$C$32)*'A1 Terrestrial'!$C$10+'A1 Terrestrial'!$C$14+(('A1 Inputs'!$C$6*1000000)*D$51)*'A1 Inputs'!$C$35) -> 0.50924717 | E57: =(('A1 Orbital'!$C$5*$C$48+(('A1 Inputs'!$C$6*1000000)*$B57)+'A1 Orbital'!$C$13*$C$48)*'A1 Orbital'!$C$18+(('A1 Inputs'!$C$6*1000000)*$B57)*'A1 Inputs'!$C$21+'A1 Orbital'!$C$5*'A1 Inputs'!$C$21*$C$48+('A1 Orbital'!$C$5*$C$48+(('A1 Inputs'!$C$6*1000000)*$B57)+'A1 Orbital'!$C$13*$C$48)*'A1 Inputs'!$C$22)/((('A1 Inputs'!$C$6*1000000)*E$51)*'A1 Inputs'!$C$32*'A1 Terrestrial'!$C$9+(('A1 Inputs'!$C$6*1000000)*E$51)*(1-'A1 Inputs'!$C$32)*'A1 Terrestrial'!$C$10+'A1 Terrestrial'!$C$14+(('A1 Inputs'!$C$6*1000000)*E$51)*'A1 Inputs'!$C$35) -> 0.37049592 | F57: =(('A1 Orbital'!$C$5*$C$48+(('A1 Inputs'!$C$6*1000000)*$B57)+'A1 Orbital'!$C$13*$C$48)*'A1 Orbital'!$C$18+(('A1 Inputs'!$C$6*1000000)*$B57)*'A1 Inputs'!$C$21+'A1 Orbital'!$C$5*'A1 Inputs'!$C$21*$C$48+('A1 Orbital'!$C$5*$C$48+(('A1 Inputs'!$C$6*1000000)*$B57)+'A1 Orbital'!$C$13*$C$48)*'A1 Inputs'!$C$22)/((('A1 Inputs'!$C$6*1000000)*F$51)*'A1 Inputs'!$C$32*'A1 Terrestrial'!$C$9+(('A1 Inputs'!$C$6*1000000)*F$51)*(1-'A1 Inputs'!$C$32)*'A1 Terrestrial'!$C$10+'A1 Terrestrial'!$C$14+(('A1 Inputs'!$C$6*1000000)*F$51)*'A1 Inputs'!$C$35) -> 0.26300645 | G57: =(('A1 Orbital'!$C$5*$C$48+(('A1 Inputs'!$C$6*1000000)*$B57)+'A1 Orbital'!$C$13*$C$48)*'A1 Orbital'!$C$18+(('A1 Inputs'!$C$6*1000000)*$B57)*'A1 Inputs'!$C$21+'A1 Orbital'!$C$5*'A1 Inputs'!$C$21*$C$48+('A1 Orbital'!$C$5*$C$48+(('A1 Inputs'!$C$6*1000000)*$B57)+'A1 Orbital'!$C$13*$C$48)*'A1 Inputs'!$C$22)/((('A1 Inputs'!$C$6*1000000)*G$51)*'A1 Inputs'!$C$32*'A1 Terrestrial'!$C$9+(('A1 Inputs'!$C$6*1000000)*G$51)*(1-'A1 Inputs'!$C$32)*'A1 Terrestrial'!$C$10+'A1 Terrestrial'!$C$14+(('A1 Inputs'!$C$6*1000000)*G$51)*'A1 Inputs'!$C$35) -> 0.17728318
B59: Metric = orbital ÷ terrestrial ANNUAL cost = the inference cost-per-effective-PFLOP-hr ratio (orbital & terrestrial MFU equal for batch inference, so the PFLOP terms cancel). Set the scenario launch to $1,000 and the (49, 38) cell returns the base-case 2.16x — ties to Effective Compute.
B61: LAUNCH-COST REFERENCE — what a $/kg target means per launch (context for the launch lever)
B62: Cost per launch = $/kg x payload. $200-300/kg is ~$20-45M/launch — about 3x HIGHER than SpaceX's ~$10M/launch target, so the crossover threshold is reached BEFORE Starship hits its own cost goals. A reusability / cost-per-launch problem, not a per-hour-cadence one.
B63: Launch $/kg \ Payload -> | C63: 150 | D63: 100 | E63: (= cost per launch, $M)
B64: 200 | C64: =$B64*C$63/1000 -> 30 | D64: =$B64*D$63/1000 -> 20
B65: 300 | C65: =$B65*C$63/1000 -> 45 | D65: =$B65*D$63/1000 -> 30
B66: 500 | C66: =$B66*C$63/1000 -> 75 | D66: =$B66*D$63/1000 -> 50
B67: 1000 | C67: =$B67*C$63/1000 -> 150 | D67: =$B67*D$63/1000 -> 100
B69: Cost/launch ($M) \ Payload -> | C69: 150 | D69: 100 | E69: (= $/kg)
B70: 10 | C70: =$B70*1000/C$69 -> 66.666667 | D70: =$B70*1000/D$69 -> 100
B71: 3 | C71: =$B71*1000/C$69 -> 20 | D71: =$B71*1000/D$69 -> 30
B72: 2 | C72: =$B72*1000/C$69 -> 13.333333 | D72: =$B72*1000/D$69 -> 20
B73: 1 | C73: =$B73*1000/C$69 -> 6.6666667 | D73: =$B73*1000/D$69 -> 10
B75: Read: SpaceX's ~$10M/launch target = ~$67/kg at 150 t — already below the $200-300/kg crossover band. Per-hour/daily cadence is what drives cost toward the $7-20/kg floor and what deploys terawatt-scale VOLUME — a separate question from the price-per-kg crossover.
B77: J. Shapiro · Prepared as an independent work sample · all figures public-sourced or labeled illustrative

Sheet A2 Inputs
B2: INPUTS & ASSUMPTIONS
B3: Most cost inputs here are [SPX-IN] placeholders — replace with real Bastrop figures to make it a live tool.
B5: COMPONENT & VOLUME
B6: Component | C6: RF packaging | E6: [FACT] | F6: Bastrop insourcing RF-chip packaging; line targeted end-2026
B7: Year-1 annual volume | C7: 2000000 | D7: units/yr | E7: [SPX-IN] | F7: Illustrative; tie to ~15,000 dishes/day = ~5.5M/yr terminal run-rate
B8: Annual volume growth | C8: 0.25 | D8: %/yr | E8: [EST] | F8: US kit output +62% over 9 mo in 2025; assume 25%/yr
B9: Analysis horizon (structural) | C9: 7 | D9: years | E9: [EST] | F9: Standard capex horizon
B10: Discount rate (WACC) | C10: ='Global Assumptions'!$C$6 -> 0.12 | D10: %/yr | E10: [SPX-IN] | F10: Placeholder cost of capital
B12: BUY (outsource) PATH
B13: Outsourced unit price (Y1) | C13: 4.5 | D13: $/unit | E13: [SPX-IN] | F13: Illustrative current vendor price incl margin
B14: Vendor price escalation | C14: 0.03 | D14: %/yr | E14: [EST] | F14: Annual price increase
B16: BUILD (insource) PATH
B17: Line capex (equipment+install) | C17: 35000000 | D17: $ | E17: [SPX-IN] | F17: Illustrative packaging line; replace w/ real equipment quote
B18: Equipment depreciation life (ref. only) | C18: 7 | D18: years | E18: [EST] | F18: Reference only — this is a pure cash NPV model and does not depreciate. Shown for context.
B19: In-house unit cost at Y1 volume | C19: 3.6 | D19: $/unit | E19: [SPX-IN] | F19: BOM+labor+overhead at the Year-1 cumulative volume anchor (not unit 1). Learning applies to doublings beyond Y1.
B20: Learning rate (Wright's law) | C20: 0.85 | D20: % | E20: [FACT] | F20: Electronics typically 85-90%: 15% cost cut per cumulative doubling
B21: Year-1 yield | C21: 0.8 | D21: % | E21: [EST] | F21: Ramp yield; improves to mature
B22: Mature yield | C22: 0.97 | D22: % | E22: [EST] | F22: Steady-state
B23: Fixed line opex | C23: 0.06 | D23: %capex/yr | E23: [EST] | F23: Maintenance/utilities/staff as % of capex
B26: J. Shapiro · Independent work sample · illustrative inputs labeled [SPX-IN]

Sheet A2 BuildVsBuy
B2: BUILD vs BUY — ANNUAL CASH FLOWS
B4: Year | C4: 1 | D4: 2 | E4: 3 | F4: 4 | G4: 5 | H4: 6 | I4: 7
B5: Annual volume (units) | C5: ='A2 Inputs'!$C$7 -> 2000000 | D5: =C5*(1+'A2 Inputs'!$C$8) -> 2500000 | E5: =D5*(1+'A2 Inputs'!$C$8) -> 3125000 | F5: =E5*(1+'A2 Inputs'!$C$8) -> 3906250 | G5: =F5*(1+'A2 Inputs'!$C$8) -> 4882812.5 | H5: =G5*(1+'A2 Inputs'!$C$8) -> 6103515.6 | I5: =H5*(1+'A2 Inputs'!$C$8) -> 7629394.5
B6: Cumulative volume | C6: =C5 -> 2000000 | D6: =C6+D5 -> 4500000 | E6: =D6+E5 -> 7625000 | F6: =E6+F5 -> 11531250 | G6: =F6+G5 -> 16414062 | H6: =G6+H5 -> 22517578 | I6: =H6+I5 -> 30146973
B8: BUY: outsourced cost ($) | C8: =C5*'A2 Inputs'!$C$13*(1+'A2 Inputs'!$C$14)^0 -> 9000000 | D8: =D5*'A2 Inputs'!$C$13*(1+'A2 Inputs'!$C$14)^1 -> 11587500 | E8: =E5*'A2 Inputs'!$C$13*(1+'A2 Inputs'!$C$14)^2 -> 14918906 | F8: =F5*'A2 Inputs'!$C$13*(1+'A2 Inputs'!$C$14)^3 -> 19208092 | G8: =G5*'A2 Inputs'!$C$13*(1+'A2 Inputs'!$C$14)^4 -> 24730418 | H8: =H5*'A2 Inputs'!$C$13*(1+'A2 Inputs'!$C$14)^5 -> 31840413 | I8: =I5*'A2 Inputs'!$C$13*(1+'A2 Inputs'!$C$14)^6 -> 40994532
B10: BUILD: in-house unit cost ($) | C10: ='A2 Inputs'!$C$19*((C6/$C$6)^(LOG('A2 Inputs'!$C$20,2)))/('A2 Inputs'!$C$21+('A2 Inputs'!$C$22-'A2 Inputs'!$C$21)*MIN(1,0/3)) -> 4.5 | D10: ='A2 Inputs'!$C$19*((D6/$C$6)^(LOG('A2 Inputs'!$C$20,2)))/('A2 Inputs'!$C$21+('A2 Inputs'!$C$22-'A2 Inputs'!$C$21)*MIN(1,1/3)) -> 3.47469 | E10: ='A2 Inputs'!$C$19*((E6/$C$6)^(LOG('A2 Inputs'!$C$20,2)))/('A2 Inputs'!$C$21+('A2 Inputs'!$C$22-'A2 Inputs'!$C$21)*MIN(1,2/3)) -> 2.8800477 | F10: ='A2 Inputs'!$C$19*((F6/$C$6)^(LOG('A2 Inputs'!$C$20,2)))/('A2 Inputs'!$C$21+('A2 Inputs'!$C$22-'A2 Inputs'!$C$21)*MIN(1,3/3)) -> 2.4611536 | G10: ='A2 Inputs'!$C$19*((G6/$C$6)^(LOG('A2 Inputs'!$C$20,2)))/('A2 Inputs'!$C$21+('A2 Inputs'!$C$22-'A2 Inputs'!$C$21)*MIN(1,4/3)) -> 2.2656139 | H10: ='A2 Inputs'!$C$19*((H6/$C$6)^(LOG('A2 Inputs'!$C$20,2)))/('A2 Inputs'!$C$21+('A2 Inputs'!$C$22-'A2 Inputs'!$C$21)*MIN(1,5/3)) -> 2.1037421 | I10: ='A2 Inputs'!$C$19*((I6/$C$6)^(LOG('A2 Inputs'!$C$20,2)))/('A2 Inputs'!$C$21+('A2 Inputs'!$C$22-'A2 Inputs'!$C$21)*MIN(1,6/3)) -> 1.9646292
B11: BUILD: variable cost ($) | C11: =C5*C10 -> 9000000 | D11: =D5*D10 -> 8686725.1 | E11: =E5*E10 -> 9000149 | F11: =F5*F10 -> 9613881.4 | G11: =G5*G10 -> 11062568 | H11: =H5*H10 -> 12840223 | I11: =I5*I10 -> 14988931
B12: BUILD: fixed line opex ($) | C12: ='A2 Inputs'!$C$17*'A2 Inputs'!$C$23 -> 2100000 | D12: ='A2 Inputs'!$C$17*'A2 Inputs'!$C$23 -> 2100000 | E12: ='A2 Inputs'!$C$17*'A2 Inputs'!$C$23 -> 2100000 | F12: ='A2 Inputs'!$C$17*'A2 Inputs'!$C$23 -> 2100000 | G12: ='A2 Inputs'!$C$17*'A2 Inputs'!$C$23 -> 2100000 | H12: ='A2 Inputs'!$C$17*'A2 Inputs'!$C$23 -> 2100000 | I12: ='A2 Inputs'!$C$17*'A2 Inputs'!$C$23 -> 2100000
B13: BUILD: capex ($) | C13: ='A2 Inputs'!$C$17 -> 35000000 | D13: =0 -> 0 | E13: =0 -> 0 | F13: =0 -> 0 | G13: =0 -> 0 | H13: =0 -> 0 | I13: =0 -> 0
B14: BUILD: total cost ($) | C14: =C11+C12+C13 -> 46100000 | D14: =D11+D12+D13 -> 10786725 | E14: =E11+E12+E13 -> 11100149 | F14: =F11+F12+F13 -> 11713881 | G14: =G11+G12+G13 -> 13162568 | H14: =H11+H12+H13 -> 14940223 | I14: =I11+I12+I13 -> 17088931
B16: Annual saving (Buy - Build) ($) | C16: =C8-C14 -> -37100000 | D16: =D8-D14 -> 800774.91 | E16: =E8-E14 -> 3818757.3 | F16: =F8-F14 -> 7494210.4 | G16: =G8-G14 -> 11567850 | H16: =H8-H14 -> 16900191 | I16: =I8-I14 -> 23905601
B17: Discounted saving ($) | C17: =C16/(1+'A2 Inputs'!$C$10)^1 -> -33125000 | D17: =D16/(1+'A2 Inputs'!$C$10)^2 -> 638372.86 | E17: =E16/(1+'A2 Inputs'!$C$10)^3 -> 2718116 | F17: =F16/(1+'A2 Inputs'!$C$10)^4 -> 4762706.2 | G17: =G16/(1+'A2 Inputs'!$C$10)^5 -> 6563909 | H17: =H16/(1+'A2 Inputs'!$C$10)^6 -> 8562162.5 | I17: =I16/(1+'A2 Inputs'!$C$10)^7 -> 10813680
B18: Cumulative NPV ($) | C18: =C17 -> -33125000 | D18: =C18+D17 -> -32486627 | E18: =D18+E17 -> -29768511 | F18: =E18+F17 -> -25005805 | G18: =F18+G17 -> -18441896 | H18: =G18+H17 -> -9879733.4 | I18: =H18+I17 -> 933946.48
B21: SUMMARY
B22: Net NPV of insourcing ($) | C22: =I18 -> 933946.48
B23: Mature in-house unit cost ($) | C23: =I10 -> 1.9646292
B24: Mature outsourced price ($) | C24: =I8/I5 -> 5.3732353
B25: Unit cost advantage at maturity ($) | C25: =C24-C23 -> 3.4086062
B28: J. Shapiro · Independent work sample · illustrative inputs labeled [SPX-IN]

Sheet A2 CostCurve
B2: COST-DOWN CURVE & NPV SENSITIVITY
B3: Each (learning rate × Y1 volume) cell reproduces the main tab's per-year logic exactly: 25%/yr volume growth, yield ramp,
B4: normalized Wright's-law curve, per-year discounting. The base case (0.85 / 2.0M) ties to tab 2's headline NPV.
B6: NPV of insourcing ($), 7-yr horizon
B7: LR \ Y1 volume | C7: 1000000 | D7: 2000000 | E7: 3500000 | F7: 5500000 | G7: 8000000
B8: 0.9 | C8: =SUM(C24:I24) -> -23201618 | D8: =SUM(C33:I33) -> -5569347 | E8: =SUM(C42:I42) -> 20879059 | F8: =SUM(C51:I51) -> 56143601 | G8: =SUM(C60:I60) -> 1.0022428e+08
B9: 0.88 | C9: =SUM(C69:I69) -> -21855644 | D9: =SUM(C78:I78) -> -2877399 | E9: =SUM(C87:I87) -> 25589968 | F9: =SUM(C96:I96) -> 63546458 | G9: =SUM(C105:I105) -> 1.1099207e+08
B10: 0.85 | C10: =SUM(C114:I114) -> -19949971 | D10: =SUM(C123:I123) -> 933946.48 | E10: =SUM(C132:I132) -> 32259823 | F10: =SUM(C141:I141) -> 74027658 | G10: =SUM(C150:I150) -> 1.2623745e+08
B11: 0.82 | C11: =SUM(C159:I159) -> -18174658 | D11: =SUM(C168:I168) -> 4484573.4 | E11: =SUM(C177:I177) -> 38473420 | F11: =SUM(C186:I186) -> 83791882 | G11: =SUM(C195:I195) -> 1.4043996e+08
B12: 0.8 | C12: =SUM(C204:I204) -> -17060490 | D12: =SUM(C213:I213) -> 6712909.7 | E12: =SUM(C222:I222) -> 42373008 | F12: =SUM(C231:I231) -> 89919807 | G12: =SUM(C240:I240) -> 1.493533e+08
B14: TIE-OUT: base cell (LR 0.85 / V1 2,000,000) equals tab 2 headline Net NPV by construction (same per-year math). Holds at the DEFAULT LR; the grid varies LR independently, so changing Inputs!C20 moves the headline but not this base cell.
B15: READING: green = insourcing NPV-positive; red = BUY wins. Insourcing needs BOTH adequate volume AND a steep
B16: enough learning rate to amortize the line's fixed capex; below breakeven volume the line is underutilized and BUY wins.
B17: WHAT I'D NEED FROM SPACEX: real line capex, current outsourced price, first-block in-house cost, yield ramp, committed volume. | C17: Y1 | D17: Y2 | E17: Y3 | F17: Y4 | G17: Y5 | H17: Y6 | I17: Y7
B18: vol_t | C18: =1000000*(1+'A2 Inputs'!$C$8)^0 -> 1000000 | D18: =1000000*(1+'A2 Inputs'!$C$8)^1 -> 1250000 | E18: =1000000*(1+'A2 Inputs'!$C$8)^2 -> 1562500 | F18: =1000000*(1+'A2 Inputs'!$C$8)^3 -> 1953125 | G18: =1000000*(1+'A2 Inputs'!$C$8)^4 -> 2441406.2 | H18: =1000000*(1+'A2 Inputs'!$C$8)^5 -> 3051757.8 | I18: =1000000*(1+'A2 Inputs'!$C$8)^6 -> 3814697.3
B19: cumvol_t | C19: =1000000*((1+'A2 Inputs'!$C$8)^1-1)/'A2 Inputs'!$C$8 -> 1000000 | D19: =1000000*((1+'A2 Inputs'!$C$8)^2-1)/'A2 Inputs'!$C$8 -> 2250000 | E19: =1000000*((1+'A2 Inputs'!$C$8)^3-1)/'A2 Inputs'!$C$8 -> 3812500 | F19: =1000000*((1+'A2 Inputs'!$C$8)^4-1)/'A2 Inputs'!$C$8 -> 5765625 | G19: =1000000*((1+'A2 Inputs'!$C$8)^5-1)/'A2 Inputs'!$C$8 -> 8207031.2 | H19: =1000000*((1+'A2 Inputs'!$C$8)^6-1)/'A2 Inputs'!$C$8 -> 11258789 | I19: =1000000*((1+'A2 Inputs'!$C$8)^7-1)/'A2 Inputs'!$C$8 -> 15073486
B20: yield_t | C20: ='A2 Inputs'!$C$21+('A2 Inputs'!$C$22-'A2 Inputs'!$C$21)*MIN(1,(0)/3) -> 0.8 | D20: ='A2 Inputs'!$C$21+('A2 Inputs'!$C$22-'A2 Inputs'!$C$21)*MIN(1,(1)/3) -> 0.85666667 | E20: ='A2 Inputs'!$C$21+('A2 Inputs'!$C$22-'A2 Inputs'!$C$21)*MIN(1,(2)/3) -> 0.91333333 | F20: ='A2 Inputs'!$C$21+('A2 Inputs'!$C$22-'A2 Inputs'!$C$21)*MIN(1,(3)/3) -> 0.97 | G20: ='A2 Inputs'!$C$21+('A2 Inputs'!$C$22-'A2 Inputs'!$C$21)*MIN(1,(4)/3) -> 0.97 | H20: ='A2 Inputs'!$C$21+('A2 Inputs'!$C$22-'A2 Inputs'!$C$21)*MIN(1,(5)/3) -> 0.97 | I20: ='A2 Inputs'!$C$21+('A2 Inputs'!$C$22-'A2 Inputs'!$C$21)*MIN(1,(6)/3) -> 0.97
B21: inhouse_t | C21: ='A2 Inputs'!$C$19*((C19/1000000)^(LOG(0.9,2)))/C20 -> 4.5 | D21: ='A2 Inputs'!$C$19*((D19/1000000)^(LOG(0.9,2)))/D20 -> 3.7149913 | E21: ='A2 Inputs'!$C$19*((E19/1000000)^(LOG(0.9,2)))/E20 -> 3.2160848 | F21: ='A2 Inputs'!$C$19*((F19/1000000)^(LOG(0.9,2)))/F20 -> 2.8436737 | G21: ='A2 Inputs'!$C$19*((G19/1000000)^(LOG(0.9,2)))/G20 -> 2.69508 | H21: ='A2 Inputs'!$C$19*((H19/1000000)^(LOG(0.9,2)))/H20 -> 2.5686254 | I21: ='A2 Inputs'!$C$19*((I19/1000000)^(LOG(0.9,2)))/I20 -> 2.4571894
B22: buy_t | C22: =C18*'A2 Inputs'!$C$13*(1+'A2 Inputs'!$C$14)^0 -> 4500000 | D22: =D18*'A2 Inputs'!$C$13*(1+'A2 Inputs'!$C$14)^1 -> 5793750 | E22: =E18*'A2 Inputs'!$C$13*(1+'A2 Inputs'!$C$14)^2 -> 7459453.1 | F22: =F18*'A2 Inputs'!$C$13*(1+'A2 Inputs'!$C$14)^3 -> 9604045.9 | G22: =G18*'A2 Inputs'!$C$13*(1+'A2 Inputs'!$C$14)^4 -> 12365209 | H22: =H18*'A2 Inputs'!$C$13*(1+'A2 Inputs'!$C$14)^5 -> 15920207 | I22: =I18*'A2 Inputs'!$C$13*(1+'A2 Inputs'!$C$14)^6 -> 20497266
B23: build_t | C23: =C18*C21+'A2 Inputs'!$C$17*'A2 Inputs'!$C$23+'A2 Inputs'!$C$17 -> 41600000 | D23: =D18*D21+'A2 Inputs'!$C$17*'A2 Inputs'!$C$23 -> 6743739.1 | E23: =E18*E21+'A2 Inputs'!$C$17*'A2 Inputs'!$C$23 -> 7125132.6 | F23: =F18*F21+'A2 Inputs'!$C$17*'A2 Inputs'!$C$23 -> 7654050.2 | G23: =G18*G21+'A2 Inputs'!$C$17*'A2 Inputs'!$C$23 -> 8679785 | H23: =H18*H21+'A2 Inputs'!$C$17*'A2 Inputs'!$C$23 -> 9938822.7 | I23: =I18*I21+'A2 Inputs'!$C$17*'A2 Inputs'!$C$23 -> 11473434
B24: disc_t | C24: =(C22-C23)/(1+'A2 Inputs'!$C$10)^1 -> -33125000 | D24: =(D22-D23)/(1+'A2 Inputs'!$C$10)^2 -> -757325.5 | E24: =(E22-E23)/(1+'A2 Inputs'!$C$10)^3 -> 237962.77 | F24: =(F22-F23)/(1+'A2 Inputs'!$C$10)^4 -> 1239257.5 | G24: =(G22-G23)/(1+'A2 Inputs'!$C$10)^5 -> 2091208.6 | H24: =(H22-H23)/(1+'A2 Inputs'!$C$10)^6 -> 3030355.3 | I24: =(I22-I23)/(1+'A2 Inputs'!$C$10)^7 -> 4081923.5
B26: LR 0.9 / V1 2,000,000 | C26: Y1 | D26: Y2 | E26: Y3 | F26: Y4 | G26: Y5 | H26: Y6 | I26: Y7
B27: vol_t | C27: =2000000*(1+'A2 Inputs'!$C$8)^0 -> 2000000 | D27: =2000000*(1+'A2 Inputs'!$C$8)^1 -> 2500000 | E27: =2000000*(1+'A2 Inputs'!$C$8)^2 -> 3125000 | F27: =2000000*(1+'A2 Inputs'!$C$8)^3 -> 3906250 | G27: =2000000*(1+'A2 Inputs'!$C$8)^4 -> 4882812.5 | H27: =2000000*(1+'A2 Inputs'!$C$8)^5 -> 6103515.6 | I27: =2000000*(1+'A2 Inputs'!$C$8)^6 -> 7629394.5
B28: cumvol_t | C28: =2000000*((1+'A2 Inputs'!$C$8)^1-1)/'A2 Inputs'!$C$8 -> 2000000 | D28: =2000000*((1+'A2 Inputs'!$C$8)^2-1)/'A2 Inputs'!$C$8 -> 4500000 | E28: =2000000*((1+'A2 Inputs'!$C$8)^3-1)/'A2 Inputs'!$C$8 -> 7625000 | F28: =2000000*((1+'A2 Inputs'!$C$8)^4-1)/'A2 Inputs'!$C$8 -> 11531250 | G28: =2000000*((1+'A2 Inputs'!$C$8)^5-1)/'A2 Inputs'!$C$8 -> 16414062 | H28: =2000000*((1+'A2 Inputs'!$C$8)^6-1)/'A2 Inputs'!$C$8 -> 22517578 | I28: =2000000*((1+'A2 Inputs'!$C$8)^7-1)/'A2 Inputs'!$C$8 -> 30146973
B29: yield_t | C29: ='A2 Inputs'!$C$21+('A2 Inputs'!$C$22-'A2 Inputs'!$C$21)*MIN(1,(0)/3) -> 0.8 | D29: ='A2 Inputs'!$C$21+('A2 Inputs'!$C$22-'A2 Inputs'!$C$21)*MIN(1,(1)/3) -> 0.85666667 | E29: ='A2 Inputs'!$C$21+('A2 Inputs'!$C$22-'A2 Inputs'!$C$21)*MIN(1,(2)/3) -> 0.91333333 | F29: ='A2 Inputs'!$C$21+('A2 Inputs'!$C$22-'A2 Inputs'!$C$21)*MIN(1,(3)/3) -> 0.97 | G29: ='A2 Inputs'!$C$21+('A2 Inputs'!$C$22-'A2 Inputs'!$C$21)*MIN(1,(4)/3) -> 0.97 | H29: ='A2 Inputs'!$C$21+('A2 Inputs'!$C$22-'A2 Inputs'!$C$21)*MIN(1,(5)/3) -> 0.97 | I29: ='A2 Inputs'!$C$21+('A2 Inputs'!$C$22-'A2 Inputs'!$C$21)*MIN(1,(6)/3) -> 0.97
B30: inhouse_t | C30: ='A2 Inputs'!$C$19*((C28/2000000)^(LOG(0.9,2)))/C29 -> 4.5 | D30: ='A2 Inputs'!$C$19*((D28/2000000)^(LOG(0.9,2)))/D29 -> 3.7149913 | E30: ='A2 Inputs'!$C$19*((E28/2000000)^(LOG(0.9,2)))/E29 -> 3.2160848 | F30: ='A2 Inputs'!$C$19*((F28/2000000)^(LOG(0.9,2)))/F29 -> 2.8436737 | G30: ='A2 Inputs'!$C$19*((G28/2000000)^(LOG(0.9,2)))/G29 -> 2.69508 | H30: ='A2 Inputs'!$C$19*((H28/2000000)^(LOG(0.9,2)))/H29 -> 2.5686254 | I30: ='A2 Inputs'!$C$19*((I28/2000000)^(LOG(0.9,2)))/I29 -> 2.4571894
B31: buy_t | C31: =C27*'A2 Inputs'!$C$13*(1+'A2 Inputs'!$C$14)^0 -> 9000000 | D31: =D27*'A2 Inputs'!$C$13*(1+'A2 Inputs'!$C$14)^1 -> 11587500 | E31: =E27*'A2 Inputs'!$C$13*(1+'A2 Inputs'!$C$14)^2 -> 14918906 | F31: =F27*'A2 Inputs'!$C$13*(1+'A2 Inputs'!$C$14)^3 -> 19208092 | G31: =G27*'A2 Inputs'!$C$13*(1+'A2 Inputs'!$C$14)^4 -> 24730418 | H31: =H27*'A2 Inputs'!$C$13*(1+'A2 Inputs'!$C$14)^5 -> 31840413 | I31: =I27*'A2 Inputs'!$C$13*(1+'A2 Inputs'!$C$14)^6 -> 40994532
B32: build_t | C32: =C27*C30+'A2 Inputs'!$C$17*'A2 Inputs'!$C$23+'A2 Inputs'!$C$17 -> 46100000 | D32: =D27*D30+'A2 Inputs'!$C$17*'A2 Inputs'!$C$23 -> 11387478 | E32: =E27*E30+'A2 Inputs'!$C$17*'A2 Inputs'!$C$23 -> 12150265 | F32: =F27*F30+'A2 Inputs'!$C$17*'A2 Inputs'!$C$23 -> 13208100 | G32: =G27*G30+'A2 Inputs'!$C$17*'A2 Inputs'!$C$23 -> 15259570 | H32: =H27*H30+'A2 Inputs'!$C$17*'A2 Inputs'!$C$23 -> 17777645 | I32: =I27*I30+'A2 Inputs'!$C$17*'A2 Inputs'!$C$23 -> 20846868
B33: disc_t | C33: =(C31-C32)/(1+'A2 Inputs'!$C$10)^1 -> -33125000 | D33: =(D31-D32)/(1+'A2 Inputs'!$C$10)^2 -> 159456.13 | E33: =(E31-E32)/(1+'A2 Inputs'!$C$10)^3 -> 1970664.1 | F33: =(F31-F32)/(1+'A2 Inputs'!$C$10)^4 -> 3813103 | G33: =(G31-G32)/(1+'A2 Inputs'!$C$10)^5 -> 5374013.6 | H33: =(H31-H32)/(1+'A2 Inputs'!$C$10)^6 -> 7124635.9 | I33: =(I31-I32)/(1+'A2 Inputs'!$C$10)^7 -> 9113780.3
B35: LR 0.9 / V1 3,500,000 | C35: Y1 | D35: Y2 | E35: Y3 | F35: Y4 | G35: Y5 | H35: Y6 | I35: Y7
B36: vol_t | C36: =3500000*(1+'A2 Inputs'!$C$8)^0 -> 3500000 | D36: =3500000*(1+'A2 Inputs'!$C$8)^1 -> 4375000 | E36: =3500000*(1+'A2 Inputs'!$C$8)^2 -> 5468750 | F36: =3500000*(1+'A2 Inputs'!$C$8)^3 -> 6835937.5 | G36: =3500000*(1+'A2 Inputs'!$C$8)^4 -> 8544921.9 | H36: =3500000*(1+'A2 Inputs'!$C$8)^5 -> 10681152 | I36: =3500000*(1+'A2 Inputs'!$C$8)^6 -> 13351440
B37: cumvol_t | C37: =3500000*((1+'A2 Inputs'!$C$8)^1-1)/'A2 Inputs'!$C$8 -> 3500000 | D37: =3500000*((1+'A2 Inputs'!$C$8)^2-1)/'A2 Inputs'!$C$8 -> 7875000 | E37: =3500000*((1+'A2 Inputs'!$C$8)^3-1)/'A2 Inputs'!$C$8 -> 13343750 | F37: =3500000*((1+'A2 Inputs'!$C$8)^4-1)/'A2 Inputs'!$C$8 -> 20179688 | G37: =3500000*((1+'A2 Inputs'!$C$8)^5-1)/'A2 Inputs'!$C$8 -> 28724609 | H37: =3500000*((1+'A2 Inputs'!$C$8)^6-1)/'A2 Inputs'!$C$8 -> 39405762 | I37: =3500000*((1+'A2 Inputs'!$C$8)^7-1)/'A2 Inputs'!$C$8 -> 52757202
B38: yield_t | C38: ='A2 Inputs'!$C$21+('A2 Inputs'!$C$22-'A2 Inputs'!$C$21)*MIN(1,(0)/3) -> 0.8 | D38: ='A2 Inputs'!$C$21+('A2 Inputs'!$C$22-'A2 Inputs'!$C$21)*MIN(1,(1)/3) -> 0.85666667 | E38: ='A2 Inputs'!$C$21+('A2 Inputs'!$C$22-'A2 Inputs'!$C$21)*MIN(1,(2)/3) -> 0.91333333 | F38: ='A2 Inputs'!$C$21+('A2 Inputs'!$C$22-'A2 Inputs'!$C$21)*MIN(1,(3)/3) -> 0.97 | G38: ='A2 Inputs'!$C$21+('A2 Inputs'!$C$22-'A2 Inputs'!$C$21)*MIN(1,(4)/3) -> 0.97 | H38: ='A2 Inputs'!$C$21+('A2 Inputs'!$C$22-'A2 Inputs'!$C$21)*MIN(1,(5)/3) -> 0.97 | I38: ='A2 Inputs'!$C$21+('A2 Inputs'!$C$22-'A2 Inputs'!$C$21)*MIN(1,(6)/3) -> 0.97
B39: inhouse_t | C39: ='A2 Inputs'!$C$19*((C37/3500000)^(LOG(0.9,2)))/C38 -> 4.5 | D39: ='A2 Inputs'!$C$19*((D37/3500000)^(LOG(0.9,2)))/D38 -> 3.7149913 | E39: ='A2 Inputs'!$C$19*((E37/3500000)^(LOG(0.9,2)))/E38 -> 3.2160848 | F39: ='A2 Inputs'!$C$19*((F37/3500000)^(LOG(0.9,2)))/F38 -> 2.8436737 | G39: ='A2 Inputs'!$C$19*((G37/3500000)^(LOG(0.9,2)))/G38 -> 2.69508 | H39: ='A2 Inputs'!$C$19*((H37/3500000)^(LOG(0.9,2)))/H38 -> 2.5686254 | I39: ='A2 Inputs'!$C$19*((I37/3500000)^(LOG(0.9,2)))/I38 -> 2.4571894
B40: buy_t | C40: =C36*'A2 Inputs'!$C$13*(1+'A2 Inputs'!$C$14)^0 -> 15750000 | D40: =D36*'A2 Inputs'!$C$13*(1+'A2 Inputs'!$C$14)^1 -> 20278125 | E40: =E36*'A2 Inputs'!$C$13*(1+'A2 Inputs'!$C$14)^2 -> 26108086 | F40: =F36*'A2 Inputs'!$C$13*(1+'A2 Inputs'!$C$14)^3 -> 33614161 | G40: =G36*'A2 Inputs'!$C$13*(1+'A2 Inputs'!$C$14)^4 -> 43278232 | H40: =H36*'A2 Inputs'!$C$13*(1+'A2 Inputs'!$C$14)^5 -> 55720723 | I40: =I36*'A2 Inputs'!$C$13*(1+'A2 Inputs'!$C$14)^6 -> 71740431
B41: build_t | C41: =C36*C39+'A2 Inputs'!$C$17*'A2 Inputs'!$C$23+'A2 Inputs'!$C$17 -> 52850000 | D41: =D36*D39+'A2 Inputs'!$C$17*'A2 Inputs'!$C$23 -> 18353087 | E41: =E36*E39+'A2 Inputs'!$C$17*'A2 Inputs'!$C$23 -> 19687964 | F41: =F36*F39+'A2 Inputs'!$C$17*'A2 Inputs'!$C$23 -> 21539176 | G41: =G36*G39+'A2 Inputs'!$C$17*'A2 Inputs'!$C$23 -> 25129248 | H41: =H36*H39+'A2 Inputs'!$C$17*'A2 Inputs'!$C$23 -> 29535880 | I41: =I36*I39+'A2 Inputs'!$C$17*'A2 Inputs'!$C$23 -> 34907018
B42: disc_t | C42: =(C40-C41)/(1+'A2 Inputs'!$C$10)^1 -> -33125000 | D42: =(D40-D41)/(1+'A2 Inputs'!$C$10)^2 -> 1534628.6 | E42: =(E40-E41)/(1+'A2 Inputs'!$C$10)^3 -> 4569716 | F42: =(F40-F41)/(1+'A2 Inputs'!$C$10)^4 -> 7673871.2 | G42: =(G40-G41)/(1+'A2 Inputs'!$C$10)^5 -> 10298221 | H42: =(H40-H41)/(1+'A2 Inputs'!$C$10)^6 -> 13266057 | I42: =(I40-I41)/(1+'A2 Inputs'!$C$10)^7 -> 16661566
B44: LR 0.9 / V1 5,500,000 | C44: Y1 | D44: Y2 | E44: Y3 | F44: Y4 | G44: Y5 | H44: Y6 | I44: Y7
B45: vol_t | C45: =5500000*(1+'A2 Inputs'!$C$8)^0 -> 5500000 | D45: =5500000*(1+'A2 Inputs'!$C$8)^1 -> 6875000 | E45: =5500000*(1+'A2 Inputs'!$C$8)^2 -> 8593750 | F45: =5500000*(1+'A2 Inputs'!$C$8)^3 -> 10742188 | G45: =5500000*(1+'A2 Inputs'!$C$8)^4 -> 13427734 | H45: =5500000*(1+'A2 Inputs'!$C$8)^5 -> 16784668 | I45: =5500000*(1+'A2 Inputs'!$C$8)^6 -> 20980835
B46: cumvol_t | C46: =5500000*((1+'A2 Inputs'!$C$8)^1-1)/'A2 Inputs'!$C$8 -> 5500000 | D46: =5500000*((1+'A2 Inputs'!$C$8)^2-1)/'A2 Inputs'!$C$8 -> 12375000 | E46: =5500000*((1+'A2 Inputs'!$C$8)^3-1)/'A2 Inputs'!$C$8 -> 20968750 | F46: =5500000*((1+'A2 Inputs'!$C$8)^4-1)/'A2 Inputs'!$C$8 -> 31710938 | G46: =5500000*((1+'A2 Inputs'!$C$8)^5-1)/'A2 Inputs'!$C$8 -> 45138672 | H46: =5500000*((1+'A2 Inputs'!$C$8)^6-1)/'A2 Inputs'!$C$8 -> 61923340 | I46: =5500000*((1+'A2 Inputs'!$C$8)^7-1)/'A2 Inputs'!$C$8 -> 82904175
B47: yield_t | C47: ='A2 Inputs'!$C$21+('A2 Inputs'!$C$22-'A2 Inputs'!$C$21)*MIN(1,(0)/3) -> 0.8 | D47: ='A2 Inputs'!$C$21+('A2 Inputs'!$C$22-'A2 Inputs'!$C$21)*MIN(1,(1)/3) -> 0.85666667 | E47: ='A2 Inputs'!$C$21+('A2 Inputs'!$C$22-'A2 Inputs'!$C$21)*MIN(1,(2)/3) -> 0.91333333 | F47: ='A2 Inputs'!$C$21+('A2 Inputs'!$C$22-'A2 Inputs'!$C$21)*MIN(1,(3)/3) -> 0.97 | G47: ='A2 Inputs'!$C$21+('A2 Inputs'!$C$22-'A2 Inputs'!$C$21)*MIN(1,(4)/3) -> 0.97 | H47: ='A2 Inputs'!$C$21+('A2 Inputs'!$C$22-'A2 Inputs'!$C$21)*MIN(1,(5)/3) -> 0.97 | I47: ='A2 Inputs'!$C$21+('A2 Inputs'!$C$22-'A2 Inputs'!$C$21)*MIN(1,(6)/3) -> 0.97
B48: inhouse_t | C48: ='A2 Inputs'!$C$19*((C46/5500000)^(LOG(0.9,2)))/C47 -> 4.5 | D48: ='A2 Inputs'!$C$19*((D46/5500000)^(LOG(0.9,2)))/D47 -> 3.7149913 | E48: ='A2 Inputs'!$C$19*((E46/5500000)^(LOG(0.9,2)))/E47 -> 3.2160848 | F48: ='A2 Inputs'!$C$19*((F46/5500000)^(LOG(0.9,2)))/F47 -> 2.8436737 | G48: ='A2 Inputs'!$C$19*((G46/5500000)^(LOG(0.9,2)))/G47 -> 2.69508 | H48: ='A2 Inputs'!$C$19*((H46/5500000)^(LOG(0.9,2)))/H47 -> 2.5686254 | I48: ='A2 Inputs'!$C$19*((I46/5500000)^(LOG(0.9,2)))/I47 -> 2.4571894
B49: buy_t | C49: =C45*'A2 Inputs'!$C$13*(1+'A2 Inputs'!$C$14)^0 -> 24750000 | D49: =D45*'A2 Inputs'!$C$13*(1+'A2 Inputs'!$C$14)^1 -> 31865625 | E49: =E45*'A2 Inputs'!$C$13*(1+'A2 Inputs'!$C$14)^2 -> 41026992 | F49: =F45*'A2 Inputs'!$C$13*(1+'A2 Inputs'!$C$14)^3 -> 52822252 | G49: =G45*'A2 Inputs'!$C$13*(1+'A2 Inputs'!$C$14)^4 -> 68008650 | H49: =H45*'A2 Inputs'!$C$13*(1+'A2 Inputs'!$C$14)^5 -> 87561137 | I49: =I45*'A2 Inputs'!$C$13*(1+'A2 Inputs'!$C$14)^6 -> 1.1273496e+08
B50: build_t | C50: =C45*C48+'A2 Inputs'!$C$17*'A2 Inputs'!$C$23+'A2 Inputs'!$C$17 -> 61850000 | D50: =D45*D48+'A2 Inputs'!$C$17*'A2 Inputs'!$C$23 -> 27640565 | E50: =E45*E48+'A2 Inputs'!$C$17*'A2 Inputs'!$C$23 -> 29738229 | F50: =F45*F48+'A2 Inputs'!$C$17*'A2 Inputs'!$C$23 -> 32647276 | G50: =G45*G48+'A2 Inputs'!$C$17*'A2 Inputs'!$C$23 -> 38288818 | H50: =H45*H48+'A2 Inputs'!$C$17*'A2 Inputs'!$C$23 -> 45213525 | I50: =I45*I48+'A2 Inputs'!$C$17*'A2 Inputs'!$C$23 -> 53653886
B51: disc_t | C51: =(C49-C50)/(1+'A2 Inputs'!$C$10)^1 -> -33125000 | D51: =(D49-D50)/(1+'A2 Inputs'!$C$10)^2 -> 3368191.9 | E51: =(E49-E50)/(1+'A2 Inputs'!$C$10)^3 -> 8035118.6 | F51: =(F49-F50)/(1+'A2 Inputs'!$C$10)^4 -> 12821562 | G51: =(G49-G50)/(1+'A2 Inputs'!$C$10)^5 -> 16863831 | H51: =(H49-H50)/(1+'A2 Inputs'!$C$10)^6 -> 21454618 | I51: =(I49-I50)/(1+'A2 Inputs'!$C$10)^7 -> 26725279
B53: LR 0.9 / V1 8,000,000 | C53: Y1 | D53: Y2 | E53: Y3 | F53: Y4 | G53: Y5 | H53: Y6 | I53: Y7
B54: vol_t | C54: =8000000*(1+'A2 Inputs'!$C$8)^0 -> 8000000 | D54: =8000000*(1+'A2 Inputs'!$C$8)^1 -> 10000000 | E54: =8000000*(1+'A2 Inputs'!$C$8)^2 -> 12500000 | F54: =8000000*(1+'A2 Inputs'!$C$8)^3 -> 15625000 | G54: =8000000*(1+'A2 Inputs'!$C$8)^4 -> 19531250 | H54: =8000000*(1+'A2 Inputs'!$C$8)^5 -> 24414062 | I54: =8000000*(1+'A2 Inputs'!$C$8)^6 -> 30517578
B55: cumvol_t | C55: =8000000*((1+'A2 Inputs'!$C$8)^1-1)/'A2 Inputs'!$C$8 -> 8000000 | D55: =8000000*((1+'A2 Inputs'!$C$8)^2-1)/'A2 Inputs'!$C$8 -> 18000000 | E55: =8000000*((1+'A2 Inputs'!$C$8)^3-1)/'A2 Inputs'!$C$8 -> 30500000 | F55: =8000000*((1+'A2 Inputs'!$C$8)^4-1)/'A2 Inputs'!$C$8 -> 46125000 | G55: =8000000*((1+'A2 Inputs'!$C$8)^5-1)/'A2 Inputs'!$C$8 -> 65656250 | H55: =8000000*((1+'A2 Inputs'!$C$8)^6-1)/'A2 Inputs'!$C$8 -> 90070312 | I55: =8000000*((1+'A2 Inputs'!$C$8)^7-1)/'A2 Inputs'!$C$8 -> 1.2058789e+08
B56: yield_t | C56: ='A2 Inputs'!$C$21+('A2 Inputs'!$C$22-'A2 Inputs'!$C$21)*MIN(1,(0)/3) -> 0.8 | D56: ='A2 Inputs'!$C$21+('A2 Inputs'!$C$22-'A2 Inputs'!$C$21)*MIN(1,(1)/3) -> 0.85666667 | E56: ='A2 Inputs'!$C$21+('A2 Inputs'!$C$22-'A2 Inputs'!$C$21)*MIN(1,(2)/3) -> 0.91333333 | F56: ='A2 Inputs'!$C$21+('A2 Inputs'!$C$22-'A2 Inputs'!$C$21)*MIN(1,(3)/3) -> 0.97 | G56: ='A2 Inputs'!$C$21+('A2 Inputs'!$C$22-'A2 Inputs'!$C$21)*MIN(1,(4)/3) -> 0.97 | H56: ='A2 Inputs'!$C$21+('A2 Inputs'!$C$22-'A2 Inputs'!$C$21)*MIN(1,(5)/3) -> 0.97 | I56: ='A2 Inputs'!$C$21+('A2 Inputs'!$C$22-'A2 Inputs'!$C$21)*MIN(1,(6)/3) -> 0.97
B57: inhouse_t | C57: ='A2 Inputs'!$C$19*((C55/8000000)^(LOG(0.9,2)))/C56 -> 4.5 | D57: ='A2 Inputs'!$C$19*((D55/8000000)^(LOG(0.9,2)))/D56 -> 3.7149913 | E57: ='A2 Inputs'!$C$19*((E55/8000000)^(LOG(0.9,2)))/E56 -> 3.2160848 | F57: ='A2 Inputs'!$C$19*((F55/8000000)^(LOG(0.9,2)))/F56 -> 2.8436737 | G57: ='A2 Inputs'!$C$19*((G55/8000000)^(LOG(0.9,2)))/G56 -> 2.69508 | H57: ='A2 Inputs'!$C$19*((H55/8000000)^(LOG(0.9,2)))/H56 -> 2.5686254 | I57: ='A2 Inputs'!$C$19*((I55/8000000)^(LOG(0.9,2)))/I56 -> 2.4571894
B58: buy_t | C58: =C54*'A2 Inputs'!$C$13*(1+'A2 Inputs'!$C$14)^0 -> 36000000 | D58: =D54*'A2 Inputs'!$C$13*(1+'A2 Inputs'!$C$14)^1 -> 46350000 | E58: =E54*'A2 Inputs'!$C$13*(1+'A2 Inputs'!$C$14)^2 -> 59675625 | F58: =F54*'A2 Inputs'!$C$13*(1+'A2 Inputs'!$C$14)^3 -> 76832367 | G58: =G54*'A2 Inputs'!$C$13*(1+'A2 Inputs'!$C$14)^4 -> 98921673 | H58: =H54*'A2 Inputs'!$C$13*(1+'A2 Inputs'!$C$14)^5 -> 1.2736165e+08 | I58: =I54*'A2 Inputs'!$C$13*(1+'A2 Inputs'!$C$14)^6 -> 1.6397813e+08
B59: build_t | C59: =C54*C57+'A2 Inputs'!$C$17*'A2 Inputs'!$C$23+'A2 Inputs'!$C$17 -> 73100000 | D59: =D54*D57+'A2 Inputs'!$C$17*'A2 Inputs'!$C$23 -> 39249913 | E59: =E54*E57+'A2 Inputs'!$C$17*'A2 Inputs'!$C$23 -> 42301061 | F59: =F54*F57+'A2 Inputs'!$C$17*'A2 Inputs'!$C$23 -> 46532402 | G59: =G54*G57+'A2 Inputs'!$C$17*'A2 Inputs'!$C$23 -> 54738280 | H59: =H54*H57+'A2 Inputs'!$C$17*'A2 Inputs'!$C$23 -> 64810582 | I59: =I54*I57+'A2 Inputs'!$C$17*'A2 Inputs'!$C$23 -> 77087470
B60: disc_t | C60: =(C58-C59)/(1+'A2 Inputs'!$C$10)^1 -> -33125000 | D60: =(D58-D59)/(1+'A2 Inputs'!$C$10)^2 -> 5660146 | E60: =(E58-E59)/(1+'A2 Inputs'!$C$10)^3 -> 12366872 | F60: =(F58-F59)/(1+'A2 Inputs'!$C$10)^4 -> 19256176 | G60: =(G58-G59)/(1+'A2 Inputs'!$C$10)^5 -> 25070843 | H60: =(H58-H59)/(1+'A2 Inputs'!$C$10)^6 -> 31690320 | I60: =(I58-I59)/(1+'A2 Inputs'!$C$10)^7 -> 39304921
B62: LR 0.88 / V1 1,000,000 | C62: Y1 | D62: Y2 | E62: Y3 | F62: Y4 | G62: Y5 | H62: Y6 | I62: Y7
B63: vol_t | C63: =1000000*(1+'A2 Inputs'!$C$8)^0 -> 1000000 | D63: =1000000*(1+'A2 Inputs'!$C$8)^1 -> 1250000 | E63: =1000000*(1+'A2 Inputs'!$C$8)^2 -> 1562500 | F63: =1000000*(1+'A2 Inputs'!$C$8)^3 -> 1953125 | G63: =1000000*(1+'A2 Inputs'!$C$8)^4 -> 2441406.2 | H63: =1000000*(1+'A2 Inputs'!$C$8)^5 -> 3051757.8 | I63: =1000000*(1+'A2 Inputs'!$C$8)^6 -> 3814697.3
B64: cumvol_t | C64: =1000000*((1+'A2 Inputs'!$C$8)^1-1)/'A2 Inputs'!$C$8 -> 1000000 | D64: =1000000*((1+'A2 Inputs'!$C$8)^2-1)/'A2 Inputs'!$C$8 -> 2250000 | E64: =1000000*((1+'A2 Inputs'!$C$8)^3-1)/'A2 Inputs'!$C$8 -> 3812500 | F64: =1000000*((1+'A2 Inputs'!$C$8)^4-1)/'A2 Inputs'!$C$8 -> 5765625 | G64: =1000000*((1+'A2 Inputs'!$C$8)^5-1)/'A2 Inputs'!$C$8 -> 8207031.2 | H64: =1000000*((1+'A2 Inputs'!$C$8)^6-1)/'A2 Inputs'!$C$8 -> 11258789 | I64: =1000000*((1+'A2 Inputs'!$C$8)^7-1)/'A2 Inputs'!$C$8 -> 15073486
B65: yield_t | C65: ='A2 Inputs'!$C$21+('A2 Inputs'!$C$22-'A2 Inputs'!$C$21)*MIN(1,(0)/3) -> 0.8 | D65: ='A2 Inputs'!$C$21+('A2 Inputs'!$C$22-'A2 Inputs'!$C$21)*MIN(1,(1)/3) -> 0.85666667 | E65: ='A2 Inputs'!$C$21+('A2 Inputs'!$C$22-'A2 Inputs'!$C$21)*MIN(1,(2)/3) -> 0.91333333 | F65: ='A2 Inputs'!$C$21+('A2 Inputs'!$C$22-'A2 Inputs'!$C$21)*MIN(1,(3)/3) -> 0.97 | G65: ='A2 Inputs'!$C$21+('A2 Inputs'!$C$22-'A2 Inputs'!$C$21)*MIN(1,(4)/3) -> 0.97 | H65: ='A2 Inputs'!$C$21+('A2 Inputs'!$C$22-'A2 Inputs'!$C$21)*MIN(1,(5)/3) -> 0.97 | I65: ='A2 Inputs'!$C$21+('A2 Inputs'!$C$22-'A2 Inputs'!$C$21)*MIN(1,(6)/3) -> 0.97
B66: inhouse_t | C66: ='A2 Inputs'!$C$19*((C64/1000000)^(LOG(0.88,2)))/C65 -> 4.5 | D66: ='A2 Inputs'!$C$19*((D64/1000000)^(LOG(0.88,2)))/D65 -> 3.6185912 | E66: ='A2 Inputs'!$C$19*((E64/1000000)^(LOG(0.88,2)))/E65 -> 3.0795256 | F66: ='A2 Inputs'!$C$19*((F64/1000000)^(LOG(0.88,2)))/F65 -> 2.6866556 | G66: ='A2 Inputs'!$C$19*((G64/1000000)^(LOG(0.88,2)))/G65 -> 2.517285 | H66: ='A2 Inputs'!$C$19*((H64/1000000)^(LOG(0.88,2)))/H65 -> 2.3747061 | I66: ='A2 Inputs'!$C$19*((I64/1000000)^(LOG(0.88,2)))/I65 -> 2.2502937
B67: buy_t | C67: =C63*'A2 Inputs'!$C$13*(1+'A2 Inputs'!$C$14)^0 -> 4500000 | D67: =D63*'A2 Inputs'!$C$13*(1+'A2 Inputs'!$C$14)^1 -> 5793750 | E67: =E63*'A2 Inputs'!$C$13*(1+'A2 Inputs'!$C$14)^2 -> 7459453.1 | F67: =F63*'A2 Inputs'!$C$13*(1+'A2 Inputs'!$C$14)^3 -> 9604045.9 | G67: =G63*'A2 Inputs'!$C$13*(1+'A2 Inputs'!$C$14)^4 -> 12365209 | H67: =H63*'A2 Inputs'!$C$13*(1+'A2 Inputs'!$C$14)^5 -> 15920207 | I67: =I63*'A2 Inputs'!$C$13*(1+'A2 Inputs'!$C$14)^6 -> 20497266
B68: build_t | C68: =C63*C66+'A2 Inputs'!$C$17*'A2 Inputs'!$C$23+'A2 Inputs'!$C$17 -> 41600000 | D68: =D63*D66+'A2 Inputs'!$C$17*'A2 Inputs'!$C$23 -> 6623239 | E68: =E63*E66+'A2 Inputs'!$C$17*'A2 Inputs'!$C$23 -> 6911758.7 | F68: =F63*F66+'A2 Inputs'!$C$17*'A2 Inputs'!$C$23 -> 7347374.2 | G68: =G63*G66+'A2 Inputs'!$C$17*'A2 Inputs'!$C$23 -> 8245715.4 | H68: =H63*H66+'A2 Inputs'!$C$17*'A2 Inputs'!$C$23 -> 9347027.8 | I68: =I63*I66+'A2 Inputs'!$C$17*'A2 Inputs'!$C$23 -> 10684189
B69: disc_t | C69: =(C67-C68)/(1+'A2 Inputs'!$C$10)^1 -> -33125000 | D69: =(D67-D68)/(1+'A2 Inputs'!$C$10)^2 -> -661263.55 | E69: =(E67-E68)/(1+'A2 Inputs'!$C$10)^3 -> 389838.07 | F69: =(F67-F68)/(1+'A2 Inputs'!$C$10)^4 -> 1434155.7 | G69: =(G67-G68)/(1+'A2 Inputs'!$C$10)^5 -> 2337511.4 | H69: =(H67-H68)/(1+'A2 Inputs'!$C$10)^6 -> 3330177 | I69: =(I67-I68)/(1+'A2 Inputs'!$C$10)^7 -> 4438937.6
B71: LR 0.88 / V1 2,000,000 | C71: Y1 | D71: Y2 | E71: Y3 | F71: Y4 | G71: Y5 | H71: Y6 | I71: Y7
B72: vol_t | C72: =2000000*(1+'A2 Inputs'!$C$8)^0 -> 2000000 | D72: =2000000*(1+'A2 Inputs'!$C$8)^1 -> 2500000 | E72: =2000000*(1+'A2 Inputs'!$C$8)^2 -> 3125000 | F72: =2000000*(1+'A2 Inputs'!$C$8)^3 -> 3906250 | G72: =2000000*(1+'A2 Inputs'!$C$8)^4 -> 4882812.5 | H72: =2000000*(1+'A2 Inputs'!$C$8)^5 -> 6103515.6 | I72: =2000000*(1+'A2 Inputs'!$C$8)^6 -> 7629394.5
B73: cumvol_t | C73: =2000000*((1+'A2 Inputs'!$C$8)^1-1)/'A2 Inputs'!$C$8 -> 2000000 | D73: =2000000*((1+'A2 Inputs'!$C$8)^2-1)/'A2 Inputs'!$C$8 -> 4500000 | E73: =2000000*((1+'A2 Inputs'!$C$8)^3-1)/'A2 Inputs'!$C$8 -> 7625000 | F73: =2000000*((1+'A2 Inputs'!$C$8)^4-1)/'A2 Inputs'!$C$8 -> 11531250 | G73: =2000000*((1+'A2 Inputs'!$C$8)^5-1)/'A2 Inputs'!$C$8 -> 16414062 | H73: =2000000*((1+'A2 Inputs'!$C$8)^6-1)/'A2 Inputs'!$C$8 -> 22517578 | I73: =2000000*((1+'A2 Inputs'!$C$8)^7-1)/'A2 Inputs'!$C$8 -> 30146973
B74: yield_t | C74: ='A2 Inputs'!$C$21+('A2 Inputs'!$C$22-'A2 Inputs'!$C$21)*MIN(1,(0)/3) -> 0.8 | D74: ='A2 Inputs'!$C$21+('A2 Inputs'!$C$22-'A2 Inputs'!$C$21)*MIN(1,(1)/3) -> 0.85666667 | E74: ='A2 Inputs'!$C$21+('A2 Inputs'!$C$22-'A2 Inputs'!$C$21)*MIN(1,(2)/3) -> 0.91333333 | F74: ='A2 Inputs'!$C$21+('A2 Inputs'!$C$22-'A2 Inputs'!$C$21)*MIN(1,(3)/3) -> 0.97 | G74: ='A2 Inputs'!$C$21+('A2 Inputs'!$C$22-'A2 Inputs'!$C$21)*MIN(1,(4)/3) -> 0.97 | H74: ='A2 Inputs'!$C$21+('A2 Inputs'!$C$22-'A2 Inputs'!$C$21)*MIN(1,(5)/3) -> 0.97 | I74: ='A2 Inputs'!$C$21+('A2 Inputs'!$C$22-'A2 Inputs'!$C$21)*MIN(1,(6)/3) -> 0.97
B75: inhouse_t | C75: ='A2 Inputs'!$C$19*((C73/2000000)^(LOG(0.88,2)))/C74 -> 4.5 | D75: ='A2 Inputs'!$C$19*((D73/2000000)^(LOG(0.88,2)))/D74 -> 3.6185912 | E75: ='A2 Inputs'!$C$19*((E73/2000000)^(LOG(0.88,2)))/E74 -> 3.0795256 | F75: ='A2 Inputs'!$C$19*((F73/2000000)^(LOG(0.88,2)))/F74 -> 2.6866556 | G75: ='A2 Inputs'!$C$19*((G73/2000000)^(LOG(0.88,2)))/G74 -> 2.517285 | H75: ='A2 Inputs'!$C$19*((H73/2000000)^(LOG(0.88,2)))/H74 -> 2.3747061 | I75: ='A2 Inputs'!$C$19*((I73/2000000)^(LOG(0.88,2)))/I74 -> 2.2502937
B76: buy_t | C76: =C72*'A2 Inputs'!$C$13*(1+'A2 Inputs'!$C$14)^0 -> 9000000 | D76: =D72*'A2 Inputs'!$C$13*(1+'A2 Inputs'!$C$14)^1 -> 11587500 | E76: =E72*'A2 Inputs'!$C$13*(1+'A2 Inputs'!$C$14)^2 -> 14918906 | F76: =F72*'A2 Inputs'!$C$13*(1+'A2 Inputs'!$C$14)^3 -> 19208092 | G76: =G72*'A2 Inputs'!$C$13*(1+'A2 Inputs'!$C$14)^4 -> 24730418 | H76: =H72*'A2 Inputs'!$C$13*(1+'A2 Inputs'!$C$14)^5 -> 31840413 | I76: =I72*'A2 Inputs'!$C$13*(1+'A2 Inputs'!$C$14)^6 -> 40994532
B77: build_t | C77: =C72*C75+'A2 Inputs'!$C$17*'A2 Inputs'!$C$23+'A2 Inputs'!$C$17 -> 46100000 | D77: =D72*D75+'A2 Inputs'!$C$17*'A2 Inputs'!$C$23 -> 11146478 | E77: =E72*E75+'A2 Inputs'!$C$17*'A2 Inputs'!$C$23 -> 11723517 | F77: =F72*F75+'A2 Inputs'!$C$17*'A2 Inputs'!$C$23 -> 12594748 | G77: =G72*G75+'A2 Inputs'!$C$17*'A2 Inputs'!$C$23 -> 14391431 | H77: =H72*H75+'A2 Inputs'!$C$17*'A2 Inputs'!$C$23 -> 16594056 | I77: =I72*I75+'A2 Inputs'!$C$17*'A2 Inputs'!$C$23 -> 19268379
B78: disc_t | C78: =(C76-C77)/(1+'A2 Inputs'!$C$10)^1 -> -33125000 | D78: =(D76-D77)/(1+'A2 Inputs'!$C$10)^2 -> 351580.05 | E78: =(E76-E77)/(1+'A2 Inputs'!$C$10)^3 -> 2274414.7 | F78: =(F76-F77)/(1+'A2 Inputs'!$C$10)^4 -> 4202899.3 | G78: =(G76-G77)/(1+'A2 Inputs'!$C$10)^5 -> 5866619.2 | H78: =(H76-H77)/(1+'A2 Inputs'!$C$10)^6 -> 7724279.3 | I78: =(I76-I77)/(1+'A2 Inputs'!$C$10)^7 -> 9827808.6
B80: LR 0.88 / V1 3,500,000 | C80: Y1 | D80: Y2 | E80: Y3 | F80: Y4 | G80: Y5 | H80: Y6 | I80: Y7
B81: vol_t | C81: =3500000*(1+'A2 Inputs'!$C$8)^0 -> 3500000 | D81: =3500000*(1+'A2 Inputs'!$C$8)^1 -> 4375000 | E81: =3500000*(1+'A2 Inputs'!$C$8)^2 -> 5468750 | F81: =3500000*(1+'A2 Inputs'!$C$8)^3 -> 6835937.5 | G81: =3500000*(1+'A2 Inputs'!$C$8)^4 -> 8544921.9 | H81: =3500000*(1+'A2 Inputs'!$C$8)^5 -> 10681152 | I81: =3500000*(1+'A2 Inputs'!$C$8)^6 -> 13351440
B82: cumvol_t | C82: =3500000*((1+'A2 Inputs'!$C$8)^1-1)/'A2 Inputs'!$C$8 -> 3500000 | D82: =3500000*((1+'A2 Inputs'!$C$8)^2-1)/'A2 Inputs'!$C$8 -> 7875000 | E82: =3500000*((1+'A2 Inputs'!$C$8)^3-1)/'A2 Inputs'!$C$8 -> 13343750 | F82: =3500000*((1+'A2 Inputs'!$C$8)^4-1)/'A2 Inputs'!$C$8 -> 20179688 | G82: =3500000*((1+'A2 Inputs'!$C$8)^5-1)/'A2 Inputs'!$C$8 -> 28724609 | H82: =3500000*((1+'A2 Inputs'!$C$8)^6-1)/'A2 Inputs'!$C$8 -> 39405762 | I82: =3500000*((1+'A2 Inputs'!$C$8)^7-1)/'A2 Inputs'!$C$8 -> 52757202
B83: yield_t | C83: ='A2 Inputs'!$C$21+('A2 Inputs'!$C$22-'A2 Inputs'!$C$21)*MIN(1,(0)/3) -> 0.8 | D83: ='A2 Inputs'!$C$21+('A2 Inputs'!$C$22-'A2 Inputs'!$C$21)*MIN(1,(1)/3) -> 0.85666667 | E83: ='A2 Inputs'!$C$21+('A2 Inputs'!$C$22-'A2 Inputs'!$C$21)*MIN(1,(2)/3) -> 0.91333333 | F83: ='A2 Inputs'!$C$21+('A2 Inputs'!$C$22-'A2 Inputs'!$C$21)*MIN(1,(3)/3) -> 0.97 | G83: ='A2 Inputs'!$C$21+('A2 Inputs'!$C$22-'A2 Inputs'!$C$21)*MIN(1,(4)/3) -> 0.97 | H83: ='A2 Inputs'!$C$21+('A2 Inputs'!$C$22-'A2 Inputs'!$C$21)*MIN(1,(5)/3) -> 0.97 | I83: ='A2 Inputs'!$C$21+('A2 Inputs'!$C$22-'A2 Inputs'!$C$21)*MIN(1,(6)/3) -> 0.97
B84: inhouse_t | C84: ='A2 Inputs'!$C$19*((C82/3500000)^(LOG(0.88,2)))/C83 -> 4.5 | D84: ='A2 Inputs'!$C$19*((D82/3500000)^(LOG(0.88,2)))/D83 -> 3.6185912 | E84: ='A2 Inputs'!$C$19*((E82/3500000)^(LOG(0.88,2)))/E83 -> 3.0795256 | F84: ='A2 Inputs'!$C$19*((F82/3500000)^(LOG(0.88,2)))/F83 -> 2.6866556 | G84: ='A2 Inputs'!$C$19*((G82/3500000)^(LOG(0.88,2)))/G83 -> 2.517285 | H84: ='A2 Inputs'!$C$19*((H82/3500000)^(LOG(0.88,2)))/H83 -> 2.3747061 | I84: ='A2 Inputs'!$C$19*((I82/3500000)^(LOG(0.88,2)))/I83 -> 2.2502937
B85: buy_t | C85: =C81*'A2 Inputs'!$C$13*(1+'A2 Inputs'!$C$14)^0 -> 15750000 | D85: =D81*'A2 Inputs'!$C$13*(1+'A2 Inputs'!$C$14)^1 -> 20278125 | E85: =E81*'A2 Inputs'!$C$13*(1+'A2 Inputs'!$C$14)^2 -> 26108086 | F85: =F81*'A2 Inputs'!$C$13*(1+'A2 Inputs'!$C$14)^3 -> 33614161 | G85: =G81*'A2 Inputs'!$C$13*(1+'A2 Inputs'!$C$14)^4 -> 43278232 | H85: =H81*'A2 Inputs'!$C$13*(1+'A2 Inputs'!$C$14)^5 -> 55720723 | I85: =I81*'A2 Inputs'!$C$13*(1+'A2 Inputs'!$C$14)^6 -> 71740431
B86: build_t | C86: =C81*C84+'A2 Inputs'!$C$17*'A2 Inputs'!$C$23+'A2 Inputs'!$C$17 -> 52850000 | D86: =D81*D84+'A2 Inputs'!$C$17*'A2 Inputs'!$C$23 -> 17931336 | E86: =E81*E84+'A2 Inputs'!$C$17*'A2 Inputs'!$C$23 -> 18941155 | F86: =F81*F84+'A2 Inputs'!$C$17*'A2 Inputs'!$C$23 -> 20465810 | G86: =G81*G84+'A2 Inputs'!$C$17*'A2 Inputs'!$C$23 -> 23610004 | H86: =H81*H84+'A2 Inputs'!$C$17*'A2 Inputs'!$C$23 -> 27464597 | I86: =I81*I84+'A2 Inputs'!$C$17*'A2 Inputs'!$C$23 -> 32144663
B87: disc_t | C87: =(C85-C86)/(1+'A2 Inputs'!$C$10)^1 -> -33125000 | D87: =(D85-D86)/(1+'A2 Inputs'!$C$10)^2 -> 1870845.4 | E87: =(E85-E86)/(1+'A2 Inputs'!$C$10)^3 -> 5101279.5 | F87: =(F85-F86)/(1+'A2 Inputs'!$C$10)^4 -> 8356014.7 | G87: =(G85-G86)/(1+'A2 Inputs'!$C$10)^5 -> 11160281 | H87: =(H85-H86)/(1+'A2 Inputs'!$C$10)^6 -> 14315433 | I87: =(I85-I86)/(1+'A2 Inputs'!$C$10)^7 -> 17911115
B89: LR 0.88 / V1 5,500,000 | C89: Y1 | D89: Y2 | E89: Y3 | F89: Y4 | G89: Y5 | H89: Y6 | I89: Y7
B90: vol_t | C90: =5500000*(1+'A2 Inputs'!$C$8)^0 -> 5500000 | D90: =5500000*(1+'A2 Inputs'!$C$8)^1 -> 6875000 | E90: =5500000*(1+'A2 Inputs'!$C$8)^2 -> 8593750 | F90: =5500000*(1+'A2 Inputs'!$C$8)^3 -> 10742188 | G90: =5500000*(1+'A2 Inputs'!$C$8)^4 -> 13427734 | H90: =5500000*(1+'A2 Inputs'!$C$8)^5 -> 16784668 | I90: =5500000*(1+'A2 Inputs'!$C$8)^6 -> 20980835
B91: cumvol_t | C91: =5500000*((1+'A2 Inputs'!$C$8)^1-1)/'A2 Inputs'!$C$8 -> 5500000 | D91: =5500000*((1+'A2 Inputs'!$C$8)^2-1)/'A2 Inputs'!$C$8 -> 12375000 | E91: =5500000*((1+'A2 Inputs'!$C$8)^3-1)/'A2 Inputs'!$C$8 -> 20968750 | F91: =5500000*((1+'A2 Inputs'!$C$8)^4-1)/'A2 Inputs'!$C$8 -> 31710938 | G91: =5500000*((1+'A2 Inputs'!$C$8)^5-1)/'A2 Inputs'!$C$8 -> 45138672 | H91: =5500000*((1+'A2 Inputs'!$C$8)^6-1)/'A2 Inputs'!$C$8 -> 61923340 | I91: =5500000*((1+'A2 Inputs'!$C$8)^7-1)/'A2 Inputs'!$C$8 -> 82904175
B92: yield_t | C92: ='A2 Inputs'!$C$21+('A2 Inputs'!$C$22-'A2 Inputs'!$C$21)*MIN(1,(0)/3) -> 0.8 | D92: ='A2 Inputs'!$C$21+('A2 Inputs'!$C$22-'A2 Inputs'!$C$21)*MIN(1,(1)/3) -> 0.85666667 | E92: ='A2 Inputs'!$C$21+('A2 Inputs'!$C$22-'A2 Inputs'!$C$21)*MIN(1,(2)/3) -> 0.91333333 | F92: ='A2 Inputs'!$C$21+('A2 Inputs'!$C$22-'A2 Inputs'!$C$21)*MIN(1,(3)/3) -> 0.97 | G92: ='A2 Inputs'!$C$21+('A2 Inputs'!$C$22-'A2 Inputs'!$C$21)*MIN(1,(4)/3) -> 0.97 | H92: ='A2 Inputs'!$C$21+('A2 Inputs'!$C$22-'A2 Inputs'!$C$21)*MIN(1,(5)/3) -> 0.97 | I92: ='A2 Inputs'!$C$21+('A2 Inputs'!$C$22-'A2 Inputs'!$C$21)*MIN(1,(6)/3) -> 0.97
B93: inhouse_t | C93: ='A2 Inputs'!$C$19*((C91/5500000)^(LOG(0.88,2)))/C92 -> 4.5 | D93: ='A2 Inputs'!$C$19*((D91/5500000)^(LOG(0.88,2)))/D92 -> 3.6185912 | E93: ='A2 Inputs'!$C$19*((E91/5500000)^(LOG(0.88,2)))/E92 -> 3.0795256 | F93: ='A2 Inputs'!$C$19*((F91/5500000)^(LOG(0.88,2)))/F92 -> 2.6866556 | G93: ='A2 Inputs'!$C$19*((G91/5500000)^(LOG(0.88,2)))/G92 -> 2.517285 | H93: ='A2 Inputs'!$C$19*((H91/5500000)^(LOG(0.88,2)))/H92 -> 2.3747061 | I93: ='A2 Inputs'!$C$19*((I91/5500000)^(LOG(0.88,2)))/I92 -> 2.2502937
B94: buy_t | C94: =C90*'A2 Inputs'!$C$13*(1+'A2 Inputs'!$C$14)^0 -> 24750000 | D94: =D90*'A2 Inputs'!$C$13*(1+'A2 Inputs'!$C$14)^1 -> 31865625 | E94: =E90*'A2 Inputs'!$C$13*(1+'A2 Inputs'!$C$14)^2 -> 41026992 | F94: =F90*'A2 Inputs'!$C$13*(1+'A2 Inputs'!$C$14)^3 -> 52822252 | G94: =G90*'A2 Inputs'!$C$13*(1+'A2 Inputs'!$C$14)^4 -> 68008650 | H94: =H90*'A2 Inputs'!$C$13*(1+'A2 Inputs'!$C$14)^5 -> 87561137 | I94: =I90*'A2 Inputs'!$C$13*(1+'A2 Inputs'!$C$14)^6 -> 1.1273496e+08
B95: build_t | C95: =C90*C93+'A2 Inputs'!$C$17*'A2 Inputs'!$C$23+'A2 Inputs'!$C$17 -> 61850000 | D95: =D90*D93+'A2 Inputs'!$C$17*'A2 Inputs'!$C$23 -> 26977814 | E95: =E90*E93+'A2 Inputs'!$C$17*'A2 Inputs'!$C$23 -> 28564673 | F95: =F90*F93+'A2 Inputs'!$C$17*'A2 Inputs'!$C$23 -> 30960558 | G95: =G90*G93+'A2 Inputs'!$C$17*'A2 Inputs'!$C$23 -> 35901434 | H95: =H90*H93+'A2 Inputs'!$C$17*'A2 Inputs'!$C$23 -> 41958653 | I95: =I90*I93+'A2 Inputs'!$C$17*'A2 Inputs'!$C$23 -> 49313041
B96: disc_t | C96: =(C94-C95)/(1+'A2 Inputs'!$C$10)^1 -> -33125000 | D96: =(D94-D95)/(1+'A2 Inputs'!$C$10)^2 -> 3896532.6 | E96: =(E94-E95)/(1+'A2 Inputs'!$C$10)^3 -> 8870432.7 | F96: =(F94-F95)/(1+'A2 Inputs'!$C$10)^4 -> 13893502 | G96: =(G94-G95)/(1+'A2 Inputs'!$C$10)^5 -> 18218496 | H96: =(H94-H95)/(1+'A2 Inputs'!$C$10)^6 -> 23103638 | I96: =(I94-I95)/(1+'A2 Inputs'!$C$10)^7 -> 28688857
B98: LR 0.88 / V1 8,000,000 | C98: Y1 | D98: Y2 | E98: Y3 | F98: Y4 | G98: Y5 | H98: Y6 | I98: Y7
B99: vol_t | C99: =8000000*(1+'A2 Inputs'!$C$8)^0 -> 8000000 | D99: =8000000*(1+'A2 Inputs'!$C$8)^1 -> 10000000 | E99: =8000000*(1+'A2 Inputs'!$C$8)^2 -> 12500000 | F99: =8000000*(1+'A2 Inputs'!$C$8)^3 -> 15625000 | G99: =8000000*(1+'A2 Inputs'!$C$8)^4 -> 19531250 | H99: =8000000*(1+'A2 Inputs'!$C$8)^5 -> 24414062 | I99: =8000000*(1+'A2 Inputs'!$C$8)^6 -> 30517578
B100: cumvol_t | C100: =8000000*((1+'A2 Inputs'!$C$8)^1-1)/'A2 Inputs'!$C$8 -> 8000000 | D100: =8000000*((1+'A2 Inputs'!$C$8)^2-1)/'A2 Inputs'!$C$8 -> 18000000 | E100: =8000000*((1+'A2 Inputs'!$C$8)^3-1)/'A2 Inputs'!$C$8 -> 30500000 | F100: =8000000*((1+'A2 Inputs'!$C$8)^4-1)/'A2 Inputs'!$C$8 -> 46125000 | G100: =8000000*((1+'A2 Inputs'!$C$8)^5-1)/'A2 Inputs'!$C$8 -> 65656250 | H100: =8000000*((1+'A2 Inputs'!$C$8)^6-1)/'A2 Inputs'!$C$8 -> 90070312 | I100: =8000000*((1+'A2 Inputs'!$C$8)^7-1)/'A2 Inputs'!$C$8 -> 1.2058789e+08
B101: yield_t | C101: ='A2 Inputs'!$C$21+('A2 Inputs'!$C$22-'A2 Inputs'!$C$21)*MIN(1,(0)/3) -> 0.8 | D101: ='A2 Inputs'!$C$21+('A2 Inputs'!$C$22-'A2 Inputs'!$C$21)*MIN(1,(1)/3) -> 0.85666667 | E101: ='A2 Inputs'!$C$21+('A2 Inputs'!$C$22-'A2 Inputs'!$C$21)*MIN(1,(2)/3) -> 0.91333333 | F101: ='A2 Inputs'!$C$21+('A2 Inputs'!$C$22-'A2 Inputs'!$C$21)*MIN(1,(3)/3) -> 0.97 | G101: ='A2 Inputs'!$C$21+('A2 Inputs'!$C$22-'A2 Inputs'!$C$21)*MIN(1,(4)/3) -> 0.97 | H101: ='A2 Inputs'!$C$21+('A2 Inputs'!$C$22-'A2 Inputs'!$C$21)*MIN(1,(5)/3) -> 0.97 | I101: ='A2 Inputs'!$C$21+('A2 Inputs'!$C$22-'A2 Inputs'!$C$21)*MIN(1,(6)/3) -> 0.97
B102: inhouse_t | C102: ='A2 Inputs'!$C$19*((C100/8000000)^(LOG(0.88,2)))/C101 -> 4.5 | D102: ='A2 Inputs'!$C$19*((D100/8000000)^(LOG(0.88,2)))/D101 -> 3.6185912 | E102: ='A2 Inputs'!$C$19*((E100/8000000)^(LOG(0.88,2)))/E101 -> 3.0795256 | F102: ='A2 Inputs'!$C$19*((F100/8000000)^(LOG(0.88,2)))/F101 -> 2.6866556 | G102: ='A2 Inputs'!$C$19*((G100/8000000)^(LOG(0.88,2)))/G101 -> 2.517285 | H102: ='A2 Inputs'!$C$19*((H100/8000000)^(LOG(0.88,2)))/H101 -> 2.3747061 | I102: ='A2 Inputs'!$C$19*((I100/8000000)^(LOG(0.88,2)))/I101 -> 2.2502937
B103: buy_t | C103: =C99*'A2 Inputs'!$C$13*(1+'A2 Inputs'!$C$14)^0 -> 36000000 | D103: =D99*'A2 Inputs'!$C$13*(1+'A2 Inputs'!$C$14)^1 -> 46350000 | E103: =E99*'A2 Inputs'!$C$13*(1+'A2 Inputs'!$C$14)^2 -> 59675625 | F103: =F99*'A2 Inputs'!$C$13*(1+'A2 Inputs'!$C$14)^3 -> 76832367 | G103: =G99*'A2 Inputs'!$C$13*(1+'A2 Inputs'!$C$14)^4 -> 98921673 | H103: =H99*'A2 Inputs'!$C$13*(1+'A2 Inputs'!$C$14)^5 -> 1.2736165e+08 | I103: =I99*'A2 Inputs'!$C$13*(1+'A2 Inputs'!$C$14)^6 -> 1.6397813e+08
B104: build_t | C104: =C99*C102+'A2 Inputs'!$C$17*'A2 Inputs'!$C$23+'A2 Inputs'!$C$17 -> 73100000 | D104: =D99*D102+'A2 Inputs'!$C$17*'A2 Inputs'!$C$23 -> 38285912 | E104: =E99*E102+'A2 Inputs'!$C$17*'A2 Inputs'!$C$23 -> 40594070 | F104: =F99*F102+'A2 Inputs'!$C$17*'A2 Inputs'!$C$23 -> 44078994 | G104: =G99*G102+'A2 Inputs'!$C$17*'A2 Inputs'!$C$23 -> 51265723 | H104: =H99*H102+'A2 Inputs'!$C$17*'A2 Inputs'!$C$23 -> 60076223 | I104: =I99*I102+'A2 Inputs'!$C$17*'A2 Inputs'!$C$23 -> 70773514
B105: disc_t | C105: =(C103-C104)/(1+'A2 Inputs'!$C$10)^1 -> -33125000 | D105: =(D103-D104)/(1+'A2 Inputs'!$C$10)^2 -> 6428641.6 | E105: =(E103-E104)/(1+'A2 Inputs'!$C$10)^3 -> 13581874 | F105: =(F103-F104)/(1+'A2 Inputs'!$C$10)^4 -> 20815361 | G105: =(G103-G104)/(1+'A2 Inputs'!$C$10)^5 -> 27041266 | H105: =(H103-H104)/(1+'A2 Inputs'!$C$10)^6 -> 34088893 | I105: =(I103-I104)/(1+'A2 Inputs'!$C$10)^7 -> 42161034
B107: LR 0.85 / V1 1,000,000 | C107: Y1 | D107: Y2 | E107: Y3 | F107: Y4 | G107: Y5 | H107: Y6 | I107: Y7
B108: vol_t | C108: =1000000*(1+'A2 Inputs'!$C$8)^0 -> 1000000 | D108: =1000000*(1+'A2 Inputs'!$C$8)^1 -> 1250000 | E108: =1000000*(1+'A2 Inputs'!$C$8)^2 -> 1562500 | F108: =1000000*(1+'A2 Inputs'!$C$8)^3 -> 1953125 | G108: =1000000*(1+'A2 Inputs'!$C$8)^4 -> 2441406.2 | H108: =1000000*(1+'A2 Inputs'!$C$8)^5 -> 3051757.8 | I108: =1000000*(1+'A2 Inputs'!$C$8)^6 -> 3814697.3
B109: cumvol_t | C109: =1000000*((1+'A2 Inputs'!$C$8)^1-1)/'A2 Inputs'!$C$8 -> 1000000 | D109: =1000000*((1+'A2 Inputs'!$C$8)^2-1)/'A2 Inputs'!$C$8 -> 2250000 | E109: =1000000*((1+'A2 Inputs'!$C$8)^3-1)/'A2 Inputs'!$C$8 -> 3812500 | F109: =1000000*((1+'A2 Inputs'!$C$8)^4-1)/'A2 Inputs'!$C$8 -> 5765625 | G109: =1000000*((1+'A2 Inputs'!$C$8)^5-1)/'A2 Inputs'!$C$8 -> 8207031.2 | H109: =1000000*((1+'A2 Inputs'!$C$8)^6-1)/'A2 Inputs'!$C$8 -> 11258789 | I109: =1000000*((1+'A2 Inputs'!$C$8)^7-1)/'A2 Inputs'!$C$8 -> 15073486
B110: yield_t | C110: ='A2 Inputs'!$C$21+('A2 Inputs'!$C$22-'A2 Inputs'!$C$21)*MIN(1,(0)/3) -> 0.8 | D110: ='A2 Inputs'!$C$21+('A2 Inputs'!$C$22-'A2 Inputs'!$C$21)*MIN(1,(1)/3) -> 0.85666667 | E110: ='A2 Inputs'!$C$21+('A2 Inputs'!$C$22-'A2 Inputs'!$C$21)*MIN(1,(2)/3) -> 0.91333333 | F110: ='A2 Inputs'!$C$21+('A2 Inputs'!$C$22-'A2 Inputs'!$C$21)*MIN(1,(3)/3) -> 0.97 | G110: ='A2 Inputs'!$C$21+('A2 Inputs'!$C$22-'A2 Inputs'!$C$21)*MIN(1,(4)/3) -> 0.97 | H110: ='A2 Inputs'!$C$21+('A2 Inputs'!$C$22-'A2 Inputs'!$C$21)*MIN(1,(5)/3) -> 0.97 | I110: ='A2 Inputs'!$C$21+('A2 Inputs'!$C$22-'A2 Inputs'!$C$21)*MIN(1,(6)/3) -> 0.97
B111: inhouse_t | C111: ='A2 Inputs'!$C$19*((C109/1000000)^(LOG(0.85,2)))/C110 -> 4.5 | D111: ='A2 Inputs'!$C$19*((D109/1000000)^(LOG(0.85,2)))/D110 -> 3.47469 | E111: ='A2 Inputs'!$C$19*((E109/1000000)^(LOG(0.85,2)))/E110 -> 2.8800477 | F111: ='A2 Inputs'!$C$19*((F109/1000000)^(LOG(0.85,2)))/F110 -> 2.4611536 | G111: ='A2 Inputs'!$C$19*((G109/1000000)^(LOG(0.85,2)))/G110 -> 2.2656139 | H111: ='A2 Inputs'!$C$19*((H109/1000000)^(LOG(0.85,2)))/H110 -> 2.1037421 | I111: ='A2 Inputs'!$C$19*((I109/1000000)^(LOG(0.85,2)))/I110 -> 1.9646292
B112: buy_t | C112: =C108*'A2 Inputs'!$C$13*(1+'A2 Inputs'!$C$14)^0 -> 4500000 | D112: =D108*'A2 Inputs'!$C$13*(1+'A2 Inputs'!$C$14)^1 -> 5793750 | E112: =E108*'A2 Inputs'!$C$13*(1+'A2 Inputs'!$C$14)^2 -> 7459453.1 | F112: =F108*'A2 Inputs'!$C$13*(1+'A2 Inputs'!$C$14)^3 -> 9604045.9 | G112: =G108*'A2 Inputs'!$C$13*(1+'A2 Inputs'!$C$14)^4 -> 12365209 | H112: =H108*'A2 Inputs'!$C$13*(1+'A2 Inputs'!$C$14)^5 -> 15920207 | I112: =I108*'A2 Inputs'!$C$13*(1+'A2 Inputs'!$C$14)^6 -> 20497266
B113: build_t | C113: =C108*C111+'A2 Inputs'!$C$17*'A2 Inputs'!$C$23+'A2 Inputs'!$C$17 -> 41600000 | D113: =D108*D111+'A2 Inputs'!$C$17*'A2 Inputs'!$C$23 -> 6443362.5 | E113: =E108*E111+'A2 Inputs'!$C$17*'A2 Inputs'!$C$23 -> 6600074.5 | F113: =F108*F111+'A2 Inputs'!$C$17*'A2 Inputs'!$C$23 -> 6906940.7 | G113: =G108*G111+'A2 Inputs'!$C$17*'A2 Inputs'!$C$23 -> 7631283.8 | H113: =H108*H111+'A2 Inputs'!$C$17*'A2 Inputs'!$C$23 -> 8520111.5 | I113: =I108*I111+'A2 Inputs'!$C$17*'A2 Inputs'!$C$23 -> 9594465.6
...

Sheet A3 Inputs
B2: INPUTS & ASSUMPTIONS
B5: TIMELINE
B6: First deployment year | C6: 2028 | D6: year | E6: [FACT] | F6: SpaceX S-1: 'deploy as early as 2028'
B7: Years modeled (structural) | C7: 6 | D7: years | E7: [EST] | F7: 2028-2033
B9: PER-SATELLITE SPEC (AI1 'AI Sat Mini')
B10: Power per satellite | C10: ='Global Assumptions'!$C$11 -> 120 | D10: kW avg | E10: [REVEAL] | F10: AI1 reveal: 150 kW peak / 120 kW avg ~ one GB300 NVL72 rack
B11: Specific power | C11: ='Global Assumptions'!$C$12 -> 70 | D11: kW/ton | E11: [REVEAL] | F11: AI1 reveal: 70 kW/ton
B12: Mass per satellite | C12: =C10/C11 -> 1.7142857 | D12: tons | E12: [EST] | F12: power / specific power (120/70)
B13: Cost per sat (first-year anchor) | C13: 1.2 | D13: $M/unit | E13: [EST] | F13: Quilty: V3 ~\$1.2M/sat; AI-Sat likely higher - illustrative anchor
B14: Learning rate (Wright's law) | C14: 0.85 | D14: % | E14: [EST] | F14: Electronics/sat 85-90%; Starlink rode this curve
B16: FACTORY CAPACITY (Gigasat, Bastrop)
B17: Year-1 factory capacity | C17: 500 | D17: sats/yr | E17: [SPX-IN] | F17: Ramp start; illustrative
B18: Factory capacity growth | C18: 0.6 | D18: %/yr | E18: [TGT] | F18: Press name 'Gigasat'. Musk's roadmap: ~1 GW/yr of space compute by late 2027 = ~8,000 sats/yr at 120 kW. Model uses a deliberately conservative illustrative ramp from 500/yr [SPX-IN]; a larger real factory only makes LAUNCH bind harder, strengthening the finding.
B20: LAUNCH CAPACITY (Starship)
B21: Starship payload to LEO | C21: 150 | D21: tons | E21: [TGT] | F21: V3 target >100t reusable; use 150t
B22: Year-1 Starship flights (for AI-Sat) | C22: 6 | D22: flights/yr | E22: [SPX-IN] | F22: Illustrative AI-Sat allocation of cadence
B23: Launch cadence growth | C23: 0.45 | D23: %/yr | E23: [TGT] | F23: Aggressive ramp toward high cadence
B25: LAUNCH COST
B26: Launch cost | C26: ='Global Assumptions'!$C$7 -> 1000 | D26: $/kg | E26: [TGT] | F26: Starship target; not demonstrated
B29: J. Shapiro · Independent work sample · targets labeled [TGT], internal-needed [SPX-IN]

Sheet A3 Ramp
B2: PRODUCTION RAMP — CAPACITY-GATED
B4: Year | C4: ='A3 Inputs'!$C$6+0 -> 2028 | D4: ='A3 Inputs'!$C$6+1 -> 2029 | E4: ='A3 Inputs'!$C$6+2 -> 2030 | F4: ='A3 Inputs'!$C$6+3 -> 2031 | G4: ='A3 Inputs'!$C$6+4 -> 2032 | H4: ='A3 Inputs'!$C$6+5 -> 2033
B5: Factory capacity (sats/yr) | C5: ='A3 Inputs'!$C$17 -> 500 | D5: =C5*(1+'A3 Inputs'!$C$18) -> 800 | E5: =D5*(1+'A3 Inputs'!$C$18) -> 1280 | F5: =E5*(1+'A3 Inputs'!$C$18) -> 2048 | G5: =F5*(1+'A3 Inputs'!$C$18) -> 3276.8 | H5: =G5*(1+'A3 Inputs'!$C$18) -> 5242.88
B6: Launch-limited sats/yr | C6: =('A3 Inputs'!$C$22)*'A3 Inputs'!$C$21/'A3 Inputs'!$C$12 -> 525 | D6: =('A3 Inputs'!$C$22*(1+'A3 Inputs'!$C$23)^1)*'A3 Inputs'!$C$21/'A3 Inputs'!$C$12 -> 761.25 | E6: =('A3 Inputs'!$C$22*(1+'A3 Inputs'!$C$23)^2)*'A3 Inputs'!$C$21/'A3 Inputs'!$C$12 -> 1103.8125 | F6: =('A3 Inputs'!$C$22*(1+'A3 Inputs'!$C$23)^3)*'A3 Inputs'!$C$21/'A3 Inputs'!$C$12 -> 1600.5281 | G6: =('A3 Inputs'!$C$22*(1+'A3 Inputs'!$C$23)^4)*'A3 Inputs'!$C$21/'A3 Inputs'!$C$12 -> 2320.7658 | H6: =('A3 Inputs'!$C$22*(1+'A3 Inputs'!$C$23)^5)*'A3 Inputs'!$C$21/'A3 Inputs'!$C$12 -> 3365.1104
B7: Deployed sats/yr (min constraint) | C7: =MIN(C5,C6) -> 500 | D7: =MIN(D5,D6) -> 761.25 | E7: =MIN(E5,E6) -> 1103.8125 | F7: =MIN(F5,F6) -> 1600.5281 | G7: =MIN(G5,G6) -> 2320.7658 | H7: =MIN(H5,H6) -> 3365.1104
B8: Binding constraint | C8: =IF(C5<C6,"Factory","Launch") -> Factory | D8: =IF(D5<D6,"Factory","Launch") -> Launch | E8: =IF(E5<E6,"Factory","Launch") -> Launch | F8: =IF(F5<F6,"Factory","Launch") -> Launch | G8: =IF(G5<G6,"Factory","Launch") -> Launch | H8: =IF(H5<H6,"Factory","Launch") -> Launch
B10: Cumulative sats | C10: =C7 -> 500 | D10: =C10+D7 -> 1261.25 | E10: =D10+E7 -> 2365.0625 | F10: =E10+F7 -> 3965.5906 | G10: =F10+G7 -> 6286.3564 | H10: =G10+H7 -> 9651.4668
B11: Cost per sat ($M) | C11: ='A3 Inputs'!$C$13*((C10/C10)^(LOG('A3 Inputs'!$C$14,2))) -> 1.2 | D11: ='A3 Inputs'!$C$13*((D10/C10)^(LOG('A3 Inputs'!$C$14,2))) -> 0.9659748 | E11: ='A3 Inputs'!$C$13*((E10/C10)^(LOG('A3 Inputs'!$C$14,2))) -> 0.83357958 | F11: ='A3 Inputs'!$C$13*((F10/C10)^(LOG('A3 Inputs'!$C$14,2))) -> 0.73844433 | G11: ='A3 Inputs'!$C$13*((G10/C10)^(LOG('A3 Inputs'!$C$14,2))) -> 0.66283182 | H11: ='A3 Inputs'!$C$13*((H10/C10)^(LOG('A3 Inputs'!$C$14,2))) -> 0.59944211
B12: Manufacturing capex ($M) | C12: =C7*C11 -> 600 | D12: =D7*D11 -> 735.34832 | E12: =E7*E11 -> 920.11556 | F12: =F7*F11 -> 1181.9009 | G12: =G7*G11 -> 1538.2774 | H12: =H7*H11 -> 2017.1889
B13: Launch capex ($M) | C13: =C7*'A3 Inputs'!$C$12*1000*'A3 Inputs'!$C$26/1000000 -> 857.14286 | D13: =D7*'A3 Inputs'!$C$12*1000*'A3 Inputs'!$C$26/1000000 -> 1305 | E13: =E7*'A3 Inputs'!$C$12*1000*'A3 Inputs'!$C$26/1000000 -> 1892.25 | F13: =F7*'A3 Inputs'!$C$12*1000*'A3 Inputs'!$C$26/1000000 -> 2743.7625 | G13: =G7*'A3 Inputs'!$C$12*1000*'A3 Inputs'!$C$26/1000000 -> 3978.4556 | H13: =H7*'A3 Inputs'!$C$12*1000*'A3 Inputs'!$C$26/1000000 -> 5768.7607
B14: Total capex ($M) | C14: =C12+C13 -> 1457.1429 | D14: =D12+D13 -> 2040.3483 | E14: =E12+E13 -> 2812.3656 | F14: =F12+F13 -> 3925.6634 | G14: =G12+G13 -> 5516.733 | H14: =H12+H13 -> 7785.9495
B16: Power deployed/yr (MW) | C16: =C7*'A3 Inputs'!$C$10/1000 -> 60 | D16: =D7*'A3 Inputs'!$C$10/1000 -> 91.35 | E16: =E7*'A3 Inputs'!$C$10/1000 -> 132.4575 | F16: =F7*'A3 Inputs'!$C$10/1000 -> 192.06338 | G16: =G7*'A3 Inputs'!$C$10/1000 -> 278.49189 | H16: =H7*'A3 Inputs'!$C$10/1000 -> 403.81325
B17: Cumulative power (MW) | C17: =C16 -> 60 | D17: =C17+D16 -> 151.35 | E17: =D17+E16 -> 283.8075 | F17: =E17+F16 -> 475.87088 | G17: =F17+G16 -> 754.36277 | H17: =G17+H16 -> 1158.176
B18: Cumulative capex ($M) | C18: =C14 -> 1457.1429 | D18: =C18+D14 -> 3497.4912 | E18: =D18+E14 -> 6309.8567 | F18: =E18+F14 -> 10235.52 | G18: =F18+G14 -> 15752.253 | H18: =G18+H14 -> 23538.203
B19: $/MW deployed (cumulative) | C19: =C18/C17 -> 24.285714 | D19: =D18/D17 -> 23.10863 | E19: =E18/E17 -> 22.232875 | F19: =F18/F17 -> 21.509028 | G19: =G18/G17 -> 20.881536 | H19: =H18/H17 -> 20.323511
B21: Starship flights required/yr | C21: =C7*'A3 Inputs'!$C$12/'A3 Inputs'!$C$21 -> 5.7142857 | D21: =D7*'A3 Inputs'!$C$12/'A3 Inputs'!$C$21 -> 8.7 | E21: =E7*'A3 Inputs'!$C$12/'A3 Inputs'!$C$21 -> 12.615 | F21: =F7*'A3 Inputs'!$C$12/'A3 Inputs'!$C$21 -> 18.29175 | G21: =G7*'A3 Inputs'!$C$12/'A3 Inputs'!$C$21 -> 26.523038 | H21: =H7*'A3 Inputs'!$C$12/'A3 Inputs'!$C$21 -> 38.458404
B24: SUMMARY
B25: Cumulative power by final year (GW) | C25: =H17/1000 -> 1.158176
B26: Cumulative capex by final year ($M) | C26: =H18 -> 23538.203
B27: Cost per sat, final year ($M) | C27: =H11 -> 0.59944211
B30: J. Shapiro · Independent work sample · targets labeled [TGT], internal-needed [SPX-IN]

Sheet A3 Sensitivity
B2: CUMULATIVE POWER-TO-ORBIT (GW) BY FINAL YEAR
B3: vs. Year-1 AI-Sat launch flights (rows) × launch cadence growth (cols). Factory capacity linked to Inputs; each cell
B4: reproduces tab 2's min(factory, launch) gate per year. Axes scoped so launch is the visible constraint (per the memo).
B6: Y1 flights \ growth | C6: 0.3 | D6: 0.45 | E6: 0.6 | F6: 0.8
B7: 3 | C7: =SUM(C16:H16) -> 0.40181494 | D7: =SUM(C18:H18) -> 0.58058801 | E7: =SUM(C20:H20) -> 0.82830384 | F7: =SUM(C22:H22) -> 1.2998563
B8: 4 | C8: =SUM(C24:H24) -> 0.53575326 | D8: =SUM(C26:H26) -> 0.77411734 | E8: =SUM(C28:H28) -> 1.1044051 | F8: =SUM(C30:H30) -> 1.5209856
B9: 6 | C9: =SUM(C32:H32) -> 0.80062989 | D9: =SUM(C34:H34) -> 1.158176 | E9: =SUM(C36:H36) -> 1.5777216 | F9: =SUM(C38:H38) -> 1.5777216
B10: 8 | C10: =SUM(C40:H40) -> 1.0343065 | D10: =SUM(C42:H42) -> 1.4651002 | E10: =SUM(C44:H44) -> 1.5777216 | F10: =SUM(C46:H46) -> 1.5777216
B11: 12 | C11: =SUM(C48:H48) -> 1.3830578 | D11: =SUM(C50:H50) -> 1.5777216 | E11: =SUM(C52:H52) -> 1.5777216 | F11: =SUM(C54:H54) -> 1.5777216
B13: TIE-OUT: base cell (6 flights / 0.45 growth) equals tab 2 'Cumulative power by final year' (~1.16 GW).
B14: READING: green >1 GW; yellow 0.3-1 GW; red <0.3 GW. Reaching ~1 GW requires sustained high launch cadence —
B15: the factory (Gigasat) rarely binds. This reframes '1 GW by end-2027' as a LAUNCH-cadence problem; S-1's 2028 is the base.
B16: WHAT I'D NEED FROM SPACEX: real per-sat mass & cost, Gigasat ramp, AI-Sat share of cadence, realized Starship payload, learning rate. | C16: =MIN('A3 Inputs'!$C$17*(1+'A3 Inputs'!$C$18)^0,3*(1+0.3)^0*'A3 Inputs'!$C$21/'A3 Inputs'!$C$12)*'A3 Inputs'!$C$10/1000000 -> 0.0315 | D16: =MIN('A3 Inputs'!$C$17*(1+'A3 Inputs'!$C$18)^1,3*(1+0.3)^1*'A3 Inputs'!$C$21/'A3 Inputs'!$C$12)*'A3 Inputs'!$C$10/1000000 -> 0.04095 | E16: =MIN('A3 Inputs'!$C$17*(1+'A3 Inputs'!$C$18)^2,3*(1+0.3)^2*'A3 Inputs'!$C$21/'A3 Inputs'!$C$12)*'A3 Inputs'!$C$10/1000000 -> 0.053235 | F16: =MIN('A3 Inputs'!$C$17*(1+'A3 Inputs'!$C$18)^3,3*(1+0.3)^3*'A3 Inputs'!$C$21/'A3 Inputs'!$C$12)*'A3 Inputs'!$C$10/1000000 -> 0.0692055 | G16: =MIN('A3 Inputs'!$C$17*(1+'A3 Inputs'!$C$18)^4,3*(1+0.3)^4*'A3 Inputs'!$C$21/'A3 Inputs'!$C$12)*'A3 Inputs'!$C$10/1000000 -> 0.08996715 | H16: =MIN('A3 Inputs'!$C$17*(1+'A3 Inputs'!$C$18)^5,3*(1+0.3)^5*'A3 Inputs'!$C$21/'A3 Inputs'!$C$12)*'A3 Inputs'!$C$10/1000000 -> 0.1169573
B18: 3 fl / 0.45 grw | C18: =MIN('A3 Inputs'!$C$17*(1+'A3 Inputs'!$C$18)^0,3*(1+0.45)^0*'A3 Inputs'!$C$21/'A3 Inputs'!$C$12)*'A3 Inputs'!$C$10/1000000 -> 0.0315 | D18: =MIN('A3 Inputs'!$C$17*(1+'A3 Inputs'!$C$18)^1,3*(1+0.45)^1*'A3 Inputs'!$C$21/'A3 Inputs'!$C$12)*'A3 Inputs'!$C$10/1000000 -> 0.045675 | E18: =MIN('A3 Inputs'!$C$17*(1+'A3 Inputs'!$C$18)^2,3*(1+0.45)^2*'A3 Inputs'!$C$21/'A3 Inputs'!$C$12)*'A3 Inputs'!$C$10/1000000 -> 0.06622875 | F18: =MIN('A3 Inputs'!$C$17*(1+'A3 Inputs'!$C$18)^3,3*(1+0.45)^3*'A3 Inputs'!$C$21/'A3 Inputs'!$C$12)*'A3 Inputs'!$C$10/1000000 -> 0.096031688 | G18: =MIN('A3 Inputs'!$C$17*(1+'A3 Inputs'!$C$18)^4,3*(1+0.45)^4*'A3 Inputs'!$C$21/'A3 Inputs'!$C$12)*'A3 Inputs'!$C$10/1000000 -> 0.13924595 | H18: =MIN('A3 Inputs'!$C$17*(1+'A3 Inputs'!$C$18)^5,3*(1+0.45)^5*'A3 Inputs'!$C$21/'A3 Inputs'!$C$12)*'A3 Inputs'!$C$10/1000000 -> 0.20190662
B20: 3 fl / 0.6 grw | C20: =MIN('A3 Inputs'!$C$17*(1+'A3 Inputs'!$C$18)^0,3*(1+0.6)^0*'A3 Inputs'!$C$21/'A3 Inputs'!$C$12)*'A3 Inputs'!$C$10/1000000 -> 0.0315 | D20: =MIN('A3 Inputs'!$C$17*(1+'A3 Inputs'!$C$18)^1,3*(1+0.6)^1*'A3 Inputs'!$C$21/'A3 Inputs'!$C$12)*'A3 Inputs'!$C$10/1000000 -> 0.0504 | E20: =MIN('A3 Inputs'!$C$17*(1+'A3 Inputs'!$C$18)^2,3*(1+0.6)^2*'A3 Inputs'!$C$21/'A3 Inputs'!$C$12)*'A3 Inputs'!$C$10/1000000 -> 0.08064 | F20: =MIN('A3 Inputs'!$C$17*(1+'A3 Inputs'!$C$18)^3,3*(1+0.6)^3*'A3 Inputs'!$C$21/'A3 Inputs'!$C$12)*'A3 Inputs'!$C$10/1000000 -> 0.129024 | G20: =MIN('A3 Inputs'!$C$17*(1+'A3 Inputs'!$C$18)^4,3*(1+0.6)^4*'A3 Inputs'!$C$21/'A3 Inputs'!$C$12)*'A3 Inputs'!$C$10/1000000 -> 0.2064384 | H20: =MIN('A3 Inputs'!$C$17*(1+'A3 Inputs'!$C$18)^5,3*(1+0.6)^5*'A3 Inputs'!$C$21/'A3 Inputs'!$C$12)*'A3 Inputs'!$C$10/1000000 -> 0.33030144
B22: 3 fl / 0.8 grw | C22: =MIN('A3 Inputs'!$C$17*(1+'A3 Inputs'!$C$18)^0,3*(1+0.8)^0*'A3 Inputs'!$C$21/'A3 Inputs'!$C$12)*'A3 Inputs'!$C$10/1000000 -> 0.0315 | D22: =MIN('A3 Inputs'!$C$17*(1+'A3 Inputs'!$C$18)^1,3*(1+0.8)^1*'A3 Inputs'!$C$21/'A3 Inputs'!$C$12)*'A3 Inputs'!$C$10/1000000 -> 0.0567 | E22: =MIN('A3 Inputs'!$C$17*(1+'A3 Inputs'!$C$18)^2,3*(1+0.8)^2*'A3 Inputs'!$C$21/'A3 Inputs'!$C$12)*'A3 Inputs'!$C$10/1000000 -> 0.10206 | F22: =MIN('A3 Inputs'!$C$17*(1+'A3 Inputs'!$C$18)^3,3*(1+0.8)^3*'A3 Inputs'!$C$21/'A3 Inputs'!$C$12)*'A3 Inputs'!$C$10/1000000 -> 0.183708 | G22: =MIN('A3 Inputs'!$C$17*(1+'A3 Inputs'!$C$18)^4,3*(1+0.8)^4*'A3 Inputs'!$C$21/'A3 Inputs'!$C$12)*'A3 Inputs'!$C$10/1000000 -> 0.3306744 | H22: =MIN('A3 Inputs'!$C$17*(1+'A3 Inputs'!$C$18)^5,3*(1+0.8)^5*'A3 Inputs'!$C$21/'A3 Inputs'!$C$12)*'A3 Inputs'!$C$10/1000000 -> 0.59521392
B24: 4 fl / 0.3 grw | C24: =MIN('A3 Inputs'!$C$17*(1+'A3 Inputs'!$C$18)^0,4*(1+0.3)^0*'A3 Inputs'!$C$21/'A3 Inputs'!$C$12)*'A3 Inputs'!$C$10/1000000 -> 0.042 | D24: =MIN('A3 Inputs'!$C$17*(1+'A3 Inputs'!$C$18)^1,4*(1+0.3)^1*'A3 Inputs'!$C$21/'A3 Inputs'!$C$12)*'A3 Inputs'!$C$10/1000000 -> 0.0546 | E24: =MIN('A3 Inputs'!$C$17*(1+'A3 Inputs'!$C$18)^2,4*(1+0.3)^2*'A3 Inputs'!$C$21/'A3 Inputs'!$C$12)*'A3 Inputs'!$C$10/1000000 -> 0.07098 | F24: =MIN('A3 Inputs'!$C$17*(1+'A3 Inputs'!$C$18)^3,4*(1+0.3)^3*'A3 Inputs'!$C$21/'A3 Inputs'!$C$12)*'A3 Inputs'!$C$10/1000000 -> 0.092274 | G24: =MIN('A3 Inputs'!$C$17*(1+'A3 Inputs'!$C$18)^4,4*(1+0.3)^4*'A3 Inputs'!$C$21/'A3 Inputs'!$C$12)*'A3 Inputs'!$C$10/1000000 -> 0.1199562 | H24: =MIN('A3 Inputs'!$C$17*(1+'A3 Inputs'!$C$18)^5,4*(1+0.3)^5*'A3 Inputs'!$C$21/'A3 Inputs'!$C$12)*'A3 Inputs'!$C$10/1000000 -> 0.15594306
B26: 4 fl / 0.45 grw | C26: =MIN('A3 Inputs'!$C$17*(1+'A3 Inputs'!$C$18)^0,4*(1+0.45)^0*'A3 Inputs'!$C$21/'A3 Inputs'!$C$12)*'A3 Inputs'!$C$10/1000000 -> 0.042 | D26: =MIN('A3 Inputs'!$C$17*(1+'A3 Inputs'!$C$18)^1,4*(1+0.45)^1*'A3 Inputs'!$C$21/'A3 Inputs'!$C$12)*'A3 Inputs'!$C$10/1000000 -> 0.0609 | E26: =MIN('A3 Inputs'!$C$17*(1+'A3 Inputs'!$C$18)^2,4*(1+0.45)^2*'A3 Inputs'!$C$21/'A3 Inputs'!$C$12)*'A3 Inputs'!$C$10/1000000 -> 0.088305 | F26: =MIN('A3 Inputs'!$C$17*(1+'A3 Inputs'!$C$18)^3,4*(1+0.45)^3*'A3 Inputs'!$C$21/'A3 Inputs'!$C$12)*'A3 Inputs'!$C$10/1000000 -> 0.12804225 | G26: =MIN('A3 Inputs'!$C$17*(1+'A3 Inputs'!$C$18)^4,4*(1+0.45)^4*'A3 Inputs'!$C$21/'A3 Inputs'!$C$12)*'A3 Inputs'!$C$10/1000000 -> 0.18566126 | H26: =MIN('A3 Inputs'!$C$17*(1+'A3 Inputs'!$C$18)^5,4*(1+0.45)^5*'A3 Inputs'!$C$21/'A3 Inputs'!$C$12)*'A3 Inputs'!$C$10/1000000 -> 0.26920883
B28: 4 fl / 0.6 grw | C28: =MIN('A3 Inputs'!$C$17*(1+'A3 Inputs'!$C$18)^0,4*(1+0.6)^0*'A3 Inputs'!$C$21/'A3 Inputs'!$C$12)*'A3 Inputs'!$C$10/1000000 -> 0.042 | D28: =MIN('A3 Inputs'!$C$17*(1+'A3 Inputs'!$C$18)^1,4*(1+0.6)^1*'A3 Inputs'!$C$21/'A3 Inputs'!$C$12)*'A3 Inputs'!$C$10/1000000 -> 0.0672 | E28: =MIN('A3 Inputs'!$C$17*(1+'A3 Inputs'!$C$18)^2,4*(1+0.6)^2*'A3 Inputs'!$C$21/'A3 Inputs'!$C$12)*'A3 Inputs'!$C$10/1000000 -> 0.10752 | F28: =MIN('A3 Inputs'!$C$17*(1+'A3 Inputs'!$C$18)^3,4*(1+0.6)^3*'A3 Inputs'!$C$21/'A3 Inputs'!$C$12)*'A3 Inputs'!$C$10/1000000 -> 0.172032 | G28: =MIN('A3 Inputs'!$C$17*(1+'A3 Inputs'!$C$18)^4,4*(1+0.6)^4*'A3 Inputs'!$C$21/'A3 Inputs'!$C$12)*'A3 Inputs'!$C$10/1000000 -> 0.2752512 | H28: =MIN('A3 Inputs'!$C$17*(1+'A3 Inputs'!$C$18)^5,4*(1+0.6)^5*'A3 Inputs'!$C$21/'A3 Inputs'!$C$12)*'A3 Inputs'!$C$10/1000000 -> 0.44040192
B30: 4 fl / 0.8 grw | C30: =MIN('A3 Inputs'!$C$17*(1+'A3 Inputs'!$C$18)^0,4*(1+0.8)^0*'A3 Inputs'!$C$21/'A3 Inputs'!$C$12)*'A3 Inputs'!$C$10/1000000 -> 0.042 | D30: =MIN('A3 Inputs'!$C$17*(1+'A3 Inputs'!$C$18)^1,4*(1+0.8)^1*'A3 Inputs'!$C$21/'A3 Inputs'!$C$12)*'A3 Inputs'!$C$10/1000000 -> 0.0756 | E30: =MIN('A3 Inputs'!$C$17*(1+'A3 Inputs'!$C$18)^2,4*(1+0.8)^2*'A3 Inputs'!$C$21/'A3 Inputs'!$C$12)*'A3 Inputs'!$C$10/1000000 -> 0.13608 | F30: =MIN('A3 Inputs'!$C$17*(1+'A3 Inputs'!$C$18)^3,4*(1+0.8)^3*'A3 Inputs'!$C$21/'A3 Inputs'!$C$12)*'A3 Inputs'!$C$10/1000000 -> 0.244944 | G30: =MIN('A3 Inputs'!$C$17*(1+'A3 Inputs'!$C$18)^4,4*(1+0.8)^4*'A3 Inputs'!$C$21/'A3 Inputs'!$C$12)*'A3 Inputs'!$C$10/1000000 -> 0.393216 | H30: =MIN('A3 Inputs'!$C$17*(1+'A3 Inputs'!$C$18)^5,4*(1+0.8)^5*'A3 Inputs'!$C$21/'A3 Inputs'!$C$12)*'A3 Inputs'!$C$10/1000000 -> 0.6291456
B32: 6 fl / 0.3 grw | C32: =MIN('A3 Inputs'!$C$17*(1+'A3 Inputs'!$C$18)^0,6*(1+0.3)^0*'A3 Inputs'!$C$21/'A3 Inputs'!$C$12)*'A3 Inputs'!$C$10/1000000 -> 0.06 | D32: =MIN('A3 Inputs'!$C$17*(1+'A3 Inputs'!$C$18)^1,6*(1+0.3)^1*'A3 Inputs'!$C$21/'A3 Inputs'!$C$12)*'A3 Inputs'!$C$10/1000000 -> 0.0819 | E32: =MIN('A3 Inputs'!$C$17*(1+'A3 Inputs'!$C$18)^2,6*(1+0.3)^2*'A3 Inputs'!$C$21/'A3 Inputs'!$C$12)*'A3 Inputs'!$C$10/1000000 -> 0.10647 | F32: =MIN('A3 Inputs'!$C$17*(1+'A3 Inputs'!$C$18)^3,6*(1+0.3)^3*'A3 Inputs'!$C$21/'A3 Inputs'!$C$12)*'A3 Inputs'!$C$10/1000000 -> 0.138411 | G32: =MIN('A3 Inputs'!$C$17*(1+'A3 Inputs'!$C$18)^4,6*(1+0.3)^4*'A3 Inputs'!$C$21/'A3 Inputs'!$C$12)*'A3 Inputs'!$C$10/1000000 -> 0.1799343 | H32: =MIN('A3 Inputs'!$C$17*(1+'A3 Inputs'!$C$18)^5,6*(1+0.3)^5*'A3 Inputs'!$C$21/'A3 Inputs'!$C$12)*'A3 Inputs'!$C$10/1000000 -> 0.23391459
B34: 6 fl / 0.45 grw | C34: =MIN('A3 Inputs'!$C$17*(1+'A3 Inputs'!$C$18)^0,6*(1+0.45)^0*'A3 Inputs'!$C$21/'A3 Inputs'!$C$12)*'A3 Inputs'!$C$10/1000000 -> 0.06 | D34: =MIN('A3 Inputs'!$C$17*(1+'A3 Inputs'!$C$18)^1,6*(1+0.45)^1*'A3 Inputs'!$C$21/'A3 Inputs'!$C$12)*'A3 Inputs'!$C$10/1000000 -> 0.09135 | E34: =MIN('A3 Inputs'!$C$17*(1+'A3 Inputs'!$C$18)^2,6*(1+0.45)^2*'A3 Inputs'!$C$21/'A3 Inputs'!$C$12)*'A3 Inputs'!$C$10/1000000 -> 0.1324575 | F34: =MIN('A3 Inputs'!$C$17*(1+'A3 Inputs'!$C$18)^3,6*(1+0.45)^3*'A3 Inputs'!$C$21/'A3 Inputs'!$C$12)*'A3 Inputs'!$C$10/1000000 -> 0.19206338 | G34: =MIN('A3 Inputs'!$C$17*(1+'A3 Inputs'!$C$18)^4,6*(1+0.45)^4*'A3 Inputs'!$C$21/'A3 Inputs'!$C$12)*'A3 Inputs'!$C$10/1000000 -> 0.27849189 | H34: =MIN('A3 Inputs'!$C$17*(1+'A3 Inputs'!$C$18)^5,6*(1+0.45)^5*'A3 Inputs'!$C$21/'A3 Inputs'!$C$12)*'A3 Inputs'!$C$10/1000000 -> 0.40381325
B36: 6 fl / 0.6 grw | C36: =MIN('A3 Inputs'!$C$17*(1+'A3 Inputs'!$C$18)^0,6*(1+0.6)^0*'A3 Inputs'!$C$21/'A3 Inputs'!$C$12)*'A3 Inputs'!$C$10/1000000 -> 0.06 | D36: =MIN('A3 Inputs'!$C$17*(1+'A3 Inputs'!$C$18)^1,6*(1+0.6)^1*'A3 Inputs'!$C$21/'A3 Inputs'!$C$12)*'A3 Inputs'!$C$10/1000000 -> 0.096 | E36: =MIN('A3 Inputs'!$C$17*(1+'A3 Inputs'!$C$18)^2,6*(1+0.6)^2*'A3 Inputs'!$C$21/'A3 Inputs'!$C$12)*'A3 Inputs'!$C$10/1000000 -> 0.1536 | F36: =MIN('A3 Inputs'!$C$17*(1+'A3 Inputs'!$C$18)^3,6*(1+0.6)^3*'A3 Inputs'!$C$21/'A3 Inputs'!$C$12)*'A3 Inputs'!$C$10/1000000 -> 0.24576 | G36: =MIN('A3 Inputs'!$C$17*(1+'A3 Inputs'!$C$18)^4,6*(1+0.6)^4*'A3 Inputs'!$C$21/'A3 Inputs'!$C$12)*'A3 Inputs'!$C$10/1000000 -> 0.393216 | H36: =MIN('A3 Inputs'!$C$17*(1+'A3 Inputs'!$C$18)^5,6*(1+0.6)^5*'A3 Inputs'!$C$21/'A3 Inputs'!$C$12)*'A3 Inputs'!$C$10/1000000 -> 0.6291456
B38: 6 fl / 0.8 grw | C38: =MIN('A3 Inputs'!$C$17*(1+'A3 Inputs'!$C$18)^0,6*(1+0.8)^0*'A3 Inputs'!$C$21/'A3 Inputs'!$C$12)*'A3 Inputs'!$C$10/1000000 -> 0.06 | D38: =MIN('A3 Inputs'!$C$17*(1+'A3 Inputs'!$C$18)^1,6*(1+0.8)^1*'A3 Inputs'!$C$21/'A3 Inputs'!$C$12)*'A3 Inputs'!$C$10/1000000 -> 0.096 | E38: =MIN('A3 Inputs'!$C$17*(1+'A3 Inputs'!$C$18)^2,6*(1+0.8)^2*'A3 Inputs'!$C$21/'A3 Inputs'!$C$12)*'A3 Inputs'!$C$10/1000000 -> 0.1536 | F38: =MIN('A3 Inputs'!$C$17*(1+'A3 Inputs'!$C$18)^3,6*(1+0.8)^3*'A3 Inputs'!$C$21/'A3 Inputs'!$C$12)*'A3 Inputs'!$C$10/1000000 -> 0.24576 | G38: =MIN('A3 Inputs'!$C$17*(1+'A3 Inputs'!$C$18)^4,6*(1+0.8)^4*'A3 Inputs'!$C$21/'A3 Inputs'!$C$12)*'A3 Inputs'!$C$10/1000000 -> 0.393216 | H38: =MIN('A3 Inputs'!$C$17*(1+'A3 Inputs'!$C$18)^5,6*(1+0.8)^5*'A3 Inputs'!$C$21/'A3 Inputs'!$C$12)*'A3 Inputs'!$C$10/1000000 -> 0.6291456
B40: 8 fl / 0.3 grw | C40: =MIN('A3 Inputs'!$C$17*(1+'A3 Inputs'!$C$18)^0,8*(1+0.3)^0*'A3 Inputs'!$C$21/'A3 Inputs'!$C$12)*'A3 Inputs'!$C$10/1000000 -> 0.06 | D40: =MIN('A3 Inputs'!$C$17*(1+'A3 Inputs'!$C$18)^1,8*(1+0.3)^1*'A3 Inputs'!$C$21/'A3 Inputs'!$C$12)*'A3 Inputs'!$C$10/1000000 -> 0.096 | E40: =MIN('A3 Inputs'!$C$17*(1+'A3 Inputs'!$C$18)^2,8*(1+0.3)^2*'A3 Inputs'!$C$21/'A3 Inputs'!$C$12)*'A3 Inputs'!$C$10/1000000 -> 0.14196 | F40: =MIN('A3 Inputs'!$C$17*(1+'A3 Inputs'!$C$18)^3,8*(1+0.3)^3*'A3 Inputs'!$C$21/'A3 Inputs'!$C$12)*'A3 Inputs'!$C$10/1000000 -> 0.184548 | G40: =MIN('A3 Inputs'!$C$17*(1+'A3 Inputs'!$C$18)^4,8*(1+0.3)^4*'A3 Inputs'!$C$21/'A3 Inputs'!$C$12)*'A3 Inputs'!$C$10/1000000 -> 0.2399124 | H40: =MIN('A3 Inputs'!$C$17*(1+'A3 Inputs'!$C$18)^5,8*(1+0.3)^5*'A3 Inputs'!$C$21/'A3 Inputs'!$C$12)*'A3 Inputs'!$C$10/1000000 -> 0.31188612
B42: 8 fl / 0.45 grw | C42: =MIN('A3 Inputs'!$C$17*(1+'A3 Inputs'!$C$18)^0,8*(1+0.45)^0*'A3 Inputs'!$C$21/'A3 Inputs'!$C$12)*'A3 Inputs'!$C$10/1000000 -> 0.06 | D42: =MIN('A3 Inputs'!$C$17*(1+'A3 Inputs'!$C$18)^1,8*(1+0.45)^1*'A3 Inputs'!$C$21/'A3 Inputs'!$C$12)*'A3 Inputs'!$C$10/1000000 -> 0.096 | E42: =MIN('A3 Inputs'!$C$17*(1+'A3 Inputs'!$C$18)^2,8*(1+0.45)^2*'A3 Inputs'!$C$21/'A3 Inputs'!$C$12)*'A3 Inputs'!$C$10/1000000 -> 0.1536 | F42: =MIN('A3 Inputs'!$C$17*(1+'A3 Inputs'!$C$18)^3,8*(1+0.45)^3*'A3 Inputs'!$C$21/'A3 Inputs'!$C$12)*'A3 Inputs'!$C$10/1000000 -> 0.24576 | G42: =MIN('A3 Inputs'!$C$17*(1+'A3 Inputs'!$C$18)^4,8*(1+0.45)^4*'A3 Inputs'!$C$21/'A3 Inputs'!$C$12)*'A3 Inputs'!$C$10/1000000 -> 0.37132253 | H42: =MIN('A3 Inputs'!$C$17*(1+'A3 Inputs'!$C$18)^5,8*(1+0.45)^5*'A3 Inputs'!$C$21/'A3 Inputs'!$C$12)*'A3 Inputs'!$C$10/1000000 -> 0.53841766
B44: 8 fl / 0.6 grw | C44: =MIN('A3 Inputs'!$C$17*(1+'A3 Inputs'!$C$18)^0,8*(1+0.6)^0*'A3 Inputs'!$C$21/'A3 Inputs'!$C$12)*'A3 Inputs'!$C$10/1000000 -> 0.06 | D44: =MIN('A3 Inputs'!$C$17*(1+'A3 Inputs'!$C$18)^1,8*(1+0.6)^1*'A3 Inputs'!$C$21/'A3 Inputs'!$C$12)*'A3 Inputs'!$C$10/1000000 -> 0.096 | E44: =MIN('A3 Inputs'!$C$17*(1+'A3 Inputs'!$C$18)^2,8*(1+0.6)^2*'A3 Inputs'!$C$21/'A3 Inputs'!$C$12)*'A3 Inputs'!$C$10/1000000 -> 0.1536 | F44: =MIN('A3 Inputs'!$C$17*(1+'A3 Inputs'!$C$18)^3,8*(1+0.6)^3*'A3 Inputs'!$C$21/'A3 Inputs'!$C$12)*'A3 Inputs'!$C$10/1000000 -> 0.24576 | G44: =MIN('A3 Inputs'!$C$17*(1+'A3 Inputs'!$C$18)^4,8*(1+0.6)^4*'A3 Inputs'!$C$21/'A3 Inputs'!$C$12)*'A3 Inputs'!$C$10/1000000 -> 0.393216 | H44: =MIN('A3 Inputs'!$C$17*(1+'A3 Inputs'!$C$18)^5,8*(1+0.6)^5*'A3 Inputs'!$C$21/'A3 Inputs'!$C$12)*'A3 Inputs'!$C$10/1000000 -> 0.6291456
B46: 8 fl / 0.8 grw | C46: =MIN('A3 Inputs'!$C$17*(1+'A3 Inputs'!$C$18)^0,8*(1+0.8)^0*'A3 Inputs'!$C$21/'A3 Inputs'!$C$12)*'A3 Inputs'!$C$10/1000000 -> 0.06 | D46: =MIN('A3 Inputs'!$C$17*(1+'A3 Inputs'!$C$18)^1,8*(1+0.8)^1*'A3 Inputs'!$C$21/'A3 Inputs'!$C$12)*'A3 Inputs'!$C$10/1000000 -> 0.096 | E46: =MIN('A3 Inputs'!$C$17*(1+'A3 Inputs'!$C$18)^2,8*(1+0.8)^2*'A3 Inputs'!$C$21/'A3 Inputs'!$C$12)*'A3 Inputs'!$C$10/1000000 -> 0.1536 | F46: =MIN('A3 Inputs'!$C$17*(1+'A3 Inputs'!$C$18)^3,8*(1+0.8)^3*'A3 Inputs'!$C$21/'A3 Inputs'!$C$12)*'A3 Inputs'!$C$10/1000000 -> 0.24576 | G46: =MIN('A3 Inputs'!$C$17*(1+'A3 Inputs'!$C$18)^4,8*(1+0.8)^4*'A3 Inputs'!$C$21/'A3 Inputs'!$C$12)*'A3 Inputs'!$C$10/1000000 -> 0.393216 | H46: =MIN('A3 Inputs'!$C$17*(1+'A3 Inputs'!$C$18)^5,8*(1+0.8)^5*'A3 Inputs'!$C$21/'A3 Inputs'!$C$12)*'A3 Inputs'!$C$10/1000000 -> 0.6291456
B48: 12 fl / 0.3 grw | C48: =MIN('A3 Inputs'!$C$17*(1+'A3 Inputs'!$C$18)^0,12*(1+0.3)^0*'A3 Inputs'!$C$21/'A3 Inputs'!$C$12)*'A3 Inputs'!$C$10/1000000 -> 0.06 | D48: =MIN('A3 Inputs'!$C$17*(1+'A3 Inputs'!$C$18)^1,12*(1+0.3)^1*'A3 Inputs'!$C$21/'A3 Inputs'!$C$12)*'A3 Inputs'!$C$10/1000000 -> 0.096 | E48: =MIN('A3 Inputs'!$C$17*(1+'A3 Inputs'!$C$18)^2,12*(1+0.3)^2*'A3 Inputs'!$C$21/'A3 Inputs'!$C$12)*'A3 Inputs'!$C$10/1000000 -> 0.1536 | F48: =MIN('A3 Inputs'!$C$17*(1+'A3 Inputs'!$C$18)^3,12*(1+0.3)^3*'A3 Inputs'!$C$21/'A3 Inputs'!$C$12)*'A3 Inputs'!$C$10/1000000 -> 0.24576 | G48: =MIN('A3 Inputs'!$C$17*(1+'A3 Inputs'!$C$18)^4,12*(1+0.3)^4*'A3 Inputs'!$C$21/'A3 Inputs'!$C$12)*'A3 Inputs'!$C$10/1000000 -> 0.3598686 | H48: =MIN('A3 Inputs'!$C$17*(1+'A3 Inputs'!$C$18)^5,12*(1+0.3)^5*'A3 Inputs'!$C$21/'A3 Inputs'!$C$12)*'A3 Inputs'!$C$10/1000000 -> 0.46782918
B50: 12 fl / 0.45 grw | C50: =MIN('A3 Inputs'!$C$17*(1+'A3 Inputs'!$C$18)^0,12*(1+0.45)^0*'A3 Inputs'!$C$21/'A3 Inputs'!$C$12)*'A3 Inputs'!$C$10/1000000 -> 0.06 | D50: =MIN('A3 Inputs'!$C$17*(1+'A3 Inputs'!$C$18)^1,12*(1+0.45)^1*'A3 Inputs'!$C$21/'A3 Inputs'!$C$12)*'A3 Inputs'!$C$10/1000000 -> 0.096 | E50: =MIN('A3 Inputs'!$C$17*(1+'A3 Inputs'!$C$18)^2,12*(1+0.45)^2*'A3 Inputs'!$C$21/'A3 Inputs'!$C$12)*'A3 Inputs'!$C$10/1000000 -> 0.1536 | F50: =MIN('A3 Inputs'!$C$17*(1+'A3 Inputs'!$C$18)^3,12*(1+0.45)^3*'A3 Inputs'!$C$21/'A3 Inputs'!$C$12)*'A3 Inputs'!$C$10/1000000 -> 0.24576 | G50: =MIN('A3 Inputs'!$C$17*(1+'A3 Inputs'!$C$18)^4,12*(1+0.45)^4*'A3 Inputs'!$C$21/'A3 Inputs'!$C$12)*'A3 Inputs'!$C$10/1000000 -> 0.393216 | H50: =MIN('A3 Inputs'!$C$17*(1+'A3 Inputs'!$C$18)^5,12*(1+0.45)^5*'A3 Inputs'!$C$21/'A3 Inputs'!$C$12)*'A3 Inputs'!$C$10/1000000 -> 0.6291456
B52: 12 fl / 0.6 grw | C52: =MIN('A3 Inputs'!$C$17*(1+'A3 Inputs'!$C$18)^0,12*(1+0.6)^0*'A3 Inputs'!$C$21/'A3 Inputs'!$C$12)*'A3 Inputs'!$C$10/1000000 -> 0.06 | D52: =MIN('A3 Inputs'!$C$17*(1+'A3 Inputs'!$C$18)^1,12*(1+0.6)^1*'A3 Inputs'!$C$21/'A3 Inputs'!$C$12)*'A3 Inputs'!$C$10/1000000 -> 0.096 | E52: =MIN('A3 Inputs'!$C$17*(1+'A3 Inputs'!$C$18)^2,12*(1+0.6)^2*'A3 Inputs'!$C$21/'A3 Inputs'!$C$12)*'A3 Inputs'!$C$10/1000000 -> 0.1536 | F52: =MIN('A3 Inputs'!$C$17*(1+'A3 Inputs'!$C$18)^3,12*(1+0.6)^3*'A3 Inputs'!$C$21/'A3 Inputs'!$C$12)*'A3 Inputs'!$C$10/1000000 -> 0.24576 | G52: =MIN('A3 Inputs'!$C$17*(1+'A3 Inputs'!$C$18)^4,12*(1+0.6)^4*'A3 Inputs'!$C$21/'A3 Inputs'!$C$12)*'A3 Inputs'!$C$10/1000000 -> 0.393216 | H52: =MIN('A3 Inputs'!$C$17*(1+'A3 Inputs'!$C$18)^5,12*(1+0.6)^5*'A3 Inputs'!$C$21/'A3 Inputs'!$C$12)*'A3 Inputs'!$C$10/1000000 -> 0.6291456
B54: 12 fl / 0.8 grw | C54: =MIN('A3 Inputs'!$C$17*(1+'A3 Inputs'!$C$18)^0,12*(1+0.8)^0*'A3 Inputs'!$C$21/'A3 Inputs'!$C$12)*'A3 Inputs'!$C$10/1000000 -> 0.06 | D54: =MIN('A3 Inputs'!$C$17*(1+'A3 Inputs'!$C$18)^1,12*(1+0.8)^1*'A3 Inputs'!$C$21/'A3 Inputs'!$C$12)*'A3 Inputs'!$C$10/1000000 -> 0.096 | E54: =MIN('A3 Inputs'!$C$17*(1+'A3 Inputs'!$C$18)^2,12*(1+0.8)^2*'A3 Inputs'!$C$21/'A3 Inputs'!$C$12)*'A3 Inputs'!$C$10/1000000 -> 0.1536 | F54: =MIN('A3 Inputs'!$C$17*(1+'A3 Inputs'!$C$18)^3,12*(1+0.8)^3*'A3 Inputs'!$C$21/'A3 Inputs'!$C$12)*'A3 Inputs'!$C$10/1000000 -> 0.24576 | G54: =MIN('A3 Inputs'!$C$17*(1+'A3 Inputs'!$C$18)^4,12*(1+0.8)^4*'A3 Inputs'!$C$21/'A3 Inputs'!$C$12)*'A3 Inputs'!$C$10/1000000 -> 0.393216 | H54: =MIN('A3 Inputs'!$C$17*(1+'A3 Inputs'!$C$18)^5,12*(1+0.8)^5*'A3 Inputs'!$C$21/'A3 Inputs'!$C$12)*'A3 Inputs'!$C$10/1000000 -> 0.6291456
B56: J. Shapiro · Independent work sample · targets labeled [TGT], internal-needed [SPX-IN]

Sheet RAD Model
B1: RADIATOR MASS TAX — first-principles model
B2: Q = e*sigma*A*T^4 (Stefan-Boltzmann). Blue = input. tags: [FACT]/[EST]/[REVEAL]
B4: INPUTS
B5: Emissivity (e) | C5: 0.85 | D5: - | E5: [EST]
B6: Stefan-Boltzmann (sigma) | C6: 5.670374e-08 | D6: W/m2K4 | E6: [FACT]
B7: Radiator areal mass | C7: 7 | D7: kg/m2 | E7: [EST]
B8: Target cluster power | C8: ='Global Assumptions'!$C$8 -> 1000 | D8: MW | E8: [EST]
B9: Launch cost to LEO | C9: ='Global Assumptions'!$C$7 -> 1000 | D9: $/kg | E9: [SPX-IN]
B10: Silicon throttle limit | C10: 358 | D10: K | E10: [EST]
B11: AI1 stated radiator flux | C11: ='Global Assumptions'!$C$13 -> 1400 | D11: W/m2 (2-sided) | E11: [REVEAL]
B13: AI1 BACK-CALCULATION
B14: Implied radiator temp from stated flux | C14: =(C11/(2*C5*C6))^0.25 -> 347.14975 | D14: K
B15: Margin to silicon limit | C15: =C10-C14 -> 10.850254 | D15: K | E15: Headroom before GPUs throttle
B17: TEMPERATURE SWEEP (mass & launch tax for target power)
B18: Radiator temp (K) | C18: Panel flux (W/m2) | D18: Mass (t) | E18: Launch tax ($B)
B19: 300 | C19: =2*C5*C6*B19^4 -> 780.8105 | D19: =(1000000/C19)*C8*C7/1000 -> 8965.0434 | E19: =D19*1000*C9/1000000000 -> 8.9650434
B20: 310 | C20: =2*C5*C6*B20^4 -> 890.24061 | D20: =(1000000/C20)*C8*C7/1000 -> 7863.0428 | E20: =D20*1000*C9/1000000000 -> 7.8630428
B21: 320 | C21: =2*C5*C6*B21^4 -> 1010.7891 | D21: =(1000000/C21)*C8*C7/1000 -> 6925.2826 | E21: =D21*1000*C9/1000000000 -> 6.9252826
B22: 330 | C22: =2*C5*C6*B22^4 -> 1143.1847 | D22: =(1000000/C22)*C8*C7/1000 -> 6123.2453 | E22: =D22*1000*C9/1000000000 -> 6.1232453
B23: 347 | C23: =2*C5*C6*B23^4 -> 1397.5859 | D23: =(1000000/C23)*C8*C7/1000 -> 5008.6365 | E23: =D23*1000*C9/1000000000 -> 5.0086365
B24: 358 | C24: =2*C5*C6*B24^4 -> 1583.4076 | D24: =(1000000/C24)*C8*C7/1000 -> 4420.8452 | E24: =D24*1000*C9/1000000000 -> 4.4208452
B25: 370 | C25: =2*C5*C6*B25^4 -> 1806.6229 | D25: =(1000000/C25)*C8*C7/1000 -> 3874.6325 | E25: =D25*1000*C9/1000000000 -> 3.8746325
B26: 385 | C26: =2*C5*C6*B26^4 -> 2117.8907 | D26: =(1000000/C26)*C8*C7/1000 -> 3305.1753 | E26: =D26*1000*C9/1000000000 -> 3.3051753
B27: 400 | C27: =2*C5*C6*B27^4 -> 2467.7468 | D27: =(1000000/C27)*C8*C7/1000 -> 2836.5958 | E27: =D27*1000*C9/1000000000 -> 2.8365958
B28: 420 | C28: =2*C5*C6*B28^4 -> 2999.5616 | D28: =(1000000/C28)*C8*C7/1000 -> 2333.6743 | E28: =D28*1000*C9/1000000000 -> 2.3336743
B30: Mass swings ~3x across 300-400 K on temperature alone; but the silicon limit (~358 K) floors how hot you can run, so radiator mass is effectively set by GPU junction temp, not free optimization.
B34: J. Shapiro · independent work sample

Sheet Sources
B1: SOURCES
B2: Load-bearing anchors independently verified. Primary = SEC/official; reporting = trade press (verify exact wording).
B4: PRIMARY / OFFICIAL
B5: SpaceX S-1 / S-1A (CIK 1181412, SPCX) | C5: sec.gov/cgi-bin/browse-edgar?action=getcompany&CIK=0001181412&type=S-1
B6: AI1 reveal (June 8 2026) — @SpaceX | C6: x.com/SpaceX/status/2064099405758906727
B7: FCC million-satellite filing (Jan 2026) | C7: fcc.gov/ecfs (search SpaceX "orbital data center")
B8: PUBLIC ANCHORS (verified)
B9: McCalip/Varda ~3.2x ($51.1B vs $15.9B, infra-only ~$15/W basis) | C9: andrewmccalip.com/space-datacenters
B10: Epoch AI — $38/W, $8.5B/yr TCO, servers 60%, 8.34c/kWh | C10: epoch.ai/data-insights/ai-datacenter-cost-breakdown
B11: NVIDIA GB200 NVL72 — 130 TB/s aggregate (1.8 TB/s/GPU) | C11: nvidia.com/en-us/data-center/gb200-nvl72/
B12: MFU — PaLM 540B 46.2% | C12: arxiv.org/abs/2204.02311
B13: MFU — Llama 3 405B 38-43% | C13: arxiv.org/abs/2407.21783
B14: NVIDIA H100 datasheet (989 TFLOP FP16 dense) | C14: nvidia.com/en-us/data-center/h100/
B15: Starlink dish cost-down ($3,000->$1,500 BOM; 15,000/day) | C15: nextbigfuture.com / tesmanian (Shotwell figures)
B16: Quilty per-sat ($200k V1 -> $800k V2-mini -> $1.2M V3) | C16: spacenews.com (Quilty Space analysis)
